Workbook

Sheet Core
A1: Personal Info | E1: Combat Info | L1: Clim Total Available
A2: Name | C2: Race | E2: HP | F2: =20+(10*B12)+H7 -> 70 | G2: Evasion | H2: =7+B11+E33+SUMIF($L$37:$L$42,TRUE,$H$37:$H$42) -> 11 | I2: Dodge | K2: =20+B11+H33+SUMIF($L$37:$L$42,TRUE,$I$37:$I$42) -> 24 | L2: ='EXP & Transactions'!G2 -> 4000
A3: Gender | C3: Sub-Race | House | E3: Mana | F3: =ROUNDDOWN(6+(B10)+(K34),0) -> 10 | G3: Guard | H3: =ROUNDDOWN(B12+K4,0) -> 5 | I3: Block | K3: =(B12*2)+SUMIF($L$37:$L$42,TRUE,$J$37:$J$42) -> 10
A4: Age | C4: Exp | D4: ='EXP & Transactions'!D2 - SUM(D7,D15:D35) -> 1000 | E4: Initiative | F4: =B11+H35-SUMIF($L$37:$L$42,TRUE,$K$37:$K$42) -> 4 | G4: Save Bonus | H4: =B12+G34 -> 5 | I4: Equipment Guard Value | K4: =SUMIF($L$37:$L$42,TRUE,$G$37:$G$42) -> 0
A5: Height | C5: Spirit Core | D5: =D4 + D7 + SUM(D15:D35) -> 1000 | E5: Light Damage | F5: =D37 | G5: Potency | H5: =11+B9 -> 14 | I5: Equipment Block Value | K5: =SUMIF($L$37:$L$42,TRUE,$J$37:$J$42) -> 0
A6: Weight | C6: 6/14/2026 | D6: 6/14/2026 | E6: Heavy Damage | F6: =E37 | G6: Speed | H6: 20 | I6: Equipment Penalty | K6: =SUMIF($L$37:$L$42,TRUE,$H$37:$H$42) -> 0
A7: Worships | B7: RNGesus | C7: Breakthrough | D7: =SUM(Breakthrough!B2:B58) -> 0 | E7: RP | F7: =IF(K30, 2 + (B11 - K6), 2 + B11)-E35 -> 6 | G7: HP Bonus | H7: 0 | I7: Combat Burden | K7: =Inventory!H32 -> 0
A8: Main Stats | C8: Sub-Stats | E8: Skill | F8: Stat | G8: Bonus | H8: Skill Points | I8: Expertise | K8: Proficiencies | M8: Crafting Skill | N8: Total Bonus | O8: Skill Points | P8: Equipment Bonus
A9: Focus | B9: =IFS(B45 = A9, A45, B46 = A9, A46, B47 = A9, A47, B48 = A9, A48)+F45 -> 3 | C9: Fitness | D9: =IFS(D45 = C9, C45, D46 = C9, C46, D47 = C9, C47, D48 = C9, C48, D49 = C9, C49)+H45 -> 5 | E9: Athletics | F9: Fitness | G9: =D9+H9 -> 5 | H9: 0 | K9: Armor | N9: =O9+P9 -> 0 | O9: 0
A10: Power | B10: =IFS(B45 = A10, A45, B46 = A10, A46, B47 = A10, A47, B48 = A10, A48)+F46 -> 4 | C10: Cunning | D10: =IFS(D45 = C10, C45, D46 = C10, C46, D47 = C10, C47, D48 = C10, C48, D49 = C10, C49)+H46 -> 4 | E10: Riding | F10: Fitness | G10: =D9+H10 -> 5 | H10: 0 | K10: Language | N10: =O10+P10 -> 0 | O10: 0
A11: Agility | B11: =IFS(B45 = A11, A45, B46 = A11, A46, B47 = A11, A47, B48 = A11, A48)+F47-P34+O34 -> 4 | C11: Reason | D11: =IFS(D45 = C11, C45, D46 = C11, C46, D47 = C11, C47, D48 = C11, C48, D49 = C11, C49)+H47 -> 3 | E11: Stealth | F11: Cunning | G11: =D10+H11 -> 4 | H11: 0 | K11: Weapons | N11: =O11+P11 -> 0 | O11: 0
A12: Toughness | B12: =IFS(B45 = A12, A45, B46 = A12, A46, B47 = A12, A47, B48 = A12, A48)+F48-N34+M34 -> 5 | C12: Awareness | D12: =IFS(D45 = C12, C45, D46 = C12, C46, D47 = C12, C47, D48 = C12, C48,D49 = C12, C49)+H48 -> 2 | E12: Deception | F12: Cunning | G12: =D10+H12 -> 4 | H12: 0 | K12: Elemental Mastery | N12: =O12+P12 -> 0 | O12: 0
C13: Presence | D13: =IFS(D45 = C13, C45, D46 = C13, C46, D47 = C13, C47, D48 = C13, C48,D49 = C13, C49)+H49 -> 1 | E13: Roguecraft | F13: Cunning | G13: =D10+H13 -> 4 | H13: 0 | N13: =O13+P13 -> 0 | O13: 0
A14: Class | B14: Class Tier | C14: Class Level | D14: Cost (EXP) | E14: Medicine | F14: Reason | G14: =D11+H14 -> 3 | H14: 0 | N14: =O14+P14 -> 0 | O14: 0
B15: =IFERROR(__xludf.DUMMYFUNCTION("IFERROR(INDEX(IMPORTRANGE(""https://docs.google.com/spreadsheets/d/1xgDM68xiM34Lb7pPa9X0VaOqdhswjHKkl6KIk-vu_2Q/edit?gid=0#gid=0"",""Classes!C2:C""),MATCH(A15,IMPORTRANGE(""https://docs.google.com/spreadsheets/d/1xgDM68xiM34Lb7pPa9X0VaOqdhswjHKkl6KIk-vu_2"&"Q/edit?gid=0#gid=0"",""Classes!B2:B""),0)),"""")"),"") | D15: 0 | E15: Common Knowledge | F15: Reason | G15: =D11+H15 -> 3 | H15: 0 | N15: =O15+P15 -> 0 | O15: 0
B16: =IFERROR(__xludf.DUMMYFUNCTION("IFERROR(INDEX(IMPORTRANGE(""https://docs.google.com/spreadsheets/d/1xgDM68xiM34Lb7pPa9X0VaOqdhswjHKkl6KIk-vu_2Q/edit?gid=0#gid=0"",""Classes!C2:C""),MATCH(A16,IMPORTRANGE(""https://docs.google.com/spreadsheets/d/1xgDM68xiM34Lb7pPa9X0VaOqdhswjHKkl6KIk-vu_2"&"Q/edit?gid=0#gid=0"",""Classes!B2:B""),0)),"""")"),"") | D16: 0 | E16: Linguistics | F16: Reason | G16: =D11+H16 -> 3 | H16: 0 | N16: =O16+P16 -> 0 | O16: 0
B17: =IFERROR(__xludf.DUMMYFUNCTION("IFERROR(INDEX(IMPORTRANGE(""https://docs.google.com/spreadsheets/d/1xgDM68xiM34Lb7pPa9X0VaOqdhswjHKkl6KIk-vu_2Q/edit?gid=0#gid=0"",""Classes!C2:C""),MATCH(A17,IMPORTRANGE(""https://docs.google.com/spreadsheets/d/1xgDM68xiM34Lb7pPa9X0VaOqdhswjHKkl6KIk-vu_2"&"Q/edit?gid=0#gid=0"",""Classes!B2:B""),0)),"""")"),"") | D17: 0 | E17: Magic | F17: Reason | G17: =D11+H17 -> 3 | H17: 0 | N17: =O17+P17 -> 0 | O17: 0
B18: =IFERROR(__xludf.DUMMYFUNCTION("IFERROR(INDEX(IMPORTRANGE(""https://docs.google.com/spreadsheets/d/1xgDM68xiM34Lb7pPa9X0VaOqdhswjHKkl6KIk-vu_2Q/edit?gid=0#gid=0"",""Classes!C2:C""),MATCH(A18,IMPORTRANGE(""https://docs.google.com/spreadsheets/d/1xgDM68xiM34Lb7pPa9X0VaOqdhswjHKkl6KIk-vu_2"&"Q/edit?gid=0#gid=0"",""Classes!B2:B""),0)),"""")"),"") | D18: 0 | E18: Religion | F18: Reason | G18: =D11+H18 -> 3 | H18: 0 | N18: =O18+P18 -> 0 | O18: 0
B19: =IFERROR(__xludf.DUMMYFUNCTION("IFERROR(INDEX(IMPORTRANGE(""https://docs.google.com/spreadsheets/d/1xgDM68xiM34Lb7pPa9X0VaOqdhswjHKkl6KIk-vu_2Q/edit?gid=0#gid=0"",""Classes!C2:C""),MATCH(A19,IMPORTRANGE(""https://docs.google.com/spreadsheets/d/1xgDM68xiM34Lb7pPa9X0VaOqdhswjHKkl6KIk-vu_2"&"Q/edit?gid=0#gid=0"",""Classes!B2:B""),0)),"""")"),"") | D19: 0 | E19: Appraise | F19: Reason | G19: =D11+H19 -> 3 | H19: 0 | N19: =O19+P19 -> 0 | O19: 0
B20: =IFERROR(__xludf.DUMMYFUNCTION("IFERROR(INDEX(IMPORTRANGE(""https://docs.google.com/spreadsheets/d/1xgDM68xiM34Lb7pPa9X0VaOqdhswjHKkl6KIk-vu_2Q/edit?gid=0#gid=0"",""Classes!C2:C""),MATCH(A20,IMPORTRANGE(""https://docs.google.com/spreadsheets/d/1xgDM68xiM34Lb7pPa9X0VaOqdhswjHKkl6KIk-vu_2"&"Q/edit?gid=0#gid=0"",""Classes!B2:B""),0)),"""")"),"") | D20: 0 | E20: History | F20: Reason | G20: =D11+H20 -> 3 | H20: 0 | N20: =O20+P20 -> 0 | O20: 0
B21: =IFERROR(__xludf.DUMMYFUNCTION("IFERROR(INDEX(IMPORTRANGE(""https://docs.google.com/spreadsheets/d/1xgDM68xiM34Lb7pPa9X0VaOqdhswjHKkl6KIk-vu_2Q/edit?gid=0#gid=0"",""Classes!C2:C""),MATCH(A21,IMPORTRANGE(""https://docs.google.com/spreadsheets/d/1xgDM68xiM34Lb7pPa9X0VaOqdhswjHKkl6KIk-vu_2"&"Q/edit?gid=0#gid=0"",""Classes!B2:B""),0)),"""")"),"") | D21: 0 | E21: Flight | F21: Reason | G21: =D11+H21 -> 3 | H21: 0 | N21: =O21+P21 -> 0 | O21: 0
B22: =IFERROR(__xludf.DUMMYFUNCTION("IFERROR(INDEX(IMPORTRANGE(""https://docs.google.com/spreadsheets/d/1xgDM68xiM34Lb7pPa9X0VaOqdhswjHKkl6KIk-vu_2Q/edit?gid=0#gid=0"",""Classes!C2:C""),MATCH(A22,IMPORTRANGE(""https://docs.google.com/spreadsheets/d/1xgDM68xiM34Lb7pPa9X0VaOqdhswjHKkl6KIk-vu_2"&"Q/edit?gid=0#gid=0"",""Classes!B2:B""),0)),"""")"),"") | D22: 0 | E22: Artifice | F22: Reason | G22: =D11+H22 -> 3 | H22: 0 | N22: =O22+P22 -> 0 | O22: 0
B23: =IFERROR(__xludf.DUMMYFUNCTION("IFERROR(INDEX(IMPORTRANGE(""https://docs.google.com/spreadsheets/d/1xgDM68xiM34Lb7pPa9X0VaOqdhswjHKkl6KIk-vu_2Q/edit?gid=0#gid=0"",""Classes!C2:C""),MATCH(A23,IMPORTRANGE(""https://docs.google.com/spreadsheets/d/1xgDM68xiM34Lb7pPa9X0VaOqdhswjHKkl6KIk-vu_2"&"Q/edit?gid=0#gid=0"",""Classes!B2:B""),0)),"""")"),"") | D23: 0 | E23: Perception | F23: Awareness | G23: =D12+H23 -> 2 | H23: 0 | N23: =O23+P23 -> 0 | O23: 0
B24: =IFERROR(__xludf.DUMMYFUNCTION("IFERROR(INDEX(IMPORTRANGE(""https://docs.google.com/spreadsheets/d/1xgDM68xiM34Lb7pPa9X0VaOqdhswjHKkl6KIk-vu_2Q/edit?gid=0#gid=0"",""Classes!C2:C""),MATCH(A24,IMPORTRANGE(""https://docs.google.com/spreadsheets/d/1xgDM68xiM34Lb7pPa9X0VaOqdhswjHKkl6KIk-vu_2"&"Q/edit?gid=0#gid=0"",""Classes!B2:B""),0)),"""")"),"") | D24: 0 | E24: Insight | F24: Awareness | G24: =D12+H24 -> 2 | H24: 0 | N24: =O24+P24 -> 0 | O24: 0
B25: =IFERROR(__xludf.DUMMYFUNCTION("IFERROR(INDEX(IMPORTRANGE(""https://docs.google.com/spreadsheets/d/1xgDM68xiM34Lb7pPa9X0VaOqdhswjHKkl6KIk-vu_2Q/edit?gid=0#gid=0"",""Classes!C2:C""),MATCH(A25,IMPORTRANGE(""https://docs.google.com/spreadsheets/d/1xgDM68xiM34Lb7pPa9X0VaOqdhswjHKkl6KIk-vu_2"&"Q/edit?gid=0#gid=0"",""Classes!B2:B""),0)),"""")"),"") | D25: 0 | E25: Survival | F25: Awareness | G25: =D12+H25 -> 2 | H25: 0 | N25: =O25+P25 -> 0 | O25: 0
B26: =IFERROR(__xludf.DUMMYFUNCTION("IFERROR(INDEX(IMPORTRANGE(""https://docs.google.com/spreadsheets/d/1xgDM68xiM34Lb7pPa9X0VaOqdhswjHKkl6KIk-vu_2Q/edit?gid=0#gid=0"",""Classes!C2:C""),MATCH(A26,IMPORTRANGE(""https://docs.google.com/spreadsheets/d/1xgDM68xiM34Lb7pPa9X0VaOqdhswjHKkl6KIk-vu_2"&"Q/edit?gid=0#gid=0"",""Classes!B2:B""),0)),"""")"),"") | D26: 0 | E26: Animal Husbandry | F26: Awareness | G26: =D12+H26 -> 2 | H26: 0 | N26: =O26+P26 -> 0 | O26: 0
B27: =IFERROR(__xludf.DUMMYFUNCTION("IFERROR(INDEX(IMPORTRANGE(""https://docs.google.com/spreadsheets/d/1xgDM68xiM34Lb7pPa9X0VaOqdhswjHKkl6KIk-vu_2Q/edit?gid=0#gid=0"",""Classes!C2:C""),MATCH(A27,IMPORTRANGE(""https://docs.google.com/spreadsheets/d/1xgDM68xiM34Lb7pPa9X0VaOqdhswjHKkl6KIk-vu_2"&"Q/edit?gid=0#gid=0"",""Classes!B2:B""),0)),"""")"),"") | D27: 0 | E27: Art | F27: Presence | G27: =D13+H27 -> 1 | H27: 0 | N27: =O27+P27 -> 0 | O27: 0
B28: =IFERROR(__xludf.DUMMYFUNCTION("IFERROR(INDEX(IMPORTRANGE(""https://docs.google.com/spreadsheets/d/1xgDM68xiM34Lb7pPa9X0VaOqdhswjHKkl6KIk-vu_2Q/edit?gid=0#gid=0"",""Classes!C2:C""),MATCH(A28,IMPORTRANGE(""https://docs.google.com/spreadsheets/d/1xgDM68xiM34Lb7pPa9X0VaOqdhswjHKkl6KIk-vu_2"&"Q/edit?gid=0#gid=0"",""Classes!B2:B""),0)),"""")"),"") | D28: 0 | E28: Negotiation | F28: Presence | G28: =D13+H28 -> 1 | H28: 0 | N28: =O28+P28 -> 0 | O28: 0
B29: =IFERROR(__xludf.DUMMYFUNCTION("IFERROR(INDEX(IMPORTRANGE(""https://docs.google.com/spreadsheets/d/1xgDM68xiM34Lb7pPa9X0VaOqdhswjHKkl6KIk-vu_2Q/edit?gid=0#gid=0"",""Classes!C2:C""),MATCH(A29,IMPORTRANGE(""https://docs.google.com/spreadsheets/d/1xgDM68xiM34Lb7pPa9X0VaOqdhswjHKkl6KIk-vu_2"&"Q/edit?gid=0#gid=0"",""Classes!B2:B""),0)),"""")"),"") | D29: 0 | E29: Intimidation | F29: Presence | G29: =D13+H29 -> 1 | H29: 0 | K29: Check Box if Old Armor Calc | N29: =O29+P29 -> 0 | O29: 0
B30: =IFERROR(__xludf.DUMMYFUNCTION("IFERROR(INDEX(IMPORTRANGE(""https://docs.google.com/spreadsheets/d/1xgDM68xiM34Lb7pPa9X0VaOqdhswjHKkl6KIk-vu_2Q/edit?gid=0#gid=0"",""Classes!C2:C""),MATCH(A30,IMPORTRANGE(""https://docs.google.com/spreadsheets/d/1xgDM68xiM34Lb7pPa9X0VaOqdhswjHKkl6KIk-vu_2"&"Q/edit?gid=0#gid=0"",""Classes!B2:B""),0)),"""")"),"") | D30: 0 | K30: FALSE | N30: =O30+P30 -> 0 | O30: 0
B31: =IFERROR(__xludf.DUMMYFUNCTION("IFERROR(INDEX(IMPORTRANGE(""https://docs.google.com/spreadsheets/d/1xgDM68xiM34Lb7pPa9X0VaOqdhswjHKkl6KIk-vu_2Q/edit?gid=0#gid=0"",""Classes!C2:C""),MATCH(A31,IMPORTRANGE(""https://docs.google.com/spreadsheets/d/1xgDM68xiM34Lb7pPa9X0VaOqdhswjHKkl6KIk-vu_2"&"Q/edit?gid=0#gid=0"",""Classes!B2:B""),0)),"""")"),"") | D31: 0
B32: =IFERROR(__xludf.DUMMYFUNCTION("IFERROR(INDEX(IMPORTRANGE(""https://docs.google.com/spreadsheets/d/1xgDM68xiM34Lb7pPa9X0VaOqdhswjHKkl6KIk-vu_2Q/edit?gid=0#gid=0"",""Classes!C2:C""),MATCH(A32,IMPORTRANGE(""https://docs.google.com/spreadsheets/d/1xgDM68xiM34Lb7pPa9X0VaOqdhswjHKkl6KIk-vu_2"&"Q/edit?gid=0#gid=0"",""Classes!B2:B""),0)),"""")"),"") | D32: 0 | E32: Evasion Bonus | G32: Bonus Save Value | H32: Dodge Bonus | K32: Mana Adjustments | M32: Toughness Adjustments | O32: Agility Adjustments (Racial Ability)
B33: =IFERROR(__xludf.DUMMYFUNCTION("IFERROR(INDEX(IMPORTRANGE(""https://docs.google.com/spreadsheets/d/1xgDM68xiM34Lb7pPa9X0VaOqdhswjHKkl6KIk-vu_2Q/edit?gid=0#gid=0"",""Classes!C2:C""),MATCH(A33,IMPORTRANGE(""https://docs.google.com/spreadsheets/d/1xgDM68xiM34Lb7pPa9X0VaOqdhswjHKkl6KIk-vu_2"&"Q/edit?gid=0#gid=0"",""Classes!B2:B""),0)),"""")"),"") | D33: 0 | E33: 0 | H33: 0 | K33: Add - for Negative | M33: Positive | N33: Negative | O33: Positive | P33: Negative
B34: =IFERROR(__xludf.DUMMYFUNCTION("IFERROR(INDEX(IMPORTRANGE(""https://docs.google.com/spreadsheets/d/1xgDM68xiM34Lb7pPa9X0VaOqdhswjHKkl6KIk-vu_2Q/edit?gid=0#gid=0"",""Classes!C2:C""),MATCH(A34,IMPORTRANGE(""https://docs.google.com/spreadsheets/d/1xgDM68xiM34Lb7pPa9X0VaOqdhswjHKkl6KIk-vu_2"&"Q/edit?gid=0#gid=0"",""Classes!B2:B""),0)),"""")"),"") | D34: 0 | E34: RP Adjustment (Negative) | G34: 0 | H34: Initiative Adjustment (- for negative) | K34: 0 | M34: 0 | N34: 0 | O34: 0 | P34: 0
B35: =IFERROR(__xludf.DUMMYFUNCTION("IFERROR(INDEX(IMPORTRANGE(""https://docs.google.com/spreadsheets/d/1xgDM68xiM34Lb7pPa9X0VaOqdhswjHKkl6KIk-vu_2Q/edit?gid=0#gid=0"",""Classes!C2:C""),MATCH(A35,IMPORTRANGE(""https://docs.google.com/spreadsheets/d/1xgDM68xiM34Lb7pPa9X0VaOqdhswjHKkl6KIk-vu_2"&"Q/edit?gid=0#gid=0"",""Classes!B2:B""),0)),"""")"),"") | D35: 0 | E35: 0 | H35: 0 | M35: Injuries
A36: Weapon | B36: Light/Heavy Attack | C36: Precise Attack | D36: Light Damage | E36: Heavy Damage | F36: Equipment | G36: Guard (Passive) Bonus | H36: Evasion - for negative | I36: Dodge - for negative | J36: Block (Active) Bonus | K36: Initiative Penalty (Positive Number) | L36: Armor Equipped?
B37: =B9 -> 3 | C37: =B9*2 -> 6 | L37: FALSE
B38: =B9 -> 3 | C38: =B9*2 -> 6 | L38: FALSE | M38: Main Hand | N38: FALSE | O38: Head | P38: FALSE
B39: =B9 -> 3 | C39: =B9*2 -> 6 | L39: FALSE | M39: Muscle | N39: FALSE | O39: Wound | P39: FALSE
B40: =B9 -> 3 | C40: =B9*2 -> 6 | L40: FALSE | M40: Spirit Circuit | N40: FALSE | O40: Eye | P40: FALSE
B41: =B9 -> 3 | C41: =B9*2 -> 6 | L41: FALSE | M41: Off Hand | N41: FALSE | O41: Laceration | P41: FALSE
B42: =B9 -> 3 | C42: =B9*2 -> 6 | L42: FALSE | M42: Leg | N42: FALSE | O42: Foot | P42: FALSE
A43: Character Creation Array | J43: USE AURASENSE TO CHECK FOR GRUNTS AND HEROICS. IF YOU HAVE STATUS ASSESSMENT THEN USE THAT AS WELL, BOTH OF THESE ACTIONS ARE FREE. ASK ABOUT THEIR WEAPONS AND ARMOR (Status assessment is a quick action, so if a character uses another quick action it will up the cost of the next quick action.)
A44: Main Stat Array | B44: Stat Choice | C44: Sub-Stat Array | D44: Sub-stat Choice | E44: Main Stat Bonuses (Racials and Classes) | G44: Sub Stat Bonuses (Racials and Classes)
A45: 5 | B45: Toughness | C45: 5 | D45: Fitness | E45: Focus | F45: 0 | G45: Fitness | H45: 0
A46: 4 | B46: Power | C46: 4 | D46: Cunning | E46: Power | F46: 0 | G46: Cunning | H46: 0
A47: 4 | B47: Agility | C47: 3 | D47: Reason | E47: Agility | F47: 0 | G47: Reason | H47: 0
A48: 3 | B48: Focus | C48: 2 | D48: Awareness | E48: Toughness | F48: 0 | G48: Awareness | H48: 0
A49: Check Box if Pure Human --> | B49: 0 | C49: 1 | D49: Presence | G49: Presence | H49: 0
A50: Check Box if Slow Starter --> | B50: 0
A51: Starter Skill points | B51: Starter Skill Points Spent | C51: Starter Interlude points = 3 | E51: Skill Points Gained (List Bonus and Skill)
A52: 10 | C52: Choose What Starter IP Was Spent On Below
A54: Starting Clim
A55: =SUM('EXP & Transactions'!F2) -> 4000
A57: Mirane?
A58: TRUE

Sheet Abilities
A1: Active Ability Name | B1: Cost | C1: Keywords | D1: Range | E1: Requirement | F1: Description | G1: Benefits
B2: {=IF(A2="", "", IFERROR(INDEX('All Abilities'!H:H, MATCH(A2, 'All Abilities'!B:B, 0)), ""))} | C2: {=IF(A2="", "", IFERROR(INDEX('All Abilities'!D:D, MATCH(A2, 'All Abilities'!B:B, 0)), ""))} | D2: {=IF(A2="", "", IFERROR(INDEX('All Abilities'!E:E, MATCH(A2, 'All Abilities'!B:B, 0)), ""))} | E2: {=IF(A2="", "", IFERROR(INDEX('All Abilities'!G:G, MATCH(A2, 'All Abilities'!B:B, 0)), ""))} | F2: {=IF(A2="", "", IFERROR(INDEX('All Abilities'!F:F, MATCH(A2, 'All Abilities'!B:B, 0)), ""))} | G2: {=IF(A2="", "", IFERROR(INDEX('All Abilities'!L:L, MATCH(A2, 'All Abilities'!B:B, 0)), ""))}
B3: {=IF(A3="", "", IFERROR(INDEX('All Abilities'!H:H, MATCH(A3, 'All Abilities'!B:B, 0)), ""))} | C3: {=IF(A3="", "", IFERROR(INDEX('All Abilities'!D:D, MATCH(A3, 'All Abilities'!B:B, 0)), ""))} | D3: {=IF(A3="", "", IFERROR(INDEX('All Abilities'!E:E, MATCH(A3, 'All Abilities'!B:B, 0)), ""))} | E3: {=IF(A3="", "", IFERROR(INDEX('All Abilities'!G:G, MATCH(A3, 'All Abilities'!B:B, 0)), ""))} | F3: {=IF(A3="", "", IFERROR(INDEX('All Abilities'!F:F, MATCH(A3, 'All Abilities'!B:B, 0)), ""))} | G3: {=IF(A3="", "", IFERROR(INDEX('All Abilities'!L:L, MATCH(A3, 'All Abilities'!B:B, 0)), ""))}
B4: {=IF(A4="", "", IFERROR(INDEX('All Abilities'!H:H, MATCH(A4, 'All Abilities'!B:B, 0)), ""))} | C4: {=IF(A4="", "", IFERROR(INDEX('All Abilities'!D:D, MATCH(A4, 'All Abilities'!B:B, 0)), ""))} | D4: {=IF(A4="", "", IFERROR(INDEX('All Abilities'!E:E, MATCH(A4, 'All Abilities'!B:B, 0)), ""))} | E4: {=IF(A4="", "", IFERROR(INDEX('All Abilities'!G:G, MATCH(A4, 'All Abilities'!B:B, 0)), ""))} | F4: {=IF(A4="", "", IFERROR(INDEX('All Abilities'!F:F, MATCH(A4, 'All Abilities'!B:B, 0)), ""))} | G4: {=IF(A4="", "", IFERROR(INDEX('All Abilities'!L:L, MATCH(A4, 'All Abilities'!B:B, 0)), ""))}
B5: {=IF(A5="", "", IFERROR(INDEX('All Abilities'!H:H, MATCH(A5, 'All Abilities'!B:B, 0)), ""))} | C5: {=IF(A5="", "", IFERROR(INDEX('All Abilities'!D:D, MATCH(A5, 'All Abilities'!B:B, 0)), ""))} | D5: {=IF(A5="", "", IFERROR(INDEX('All Abilities'!E:E, MATCH(A5, 'All Abilities'!B:B, 0)), ""))} | E5: {=IF(A5="", "", IFERROR(INDEX('All Abilities'!G:G, MATCH(A5, 'All Abilities'!B:B, 0)), ""))} | F5: {=IF(A5="", "", IFERROR(INDEX('All Abilities'!F:F, MATCH(A5, 'All Abilities'!B:B, 0)), ""))} | G5: {=IF(A5="", "", IFERROR(INDEX('All Abilities'!L:L, MATCH(A5, 'All Abilities'!B:B, 0)), ""))}
B6: {=IF(A6="", "", IFERROR(INDEX('All Abilities'!H:H, MATCH(A6, 'All Abilities'!B:B, 0)), ""))} | C6: {=IF(A6="", "", IFERROR(INDEX('All Abilities'!D:D, MATCH(A6, 'All Abilities'!B:B, 0)), ""))} | D6: {=IF(A6="", "", IFERROR(INDEX('All Abilities'!E:E, MATCH(A6, 'All Abilities'!B:B, 0)), ""))} | E6: {=IF(A6="", "", IFERROR(INDEX('All Abilities'!G:G, MATCH(A6, 'All Abilities'!B:B, 0)), ""))} | F6: {=IF(A6="", "", IFERROR(INDEX('All Abilities'!F:F, MATCH(A6, 'All Abilities'!B:B, 0)), ""))} | G6: {=IF(A6="", "", IFERROR(INDEX('All Abilities'!L:L, MATCH(A6, 'All Abilities'!B:B, 0)), ""))}
B7: {=IF(A7="", "", IFERROR(INDEX('All Abilities'!H:H, MATCH(A7, 'All Abilities'!B:B, 0)), ""))} | C7: {=IF(A7="", "", IFERROR(INDEX('All Abilities'!D:D, MATCH(A7, 'All Abilities'!B:B, 0)), ""))} | D7: {=IF(A7="", "", IFERROR(INDEX('All Abilities'!E:E, MATCH(A7, 'All Abilities'!B:B, 0)), ""))} | E7: {=IF(A7="", "", IFERROR(INDEX('All Abilities'!G:G, MATCH(A7, 'All Abilities'!B:B, 0)), ""))} | F7: {=IF(A7="", "", IFERROR(INDEX('All Abilities'!F:F, MATCH(A7, 'All Abilities'!B:B, 0)), ""))} | G7: {=IF(A7="", "", IFERROR(INDEX('All Abilities'!L:L, MATCH(A7, 'All Abilities'!B:B, 0)), ""))}
B8: {=IF(A8="", "", IFERROR(INDEX('All Abilities'!H:H, MATCH(A8, 'All Abilities'!B:B, 0)), ""))} | C8: {=IF(A8="", "", IFERROR(INDEX('All Abilities'!D:D, MATCH(A8, 'All Abilities'!B:B, 0)), ""))} | D8: {=IF(A8="", "", IFERROR(INDEX('All Abilities'!E:E, MATCH(A8, 'All Abilities'!B:B, 0)), ""))} | E8: {=IF(A8="", "", IFERROR(INDEX('All Abilities'!G:G, MATCH(A8, 'All Abilities'!B:B, 0)), ""))} | F8: {=IF(A8="", "", IFERROR(INDEX('All Abilities'!F:F, MATCH(A8, 'All Abilities'!B:B, 0)), ""))} | G8: {=IF(A8="", "", IFERROR(INDEX('All Abilities'!L:L, MATCH(A8, 'All Abilities'!B:B, 0)), ""))}
B9: {=IF(A9="", "", IFERROR(INDEX('All Abilities'!H:H, MATCH(A9, 'All Abilities'!B:B, 0)), ""))} | C9: {=IF(A9="", "", IFERROR(INDEX('All Abilities'!D:D, MATCH(A9, 'All Abilities'!B:B, 0)), ""))} | D9: {=IF(A9="", "", IFERROR(INDEX('All Abilities'!E:E, MATCH(A9, 'All Abilities'!B:B, 0)), ""))} | E9: {=IF(A9="", "", IFERROR(INDEX('All Abilities'!G:G, MATCH(A9, 'All Abilities'!B:B, 0)), ""))} | F9: {=IF(A9="", "", IFERROR(INDEX('All Abilities'!F:F, MATCH(A9, 'All Abilities'!B:B, 0)), ""))} | G9: {=IF(A9="", "", IFERROR(INDEX('All Abilities'!L:L, MATCH(A9, 'All Abilities'!B:B, 0)), ""))}
B10: {=IF(A10="", "", IFERROR(INDEX('All Abilities'!H:H, MATCH(A10, 'All Abilities'!B:B, 0)), ""))} | C10: {=IF(A10="", "", IFERROR(INDEX('All Abilities'!D:D, MATCH(A10, 'All Abilities'!B:B, 0)), ""))} | D10: {=IF(A10="", "", IFERROR(INDEX('All Abilities'!E:E, MATCH(A10, 'All Abilities'!B:B, 0)), ""))} | E10: {=IF(A10="", "", IFERROR(INDEX('All Abilities'!G:G, MATCH(A10, 'All Abilities'!B:B, 0)), ""))} | F10: {=IF(A10="", "", IFERROR(INDEX('All Abilities'!F:F, MATCH(A10, 'All Abilities'!B:B, 0)), ""))} | G10: {=IF(A10="", "", IFERROR(INDEX('All Abilities'!L:L, MATCH(A10, 'All Abilities'!B:B, 0)), ""))}
B11: {=IF(A11="", "", IFERROR(INDEX('All Abilities'!H:H, MATCH(A11, 'All Abilities'!B:B, 0)), ""))} | C11: {=IF(A11="", "", IFERROR(INDEX('All Abilities'!D:D, MATCH(A11, 'All Abilities'!B:B, 0)), ""))} | D11: {=IF(A11="", "", IFERROR(INDEX('All Abilities'!E:E, MATCH(A11, 'All Abilities'!B:B, 0)), ""))} | E11: {=IF(A11="", "", IFERROR(INDEX('All Abilities'!G:G, MATCH(A11, 'All Abilities'!B:B, 0)), ""))} | F11: {=IF(A11="", "", IFERROR(INDEX('All Abilities'!F:F, MATCH(A11, 'All Abilities'!B:B, 0)), ""))} | G11: {=IF(A11="", "", IFERROR(INDEX('All Abilities'!L:L, MATCH(A11, 'All Abilities'!B:B, 0)), ""))}
B12: {=IF(A12="", "", IFERROR(INDEX('All Abilities'!H:H, MATCH(A12, 'All Abilities'!B:B, 0)), ""))} | C12: {=IF(A12="", "", IFERROR(INDEX('All Abilities'!D:D, MATCH(A12, 'All Abilities'!B:B, 0)), ""))} | D12: {=IF(A12="", "", IFERROR(INDEX('All Abilities'!E:E, MATCH(A12, 'All Abilities'!B:B, 0)), ""))} | E12: {=IF(A12="", "", IFERROR(INDEX('All Abilities'!G:G, MATCH(A12, 'All Abilities'!B:B, 0)), ""))} | F12: {=IF(A12="", "", IFERROR(INDEX('All Abilities'!F:F, MATCH(A12, 'All Abilities'!B:B, 0)), ""))} | G12: {=IF(A12="", "", IFERROR(INDEX('All Abilities'!L:L, MATCH(A12, 'All Abilities'!B:B, 0)), ""))}
B13: {=IF(A13="", "", IFERROR(INDEX('All Abilities'!H:H, MATCH(A13, 'All Abilities'!B:B, 0)), ""))} | C13: {=IF(A13="", "", IFERROR(INDEX('All Abilities'!D:D, MATCH(A13, 'All Abilities'!B:B, 0)), ""))} | D13: {=IF(A13="", "", IFERROR(INDEX('All Abilities'!E:E, MATCH(A13, 'All Abilities'!B:B, 0)), ""))} | E13: {=IF(A13="", "", IFERROR(INDEX('All Abilities'!G:G, MATCH(A13, 'All Abilities'!B:B, 0)), ""))} | F13: {=IF(A13="", "", IFERROR(INDEX('All Abilities'!F:F, MATCH(A13, 'All Abilities'!B:B, 0)), ""))} | G13: {=IF(A13="", "", IFERROR(INDEX('All Abilities'!L:L, MATCH(A13, 'All Abilities'!B:B, 0)), ""))}
... B58: {=IF(A58="", "", IFERROR(INDEX('All Abilities'!H:H, MATCH(A58, 'All Abilities'!B:B, 0)), ""))} | C58: {=IF(A58="", "", IFERROR(INDEX('All Abilities'!D:D, MATCH(A58, 'All Abilities'!B:B, 0)), ""))} | D58: {=IF(A58="", "", IFERROR(INDEX('All Abilities'!E:E, MATCH(A58, 'All Abilities'!B:B, 0)), ""))} | E58: {=IF(A58="", "", IFERROR(INDEX('All Abilities'!G:G, MATCH(A58, 'All Abilities'!B:B, 0)), ""))} | F58: {=IF(A58="", "", IFERROR(INDEX('All Abilities'!F:F, MATCH(A58, 'All Abilities'!B:B, 0)), ""))} | G58: {=IF(A58="", "", IFERROR(INDEX('All Abilities'!L:L, MATCH(A58, 'All Abilities'!B:B, 0)), ""))}
A59: Passive Ability Name | B59: Cost | C59: Keywords | D59: Range | E59: Requirement | F59: Description | G59: Benefits
B60: {=IF(A60="", "", IFERROR(INDEX('All Abilities'!H:H, MATCH(A60, 'All Abilities'!B:B, 0)), ""))} | C60: {=IF(A60="", "", IFERROR(INDEX('All Abilities'!D:D, MATCH(A60, 'All Abilities'!B:B, 0)), ""))} | D60: {=IF(A60="", "", IFERROR(INDEX('All Abilities'!E:E, MATCH(A60, 'All Abilities'!B:B, 0)), ""))} | E60: {=IF(A60="", "", IFERROR(INDEX('All Abilities'!G:G, MATCH(A60, 'All Abilities'!B:B, 0)), ""))} | F60: {=IF(A60="", "", IFERROR(INDEX('All Abilities'!F:F, MATCH(A60, 'All Abilities'!B:B, 0)), ""))} | G60: {=IF(A60="", "", IFERROR(INDEX('All Abilities'!L:L, MATCH(A60, 'All Abilities'!B:B, 0)), ""))}
B61: {=IF(A61="", "", IFERROR(INDEX('All Abilities'!H:H, MATCH(A61, 'All Abilities'!B:B, 0)), ""))} | C61: {=IF(A61="", "", IFERROR(INDEX('All Abilities'!D:D, MATCH(A61, 'All Abilities'!B:B, 0)), ""))} | D61: {=IF(A61="", "", IFERROR(INDEX('All Abilities'!E:E, MATCH(A61, 'All Abilities'!B:B, 0)), ""))} | E61: {=IF(A61="", "", IFERROR(INDEX('All Abilities'!G:G, MATCH(A61, 'All Abilities'!B:B, 0)), ""))} | F61: {=IF(A61="", "", IFERROR(INDEX('All Abilities'!F:F, MATCH(A61, 'All Abilities'!B:B, 0)), ""))} | G61: {=IF(A61="", "", IFERROR(INDEX('All Abilities'!L:L, MATCH(A61, 'All Abilities'!B:B, 0)), ""))}
B62: {=IF(A62="", "", IFERROR(INDEX('All Abilities'!H:H, MATCH(A62, 'All Abilities'!B:B, 0)), ""))} | C62: {=IF(A62="", "", IFERROR(INDEX('All Abilities'!D:D, MATCH(A62, 'All Abilities'!B:B, 0)), ""))} | D62: {=IF(A62="", "", IFERROR(INDEX('All Abilities'!E:E, MATCH(A62, 'All Abilities'!B:B, 0)), ""))} | E62: {=IF(A62="", "", IFERROR(INDEX('All Abilities'!G:G, MATCH(A62, 'All Abilities'!B:B, 0)), ""))} | F62: {=IF(A62="", "", IFERROR(INDEX('All Abilities'!F:F, MATCH(A62, 'All Abilities'!B:B, 0)), ""))} | G62: {=IF(A62="", "", IFERROR(INDEX('All Abilities'!L:L, MATCH(A62, 'All Abilities'!B:B, 0)), ""))}
B63: {=IF(A63="", "", IFERROR(INDEX('All Abilities'!H:H, MATCH(A63, 'All Abilities'!B:B, 0)), ""))} | C63: {=IF(A63="", "", IFERROR(INDEX('All Abilities'!D:D, MATCH(A63, 'All Abilities'!B:B, 0)), ""))} | D63: {=IF(A63="", "", IFERROR(INDEX('All Abilities'!E:E, MATCH(A63, 'All Abilities'!B:B, 0)), ""))} | E63: {=IF(A63="", "", IFERROR(INDEX('All Abilities'!G:G, MATCH(A63, 'All Abilities'!B:B, 0)), ""))} | F63: {=IF(A63="", "", IFERROR(INDEX('All Abilities'!F:F, MATCH(A63, 'All Abilities'!B:B, 0)), ""))} | G63: {=IF(A63="", "", IFERROR(INDEX('All Abilities'!L:L, MATCH(A63, 'All Abilities'!B:B, 0)), ""))}
B64: {=IF(A64="", "", IFERROR(INDEX('All Abilities'!H:H, MATCH(A64, 'All Abilities'!B:B, 0)), ""))} | C64: {=IF(A64="", "", IFERROR(INDEX('All Abilities'!D:D, MATCH(A64, 'All Abilities'!B:B, 0)), ""))} | D64: {=IF(A64="", "", IFERROR(INDEX('All Abilities'!E:E, MATCH(A64, 'All Abilities'!B:B, 0)), ""))} | E64: {=IF(A64="", "", IFERROR(INDEX('All Abilities'!G:G, MATCH(A64, 'All Abilities'!B:B, 0)), ""))} | F64: {=IF(A64="", "", IFERROR(INDEX('All Abilities'!F:F, MATCH(A64, 'All Abilities'!B:B, 0)), ""))} | G64: {=IF(A64="", "", IFERROR(INDEX('All Abilities'!L:L, MATCH(A64, 'All Abilities'!B:B, 0)), ""))}
B65: {=IF(A65="", "", IFERROR(INDEX('All Abilities'!H:H, MATCH(A65, 'All Abilities'!B:B, 0)), ""))} | C65: {=IF(A65="", "", IFERROR(INDEX('All Abilities'!D:D, MATCH(A65, 'All Abilities'!B:B, 0)), ""))} | D65: {=IF(A65="", "", IFERROR(INDEX('All Abilities'!E:E, MATCH(A65, 'All Abilities'!B:B, 0)), ""))} | E65: {=IF(A65="", "", IFERROR(INDEX('All Abilities'!G:G, MATCH(A65, 'All Abilities'!B:B, 0)), ""))} | F65: {=IF(A65="", "", IFERROR(INDEX('All Abilities'!F:F, MATCH(A65, 'All Abilities'!B:B, 0)), ""))} | G65: {=IF(A65="", "", IFERROR(INDEX('All Abilities'!L:L, MATCH(A65, 'All Abilities'!B:B, 0)), ""))}
B66: {=IF(A66="", "", IFERROR(INDEX('All Abilities'!H:H, MATCH(A66, 'All Abilities'!B:B, 0)), ""))} | C66: {=IF(A66="", "", IFERROR(INDEX('All Abilities'!D:D, MATCH(A66, 'All Abilities'!B:B, 0)), ""))} | D66: {=IF(A66="", "", IFERROR(INDEX('All Abilities'!E:E, MATCH(A66, 'All Abilities'!B:B, 0)), ""))} | E66: {=IF(A66="", "", IFERROR(INDEX('All Abilities'!G:G, MATCH(A66, 'All Abilities'!B:B, 0)), ""))} | F66: {=IF(A66="", "", IFERROR(INDEX('All Abilities'!F:F, MATCH(A66, 'All Abilities'!B:B, 0)), ""))} | G66: {=IF(A66="", "", IFERROR(INDEX('All Abilities'!L:L, MATCH(A66, 'All Abilities'!B:B, 0)), ""))}
B67: {=IF(A67="", "", IFERROR(INDEX('All Abilities'!H:H, MATCH(A67, 'All Abilities'!B:B, 0)), ""))} | C67: {=IF(A67="", "", IFERROR(INDEX('All Abilities'!D:D, MATCH(A67, 'All Abilities'!B:B, 0)), ""))} | D67: {=IF(A67="", "", IFERROR(INDEX('All Abilities'!E:E, MATCH(A67, 'All Abilities'!B:B, 0)), ""))} | E67: {=IF(A67="", "", IFERROR(INDEX('All Abilities'!G:G, MATCH(A67, 'All Abilities'!B:B, 0)), ""))} | F67: {=IF(A67="", "", IFERROR(INDEX('All Abilities'!F:F, MATCH(A67, 'All Abilities'!B:B, 0)), ""))} | G67: {=IF(A67="", "", IFERROR(INDEX('All Abilities'!L:L, MATCH(A67, 'All Abilities'!B:B, 0)), ""))}
B68: {=IF(A68="", "", IFERROR(INDEX('All Abilities'!H:H, MATCH(A68, 'All Abilities'!B:B, 0)), ""))} | C68: {=IF(A68="", "", IFERROR(INDEX('All Abilities'!D:D, MATCH(A68, 'All Abilities'!B:B, 0)), ""))} | D68: {=IF(A68="", "", IFERROR(INDEX('All Abilities'!E:E, MATCH(A68, 'All Abilities'!B:B, 0)), ""))} | E68: {=IF(A68="", "", IFERROR(INDEX('All Abilities'!G:G, MATCH(A68, 'All Abilities'!B:B, 0)), ""))} | F68: {=IF(A68="", "", IFERROR(INDEX('All Abilities'!F:F, MATCH(A68, 'All Abilities'!B:B, 0)), ""))} | G68: {=IF(A68="", "", IFERROR(INDEX('All Abilities'!L:L, MATCH(A68, 'All Abilities'!B:B, 0)), ""))}
B69: {=IF(A69="", "", IFERROR(INDEX('All Abilities'!H:H, MATCH(A69, 'All Abilities'!B:B, 0)), ""))} | C69: {=IF(A69="", "", IFERROR(INDEX('All Abilities'!D:D, MATCH(A69, 'All Abilities'!B:B, 0)), ""))} | D69: {=IF(A69="", "", IFERROR(INDEX('All Abilities'!E:E, MATCH(A69, 'All Abilities'!B:B, 0)), ""))} | E69: {=IF(A69="", "", IFERROR(INDEX('All Abilities'!G:G, MATCH(A69, 'All Abilities'!B:B, 0)), ""))} | F69: {=IF(A69="", "", IFERROR(INDEX('All Abilities'!F:F, MATCH(A69, 'All Abilities'!B:B, 0)), ""))} | G69: {=IF(A69="", "", IFERROR(INDEX('All Abilities'!L:L, MATCH(A69, 'All Abilities'!B:B, 0)), ""))}
B70: {=IF(A70="", "", IFERROR(INDEX('All Abilities'!H:H, MATCH(A70, 'All Abilities'!B:B, 0)), ""))} | C70: {=IF(A70="", "", IFERROR(INDEX('All Abilities'!D:D, MATCH(A70, 'All Abilities'!B:B, 0)), ""))} | D70: {=IF(A70="", "", IFERROR(INDEX('All Abilities'!E:E, MATCH(A70, 'All Abilities'!B:B, 0)), ""))} | E70: {=IF(A70="", "", IFERROR(INDEX('All Abilities'!G:G, MATCH(A70, 'All Abilities'!B:B, 0)), ""))} | F70: {=IF(A70="", "", IFERROR(INDEX('All Abilities'!F:F, MATCH(A70, 'All Abilities'!B:B, 0)), ""))} | G70: {=IF(A70="", "", IFERROR(INDEX('All Abilities'!L:L, MATCH(A70, 'All Abilities'!B:B, 0)), ""))}
B71: {=IF(A71="", "", IFERROR(INDEX('All Abilities'!H:H, MATCH(A71, 'All Abilities'!B:B, 0)), ""))} | C71: {=IF(A71="", "", IFERROR(INDEX('All Abilities'!D:D, MATCH(A71, 'All Abilities'!B:B, 0)), ""))} | D71: {=IF(A71="", "", IFERROR(INDEX('All Abilities'!E:E, MATCH(A71, 'All Abilities'!B:B, 0)), ""))} | E71: {=IF(A71="", "", IFERROR(INDEX('All Abilities'!G:G, MATCH(A71, 'All Abilities'!B:B, 0)), ""))} | F71: {=IF(A71="", "", IFERROR(INDEX('All Abilities'!F:F, MATCH(A71, 'All Abilities'!B:B, 0)), ""))} | G71: {=IF(A71="", "", IFERROR(INDEX('All Abilities'!L:L, MATCH(A71, 'All Abilities'!B:B, 0)), ""))}
... B80: {=IF(A80="", "", IFERROR(INDEX('All Abilities'!H:H, MATCH(A80, 'All Abilities'!B:B, 0)), ""))} | C80: {=IF(A80="", "", IFERROR(INDEX('All Abilities'!D:D, MATCH(A80, 'All Abilities'!B:B, 0)), ""))} | D80: {=IF(A80="", "", IFERROR(INDEX('All Abilities'!E:E, MATCH(A80, 'All Abilities'!B:B, 0)), ""))} | E80: {=IF(A80="", "", IFERROR(INDEX('All Abilities'!G:G, MATCH(A80, 'All Abilities'!B:B, 0)), ""))} | F80: {=IF(A80="", "", IFERROR(INDEX('All Abilities'!F:F, MATCH(A80, 'All Abilities'!B:B, 0)), ""))} | G80: {=IF(A80="", "", IFERROR(INDEX('All Abilities'!L:L, MATCH(A80, 'All Abilities'!B:B, 0)), ""))}
A81: 2 | B81: Place Ability to the Left, the roll20 macro will be to the right. | C81: {=SUBSTITUTE(SUBSTITUTE(SUBSTITUTE(SUBSTITUTE(SUBSTITUTE(SUBSTITUTE("&{template:default} {{name=@{name} ❖ {skillname}}} {{Keywords:={keywords}}} {{Range:={range}}} {{Cost:={cost}}} {{Req:={req}}} {{Desc:={desc}}}", "{skillname}", INDIRECT("A"&$A$81)), "{keywords}", INDIRECT("C"&$A$81)), "{range}", INDIRECT("D"&$A$81)), "{cost}", INDIRECT("B"&$A$81)), "{req}", INDIRECT("E"&$A$81)), "{desc}", INDIRECT("F"&$A$81))} -> &{template:default} {{name=@{name} ❖ }} {{Keywords:=}} {{Range:=}} {{Cost:=}} {{Req:=}} {{Desc:=}}

Sheet Breakthrough
A1: Breakthrough | B1: XP Spent | C1: Requirement | D1: Description | E1: Each character starts with 300 exp that can only be used on breakthroughs. This EXP is not added to your spirit core and any exp not spent during this time is removed after the character creation process. Any breakthroughs taken during character creation using this 300xp should be left at 0 XP Spent in the dropdown. | F1: If Taking 'Mixed House' Breakthrough Select Both Chosen Houses
B2: 0 | C2: {=IF(A2="", "", IFERROR(INDEX(Breakthroughs!C:C, MATCH(A2, Breakthroughs!A:A, 0)), ""))} | D2: {=IF(A2="", "", IFERROR(INDEX(Breakthroughs!D:D, MATCH(A2, Breakthroughs!A:A, 0)), ""))}
B3: 0 | C3: {=IF(A3="", "", IFERROR(INDEX(Breakthroughs!C:C, MATCH(A3, Breakthroughs!A:A, 0)), ""))} | D3: {=IF(A3="", "", IFERROR(INDEX(Breakthroughs!D:D, MATCH(A3, Breakthroughs!A:A, 0)), ""))}
B4: 0 | C4: {=IF(A4="", "", IFERROR(INDEX(Breakthroughs!C:C, MATCH(A4, Breakthroughs!A:A, 0)), ""))} | D4: {=IF(A4="", "", IFERROR(INDEX(Breakthroughs!D:D, MATCH(A4, Breakthroughs!A:A, 0)), ""))}
B5: 0 | C5: {=IF(A5="", "", IFERROR(INDEX(Breakthroughs!C:C, MATCH(A5, Breakthroughs!A:A, 0)), ""))} | D5: {=IF(A5="", "", IFERROR(INDEX(Breakthroughs!D:D, MATCH(A5, Breakthroughs!A:A, 0)), ""))}
B6: 0 | C6: {=IF(A6="", "", IFERROR(INDEX(Breakthroughs!C:C, MATCH(A6, Breakthroughs!A:A, 0)), ""))} | D6: {=IF(A6="", "", IFERROR(INDEX(Breakthroughs!D:D, MATCH(A6, Breakthroughs!A:A, 0)), ""))}
B7: 0 | C7: {=IF(A7="", "", IFERROR(INDEX(Breakthroughs!C:C, MATCH(A7, Breakthroughs!A:A, 0)), ""))} | D7: {=IF(A7="", "", IFERROR(INDEX(Breakthroughs!D:D, MATCH(A7, Breakthroughs!A:A, 0)), ""))}
B8: 0 | C8: {=IF(A8="", "", IFERROR(INDEX(Breakthroughs!C:C, MATCH(A8, Breakthroughs!A:A, 0)), ""))} | D8: {=IF(A8="", "", IFERROR(INDEX(Breakthroughs!D:D, MATCH(A8, Breakthroughs!A:A, 0)), ""))}
B9: 0 | C9: {=IF(A9="", "", IFERROR(INDEX(Breakthroughs!C:C, MATCH(A9, Breakthroughs!A:A, 0)), ""))} | D9: {=IF(A9="", "", IFERROR(INDEX(Breakthroughs!D:D, MATCH(A9, Breakthroughs!A:A, 0)), ""))}
B10: 0 | C10: {=IF(A10="", "", IFERROR(INDEX(Breakthroughs!C:C, MATCH(A10, Breakthroughs!A:A, 0)), ""))} | D10: {=IF(A10="", "", IFERROR(INDEX(Breakthroughs!D:D, MATCH(A10, Breakthroughs!A:A, 0)), ""))}
B11: 0 | C11: {=IF(A11="", "", IFERROR(INDEX(Breakthroughs!C:C, MATCH(A11, Breakthroughs!A:A, 0)), ""))} | D11: {=IF(A11="", "", IFERROR(INDEX(Breakthroughs!D:D, MATCH(A11, Breakthroughs!A:A, 0)), ""))}
B12: 0 | C12: {=IF(A12="", "", IFERROR(INDEX(Breakthroughs!C:C, MATCH(A12, Breakthroughs!A:A, 0)), ""))} | D12: {=IF(A12="", "", IFERROR(INDEX(Breakthroughs!D:D, MATCH(A12, Breakthroughs!A:A, 0)), ""))}
B13: 0 | C13: {=IF(A13="", "", IFERROR(INDEX(Breakthroughs!C:C, MATCH(A13, Breakthroughs!A:A, 0)), ""))} | D13: {=IF(A13="", "", IFERROR(INDEX(Breakthroughs!D:D, MATCH(A13, Breakthroughs!A:A, 0)), ""))}
... B16: 0 | C16: {=IF(A16="", "", IFERROR(INDEX(Breakthroughs!C:C, MATCH(A16, Breakthroughs!A:A, 0)), ""))} | D16: {=IF(A16="", "", IFERROR(INDEX(Breakthroughs!D:D, MATCH(A16, Breakthroughs!A:A, 0)), ""))}
B17: 0 | C17: {=IF(A17="", "", IFERROR(INDEX(Breakthroughs!C:C, MATCH(A17, Breakthroughs!A:A, 0)), ""))} | D17: {=IF(A17="", "", IFERROR(INDEX(Breakthroughs!D:D, MATCH(A17, Breakthroughs!A:A, 0)), ""))} | F17: Wi, Homeless
B18: 0 | C18: {=IF(A18="", "", IFERROR(INDEX(Breakthroughs!C:C, MATCH(A18, Breakthroughs!A:A, 0)), ""))} | D18: {=IF(A18="", "", IFERROR(INDEX(Breakthroughs!D:D, MATCH(A18, Breakthroughs!A:A, 0)), ""))}
B19: 0 | C19: {=IF(A19="", "", IFERROR(INDEX(Breakthroughs!C:C, MATCH(A19, Breakthroughs!A:A, 0)), ""))} | D19: {=IF(A19="", "", IFERROR(INDEX(Breakthroughs!D:D, MATCH(A19, Breakthroughs!A:A, 0)), ""))}
B20: 0 | C20: {=IF(A20="", "", IFERROR(INDEX(Breakthroughs!C:C, MATCH(A20, Breakthroughs!A:A, 0)), ""))} | D20: {=IF(A20="", "", IFERROR(INDEX(Breakthroughs!D:D, MATCH(A20, Breakthroughs!A:A, 0)), ""))}
B21: 0 | C21: {=IF(A21="", "", IFERROR(INDEX(Breakthroughs!C:C, MATCH(A21, Breakthroughs!A:A, 0)), ""))} | D21: {=IF(A21="", "", IFERROR(INDEX(Breakthroughs!D:D, MATCH(A21, Breakthroughs!A:A, 0)), ""))}
B22: 0 | C22: {=IF(A22="", "", IFERROR(INDEX(Breakthroughs!C:C, MATCH(A22, Breakthroughs!A:A, 0)), ""))} | D22: {=IF(A22="", "", IFERROR(INDEX(Breakthroughs!D:D, MATCH(A22, Breakthroughs!A:A, 0)), ""))}
B23: 0 | C23: {=IF(A23="", "", IFERROR(INDEX(Breakthroughs!C:C, MATCH(A23, Breakthroughs!A:A, 0)), ""))} | D23: {=IF(A23="", "", IFERROR(INDEX(Breakthroughs!D:D, MATCH(A23, Breakthroughs!A:A, 0)), ""))}
B24: 0 | C24: {=IF(A24="", "", IFERROR(INDEX(Breakthroughs!C:C, MATCH(A24, Breakthroughs!A:A, 0)), ""))} | D24: {=IF(A24="", "", IFERROR(INDEX(Breakthroughs!D:D, MATCH(A24, Breakthroughs!A:A, 0)), ""))}
B25: 0 | C25: {=IF(A25="", "", IFERROR(INDEX(Breakthroughs!C:C, MATCH(A25, Breakthroughs!A:A, 0)), ""))} | D25: {=IF(A25="", "", IFERROR(INDEX(Breakthroughs!D:D, MATCH(A25, Breakthroughs!A:A, 0)), ""))}
B26: 0 | C26: {=IF(A26="", "", IFERROR(INDEX(Breakthroughs!C:C, MATCH(A26, Breakthroughs!A:A, 0)), ""))} | D26: {=IF(A26="", "", IFERROR(INDEX(Breakthroughs!D:D, MATCH(A26, Breakthroughs!A:A, 0)), ""))}
B27: 0 | C27: {=IF(A27="", "", IFERROR(INDEX(Breakthroughs!C:C, MATCH(A27, Breakthroughs!A:A, 0)), ""))} | D27: {=IF(A27="", "", IFERROR(INDEX(Breakthroughs!D:D, MATCH(A27, Breakthroughs!A:A, 0)), ""))}
B28: 0 | C28: {=IF(A28="", "", IFERROR(INDEX(Breakthroughs!C:C, MATCH(A28, Breakthroughs!A:A, 0)), ""))} | D28: {=IF(A28="", "", IFERROR(INDEX(Breakthroughs!D:D, MATCH(A28, Breakthroughs!A:A, 0)), ""))}
B29: 0 | C29: {=IF(A29="", "", IFERROR(INDEX(Breakthroughs!C:C, MATCH(A29, Breakthroughs!A:A, 0)), ""))} | D29: {=IF(A29="", "", IFERROR(INDEX(Breakthroughs!D:D, MATCH(A29, Breakthroughs!A:A, 0)), ""))}
... B37: 0 | C37: {=IF(A37="", "", IFERROR(INDEX(Breakthroughs!C:C, MATCH(A37, Breakthroughs!A:A, 0)), ""))} | D37: {=IF(A37="", "", IFERROR(INDEX(Breakthroughs!D:D, MATCH(A37, Breakthroughs!A:A, 0)), ""))}

Sheet Inventory
A1: Expedition Inventory | B1: Amount | C1: Burden | D1: Clim Cost (Price of 1 Item) | E1: Item Total Clim Value | F1: Description | G1: Burden Total
E2: =SUMPRODUCT((IF(B2="",1,B2)) * (IF(D2="",0,D2))) -> 0 | G2: =SUM(C2:C137) -> 0
E3: =SUMPRODUCT((IF(B3="",1,B3)) * (IF(D3="",0,D3))) -> 0 | G3: Inventory Clim Value | H3: =SUMPRODUCT((IF(B2:B137="",1,B2:B137)) * (IF(D2:D137="",0,D2:D137))) -> 0
E4: =SUMPRODUCT((IF(B4="",1,B4)) * (IF(D4="",0,D4))) -> 0 | G4: Total Character Clim Value | H4: =SUM(H3,Core!L2,'Mirane Locker'!G2) -> 4000
E5: =SUMPRODUCT((IF(B5="",1,B5)) * (IF(D5="",0,D5))) -> 0 | G5: Combat Loadout | H5: Burden
E6: =SUMPRODUCT((IF(B6="",1,B6)) * (IF(D6="",0,D6))) -> 0
E7: =SUMPRODUCT((IF(B7="",1,B7)) * (IF(D7="",0,D7))) -> 0
E8: =SUMPRODUCT((IF(B8="",1,B8)) * (IF(D8="",0,D8))) -> 0
E9: =SUMPRODUCT((IF(B9="",1,B9)) * (IF(D9="",0,D9))) -> 0
E10: =SUMPRODUCT((IF(B10="",1,B10)) * (IF(D10="",0,D10))) -> 0
E11: =SUMPRODUCT((IF(B11="",1,B11)) * (IF(D11="",0,D11))) -> 0
E12: =SUMPRODUCT((IF(B12="",1,B12)) * (IF(D12="",0,D12))) -> 0
E13: =SUMPRODUCT((IF(B13="",1,B13)) * (IF(D13="",0,D13))) -> 0
E14: =SUMPRODUCT((IF(B14="",1,B14)) * (IF(D14="",0,D14))) -> 0
E15: =SUMPRODUCT((IF(B15="",1,B15)) * (IF(D15="",0,D15))) -> 0
E16: =SUMPRODUCT((IF(B16="",1,B16)) * (IF(D16="",0,D16))) -> 0
E17: =SUMPRODUCT((IF(B17="",1,B17)) * (IF(D17="",0,D17))) -> 0
... E31: =SUMPRODUCT((IF(B31="",1,B31)) * (IF(D31="",0,D31))) -> 0
E32: =SUMPRODUCT((IF(B32="",1,B32)) * (IF(D32="",0,D32))) -> 0 | G32: Combat Burden Total | H32: =sum(H6:H31) -> 0
E33: =SUMPRODUCT((IF(B33="",1,B33)) * (IF(D33="",0,D33))) -> 0 | G33: Adventurer's Kit | H33: Burden
E34: =SUMPRODUCT((IF(B34="",1,B34)) * (IF(D34="",0,D34))) -> 0
E35: =SUMPRODUCT((IF(B35="",1,B35)) * (IF(D35="",0,D35))) -> 0
E36: =SUMPRODUCT((IF(B36="",1,B36)) * (IF(D36="",0,D36))) -> 0
E37: =SUMPRODUCT((IF(B37="",1,B37)) * (IF(D37="",0,D37))) -> 0
E38: =SUMPRODUCT((IF(B38="",1,B38)) * (IF(D38="",0,D38))) -> 0
E39: =SUMPRODUCT((IF(B39="",1,B39)) * (IF(D39="",0,D39))) -> 0 | G39: Adventurer's Kit Total Burden Carried | H39: =sum(H33:H38) -> 0
E40: =SUMPRODUCT((IF(B40="",1,B40)) * (IF(D40="",0,D40))) -> 0 | G40: ADVENTURER'S KIT CAN STORE 5 BURDEN MAX IN COMBAT READY STATE
E41: =SUMPRODUCT((IF(B41="",1,B41)) * (IF(D41="",0,D41))) -> 0
E42: =SUMPRODUCT((IF(B42="",1,B42)) * (IF(D42="",0,D42))) -> 0
E43: =SUMPRODUCT((IF(B43="",1,B43)) * (IF(D43="",0,D43))) -> 0
E44: =SUMPRODUCT((IF(B44="",1,B44)) * (IF(D44="",0,D44))) -> 0 | G44: Alchemy Rig | H44: Burden
E45: =SUMPRODUCT((IF(B45="",1,B45)) * (IF(D45="",0,D45))) -> 0
E46: =SUMPRODUCT((IF(B46="",1,B46)) * (IF(D46="",0,D46))) -> 0
E47: =SUMPRODUCT((IF(B47="",1,B47)) * (IF(D47="",0,D47))) -> 0
E48: =SUMPRODUCT((IF(B48="",1,B48)) * (IF(D48="",0,D48))) -> 0
E49: =SUMPRODUCT((IF(B49="",1,B49)) * (IF(D49="",0,D49))) -> 0
E50: =SUMPRODUCT((IF(B50="",1,B50)) * (IF(D50="",0,D50))) -> 0 | G50: Alchemy Rig Burden Total | H50: =SUM(H45:H49) -> 0
E51: =SUMPRODUCT((IF(B51="",1,B51)) * (IF(D51="",0,D51))) -> 0
E52: =SUMPRODUCT((IF(B52="",1,B52)) * (IF(D52="",0,D52))) -> 0
E53: =SUMPRODUCT((IF(B53="",1,B53)) * (IF(D53="",0,D53))) -> 0
E54: =SUMPRODUCT((IF(B54="",1,B54)) * (IF(D54="",0,D54))) -> 0
E55: =SUMPRODUCT((IF(B55="",1,B55)) * (IF(D55="",0,D55))) -> 0
E56: =SUMPRODUCT((IF(B56="",1,B56)) * (IF(D56="",0,D56))) -> 0
E57: =SUMPRODUCT((IF(B57="",1,B57)) * (IF(D57="",0,D57))) -> 0
E58: =SUMPRODUCT((IF(B58="",1,B58)) * (IF(D58="",0,D58))) -> 0
E59: =SUMPRODUCT((IF(B59="",1,B59)) * (IF(D59="",0,D59))) -> 0
E60: =SUMPRODUCT((IF(B60="",1,B60)) * (IF(D60="",0,D60))) -> 0
E61: =SUMPRODUCT((IF(B61="",1,B61)) * (IF(D61="",0,D61))) -> 0
E62: =SUMPRODUCT((IF(B62="",1,B62)) * (IF(D62="",0,D62))) -> 0
... E137: =SUMPRODUCT((IF(B137="",1,B137)) * (IF(D137="",0,D137))) -> 0

Sheet Mirane Locker
A1: Mirane Locker | B1: Amount | C1: Item Type | D1: Clim Cost (Price of 1 Item) | E1: Total Item Clim Value | F1: Notes | G1: Mirane Locker Clim Value Total
E2: =SUMPRODUCT((IF(B2="",1,B2)) * (IF(D2="",0,D2))) -> 0 | G2: =SUMPRODUCT((IF(B2:B137="",1,B2:B137)) * (IF(D2:D137="",0,D2:D137))) -> 0
E3: =SUMPRODUCT((IF(B3="",1,B3)) * (IF(D3="",0,D3))) -> 0
E4: =SUMPRODUCT((IF(B4="",1,B4)) * (IF(D4="",0,D4))) -> 0
E5: =SUMPRODUCT((IF(B5="",1,B5)) * (IF(D5="",0,D5))) -> 0
E6: =SUMPRODUCT((IF(B6="",1,B6)) * (IF(D6="",0,D6))) -> 0
E7: =SUMPRODUCT((IF(B7="",1,B7)) * (IF(D7="",0,D7))) -> 0
E8: =SUMPRODUCT((IF(B8="",1,B8)) * (IF(D8="",0,D8))) -> 0
E9: =SUMPRODUCT((IF(B9="",1,B9)) * (IF(D9="",0,D9))) -> 0
E10: =SUMPRODUCT((IF(B10="",1,B10)) * (IF(D10="",0,D10))) -> 0
E11: =SUMPRODUCT((IF(B11="",1,B11)) * (IF(D11="",0,D11))) -> 0
E12: =SUMPRODUCT((IF(B12="",1,B12)) * (IF(D12="",0,D12))) -> 0
E13: =SUMPRODUCT((IF(B13="",1,B13)) * (IF(D13="",0,D13))) -> 0
E14: =SUMPRODUCT((IF(B14="",1,B14)) * (IF(D14="",0,D14))) -> 0
... E137: =SUMPRODUCT((IF(B137="",1,B137)) * (IF(D137="",0,D137))) -> 0

Sheet EXP & Transactions
A1: Event | B1: Date | C1: Amount of Experience Gained | D1: Experience Total | E1: Service or Item Sold/Purchased | F1: Clim Value (Negative for Purchases) | G1: Clim Purchase and Earned Total
A2: Character Creation | B2: N/A | C2: =SUM(1000 + Core!B49 + Core!B50) -> 1000 | D2: =SUM(C2:C166) -> 1000 | E2: Character Creation | F2: =IF(Core!A58, 4000, 3000) + IF(COUNTIF(Breakthrough!A:A,"Rich Parents")>0, 3000, 0) -> 4000 | G2: =SUM(F2:F166) -> 4000
A3: Retirement/Death | B3: N/A | C3: 0 | D3: Slow Starter and Human EXP changes are already accounted for by the checkboxes in the 'Core' tab. Do not add/subtract them here.
E4: Character Creation Purchases | F4: 0

Sheet Leveling Planner
A1: Level Ups | B1: Class | C1: Class Tier | D1: Class Level | E1: Ability Name | F1: Cost | G1: Keywords | H1: Range | I1: Requirement | J1: Description
A2: 1
A3: 2
A4: 3
A5: 4
A6: 5
A7: 6
A8: 7
A9: 8
A10: 9
A11: 10
A12: 11
A13: 12
... A41: 40

Sheet Images

Sheet Backstory

Sheet Journals

Sheet Custom Abilities
A1: Custom Active Ability Name | B1: Cost | C1: Keywords | D1: Range | E1: Requirement | F1: Description | G1: Benefits
A38: Custom Passive Ability Name | B38: Cost | C38: Keywords | D38: Range | E38: Requirement | F38: Description | G38: Benefits

Sheet Basic Gatherer & Crafter Action
A1: Ability Name | B1: Cost | C1: Keywords | D1: Range | E1: Requirement | F1: Description
A2: Basic Craft | B2: 1 Crafting Dice | C2: Rapid | D2: Self | E2: Must be in a crafting session | F2: You add a crafting check to the item.
A3: Beginner's Luck | B3: 1 Crafting Dice | D3: Self | E3: Must be in a crafting session | F3: You do not add your crafting skill to the check, but you roll two d10s and pick the highest one.
A4: Standard Finish | B4: 2 Crafting Dice | D4: Self | E4: Must be in a crafting session | F4: Double the current crafting points and end crafting. Cannot be used if the item being crafted has been modified beyond it's base form (for example, by adding a +1 power bonus to it via blacksmithing).
A5: Steady Craft | B5: 1 Crafting Dice | D5: Self | E5: Must be in a crafting session | F5: You add a crafting check to the item. The crafting dice automatically is a 5.
A6: Basic Strike | B6: 1 Strike Dice | C6: Rapid | D6: Self | E6: Must be in a gathering session | F6: You add a gathering check to the node points to the target node.
A7: Lucky Strike | B7: 1 Strike Dice, 10 Node Points | C7: Rapid | D7: Self | E7: Must be in a gathering session | F7: You add a gathering check to the lucky points to the target node. This strike has a +10 bonus.
A8: Novice's Perseverance | B8: 1 Strike Dice | D8: Self | E8: Must be in a gathering session | F8: You do not add your crafting skill to the check, but you roll two d10s and pick the highest. Can be used against either NP or LP
A9: Back to Basics | B9: 2 Strike Dice | D9: Self | E9: Must be in a gathering session | F9: Convert all LP up to a maximum of 60 to NP.
A10: Iron Focus | B10: 1 Strike Dice, 5 Lucky Points | D10: Self | E10: Must be in a gathering session | F10: Make a gathering check. Afterwards, you gain a +5 bonus to all gathering checks for the rest of this gathering session.
A11: 2 | B11: Place Ability Row Number to the Left, the roll20 macro will be to the right. | C11: {=SUBSTITUTE(SUBSTITUTE(SUBSTITUTE(SUBSTITUTE(SUBSTITUTE(SUBSTITUTE("&{template:default} {{name=@{name} ❖ {skillname}}} {{Keywords:={keywords}}} {{Range:={range}}} {{Cost:={cost}}} {{Req:={req}}} {{Desc:={desc}}}", "{skillname}", INDIRECT("A"&$A$11)), "{cost}", INDIRECT("B"&$A$11)), "{keywords}", INDIRECT("C"&$A$11)), "{range}", INDIRECT("D"&$A$11)), "{req}", INDIRECT("E"&$A$11)), "{desc}", INDIRECT("F"&$A$11))} -> &{template:default} {{name=@{name} ❖ Basic Craft}} {{Keywords:=Rapid}} {{Range:=Self}} {{Cost:=1 Crafting Dice}} {{Req:=Must be in a crafting session}} {{Desc:=You add a crafting check to the item.}}

Sheet All Abilities
B1: =IFERROR(__xludf.DUMMYFUNCTION("IMPORTRANGE(""https://docs.google.com/spreadsheets/d/1xgDM68xiM34Lb7pPa9X0VaOqdhswjHKkl6KIk-vu_2Q/edit?gid=404700120#gid=404700120"", ""Abilities!B1:B1500"")"),"Name") -> Name | D1: =IFERROR(__xludf.DUMMYFUNCTION("IMPORTRANGE(""https://docs.google.com/spreadsheets/d/1xgDM68xiM34Lb7pPa9X0VaOqdhswjHKkl6KIk-vu_2Q/edit?gid=404700120#gid=404700120"", ""Abilities!F1:F1500"")"),"Keywords") -> Keywords | E1: =IFERROR(__xludf.DUMMYFUNCTION("IMPORTRANGE(""https://docs.google.com/spreadsheets/d/1xgDM68xiM34Lb7pPa9X0VaOqdhswjHKkl6KIk-vu_2Q/edit?gid=404700120#gid=404700120"", ""Abilities!G1:G1500"")"),"Range") -> Range | F1: =IFERROR(__xludf.DUMMYFUNCTION("IMPORTRANGE(""https://docs.google.com/spreadsheets/d/1xgDM68xiM34Lb7pPa9X0VaOqdhswjHKkl6KIk-vu_2Q/edit?gid=404700120#gid=404700120"", ""Abilities!I1:I1500"")"),"Description") -> Description | G1: =IFERROR(__xludf.DUMMYFUNCTION("IMPORTRANGE(""https://docs.google.com/spreadsheets/d/1xgDM68xiM34Lb7pPa9X0VaOqdhswjHKkl6KIk-vu_2Q/edit?gid=404700120#gid=404700120"", ""Abilities!H1:H1500"")"),"Requirement") -> Requirement | H1: =IFERROR(__xludf.DUMMYFUNCTION("IMPORTRANGE(""https://docs.google.com/spreadsheets/d/1xgDM68xiM34Lb7pPa9X0VaOqdhswjHKkl6KIk-vu_2Q/edit?gid=404700120#gid=404700120"", ""Abilities!L1:L1500"")"),"Total cost") -> Total cost | I1: =IFERROR(__xludf.DUMMYFUNCTION("IMPORTRANGE(""https://docs.google.com/spreadsheets/d/1xgDM68xiM34Lb7pPa9X0VaOqdhswjHKkl6KIk-vu_2Q/edit?gid=404700120#gid=404700120"", ""Abilities!C1:C1500"")"),"AP cost") -> AP cost | J1: =IFERROR(__xludf.DUMMYFUNCTION("IMPORTRANGE(""https://docs.google.com/spreadsheets/d/1xgDM68xiM34Lb7pPa9X0VaOqdhswjHKkl6KIk-vu_2Q/edit?gid=404700120#gid=404700120"", ""Abilities!D1:D1500"")"),"Mana cost") -> Mana cost | K1: =IFERROR(__xludf.DUMMYFUNCTION("IMPORTRANGE(""https://docs.google.com/spreadsheets/d/1xgDM68xiM34Lb7pPa9X0VaOqdhswjHKkl6KIk-vu_2Q/edit?gid=404700120#gid=404700120"", ""Abilities!E1:E1500"")"),"RP cost") -> RP cost | L1: =IFERROR(__xludf.DUMMYFUNCTION("IMPORTRANGE(""https://docs.google.com/spreadsheets/d/1xgDM68xiM34Lb7pPa9X0VaOqdhswjHKkl6KIk-vu_2Q/edit?gid=404700120#gid=404700120"", ""Abilities!J1:J1500"")"),"Benefits") -> Benefits
B2: =IFERROR(__xludf.DUMMYFUNCTION("""COMPUTED_VALUE"""),"Abjurer's Blast") -> Abjurer's Blast | D2: =IFERROR(__xludf.DUMMYFUNCTION("""COMPUTED_VALUE"""),"Rapid, Spell") -> Rapid, Spell | E2: =IFERROR(__xludf.DUMMYFUNCTION("""COMPUTED_VALUE"""),"10ft") -> 10ft | F2: =IFERROR(__xludf.DUMMYFUNCTION("""COMPUTED_VALUE"""),"You make a Light (1 AP), Heavy (2 AP) or Precise (2 AP) attack against the target that deals Arcane damage. This spell does not provoke attacks of opportunity.") -> You make a Light (1 AP), Heavy (2 AP) or Precise (2 AP) attack against the target that deals Arcane damage. This spell does not provoke attacks of opportunity. | G2: =IFERROR(__xludf.DUMMYFUNCTION("""COMPUTED_VALUE"""),"") | H2: =IFERROR(__xludf.DUMMYFUNCTION("""COMPUTED_VALUE"""),"1 AP") -> 1 AP | I2: =IFERROR(__xludf.DUMMYFUNCTION("""COMPUTED_VALUE"""),"1 AP") -> 1 AP | J2: =IFERROR(__xludf.DUMMYFUNCTION("""COMPUTED_VALUE"""),"") | K2: =IFERROR(__xludf.DUMMYFUNCTION("""COMPUTED_VALUE"""),"") | L2: =IFERROR(__xludf.DUMMYFUNCTION("""COMPUTED_VALUE"""),"")
B3: =IFERROR(__xludf.DUMMYFUNCTION("""COMPUTED_VALUE"""),"Absorb Ice") -> Absorb Ice | D3: =IFERROR(__xludf.DUMMYFUNCTION("""COMPUTED_VALUE"""),"Rapid") -> Rapid | E3: =IFERROR(__xludf.DUMMYFUNCTION("""COMPUTED_VALUE"""),"Self") -> Self | F3: =IFERROR(__xludf.DUMMYFUNCTION("""COMPUTED_VALUE"""),"You gain Absorb Ice, which gives you Damage Reduction 100 Frost against the triggering damage. After the damage resolves, if the caster is not you, someone allied to you or from an effect made by you or an ally, you gain Temporary HP until the end of the "&"encounter equal to the amount of damage this ability reduces. Any on hit effects from the damage do not apply if you took 0 damage from it because of your DR.") -> You gain Absorb Ice, which gives you Damage Reduction 100 Frost against the triggering damage. After the damage resolves, if the caster is not you, someone allied to you or from an effect made by you or an ally, you gain Temporary HP until the end of the encounter equal to the amount of damage this ability reduces. Any on hit effects from the damage do not apply if you took 0 damage from it because of your DR. | G3: =IFERROR(__xludf.DUMMYFUNCTION("""COMPUTED_VALUE"""),"You're about to take Frost Damage.") -> You're about to take Frost Damage. | H3: =IFERROR(__xludf.DUMMYFUNCTION("""COMPUTED_VALUE"""),"1 RP") -> 1 RP | I3: =IFERROR(__xludf.DUMMYFUNCTION("""COMPUTED_VALUE"""),"") | J3: =IFERROR(__xludf.DUMMYFUNCTION("""COMPUTED_VALUE"""),"") | K3: =IFERROR(__xludf.DUMMYFUNCTION("""COMPUTED_VALUE"""),"1 RP") -> 1 RP | L3: =IFERROR(__xludf.DUMMYFUNCTION("""COMPUTED_VALUE"""),"")
B4: =IFERROR(__xludf.DUMMYFUNCTION("""COMPUTED_VALUE"""),"Accelerando") -> Accelerando | D4: =IFERROR(__xludf.DUMMYFUNCTION("""COMPUTED_VALUE"""),"Encounter Start") -> Encounter Start | E4: =IFERROR(__xludf.DUMMYFUNCTION("""COMPUTED_VALUE"""),"120ft") -> 120ft | F4: =IFERROR(__xludf.DUMMYFUNCTION("""COMPUTED_VALUE"""),"Grant yourself or an ally +4 initiative.") -> Grant yourself or an ally +4 initiative. | G4: =IFERROR(__xludf.DUMMYFUNCTION("""COMPUTED_VALUE"""),"") | H4: =IFERROR(__xludf.DUMMYFUNCTION("""COMPUTED_VALUE"""),"") | I4: =IFERROR(__xludf.DUMMYFUNCTION("""COMPUTED_VALUE"""),"") | J4: =IFERROR(__xludf.DUMMYFUNCTION("""COMPUTED_VALUE"""),"") | K4: =IFERROR(__xludf.DUMMYFUNCTION("""COMPUTED_VALUE"""),"") | L4: =IFERROR(__xludf.DUMMYFUNCTION("""COMPUTED_VALUE"""),"")
B5: =IFERROR(__xludf.DUMMYFUNCTION("""COMPUTED_VALUE"""),"Accelerating Strike") -> Accelerating Strike | D5: =IFERROR(__xludf.DUMMYFUNCTION("""COMPUTED_VALUE"""),"") | E5: =IFERROR(__xludf.DUMMYFUNCTION("""COMPUTED_VALUE"""),"Melee Weapon Range") -> Melee Weapon Range | F5: =IFERROR(__xludf.DUMMYFUNCTION("""COMPUTED_VALUE"""),"You make a Heavy Attack against the target. Afterwards, you gain Accelerating Strike, which increases your Initiative by up to 2.") -> You make a Heavy Attack against the target. Afterwards, you gain Accelerating Strike, which increases your Initiative by up to 2. | G5: =IFERROR(__xludf.DUMMYFUNCTION("""COMPUTED_VALUE"""),"") | H5: =IFERROR(__xludf.DUMMYFUNCTION("""COMPUTED_VALUE"""),"2 AP, 1 MP") -> 2 AP, 1 MP | I5: =IFERROR(__xludf.DUMMYFUNCTION("""COMPUTED_VALUE"""),"2 AP") -> 2 AP | J5: =IFERROR(__xludf.DUMMYFUNCTION("""COMPUTED_VALUE"""),"1 MP") -> 1 MP | K5: =IFERROR(__xludf.DUMMYFUNCTION("""COMPUTED_VALUE"""),"") | L5: =IFERROR(__xludf.DUMMYFUNCTION("""COMPUTED_VALUE"""),"")
B6: =IFERROR(__xludf.DUMMYFUNCTION("""COMPUTED_VALUE"""),"Adaptive Defense") -> Adaptive Defense | D6: =IFERROR(__xludf.DUMMYFUNCTION("""COMPUTED_VALUE"""),"Rapid") -> Rapid | E6: =IFERROR(__xludf.DUMMYFUNCTION("""COMPUTED_VALUE"""),"Self") -> Self | F6: =IFERROR(__xludf.DUMMYFUNCTION("""COMPUTED_VALUE"""),"You take the Block Action. You then gain 4 Adaptive Defense (Type) which grants you Damage Reduction 4 against that damage type until the end of your next turn. You can only have one instance of Adaptive Defense at a time.") -> You take the Block Action. You then gain 4 Adaptive Defense (Type) which grants you Damage Reduction 4 against that damage type until the end of your next turn. You can only have one instance of Adaptive Defense at a time. | G6: =IFERROR(__xludf.DUMMYFUNCTION("""COMPUTED_VALUE"""),"") | H6: =IFERROR(__xludf.DUMMYFUNCTION("""COMPUTED_VALUE"""),"2 MP, 1 RP") -> 2 MP, 1 RP | I6: =IFERROR(__xludf.DUMMYFUNCTION("""COMPUTED_VALUE"""),"") | J6: =IFERROR(__xludf.DUMMYFUNCTION("""COMPUTED_VALUE"""),"2 MP") -> 2 MP | K6: =IFERROR(__xludf.DUMMYFUNCTION("""COMPUTED_VALUE"""),"1 RP") -> 1 RP | L6: =IFERROR(__xludf.DUMMYFUNCTION("""COMPUTED_VALUE"""),"")
B7: =IFERROR(__xludf.DUMMYFUNCTION("""COMPUTED_VALUE"""),"Advanced Artificing") -> Advanced Artificing | D7: =IFERROR(__xludf.DUMMYFUNCTION("""COMPUTED_VALUE"""),"") | E7: =IFERROR(__xludf.DUMMYFUNCTION("""COMPUTED_VALUE"""),"") | F7: =IFERROR(__xludf.DUMMYFUNCTION("""COMPUTED_VALUE"""),"Artifice Modification B Cost: X crafting points Description: You add a B-Type modification to an artifice. See the Universal Artifice mods page as well as the individual weapon page for details. Each modification has its own cost. Weapon Modification B Co"&"st: X Crafting Points Description: You add an B-Type modification to the weapon. See the Universal Weapon page as well as the individual weapon page for details. Each modification has its own cost.") -> Artifice Modification B Cost: X crafting points Description: You add a B-Type modification to an artifice. See the Universal Artifice mods page as well as the individual weapon page for details. Each modification has its own cost. Weapon Modification B Cost: X Crafting Points Description: You add an B-Type modification to the weapon. See the Universal Weapon page as well as the individual weapon page for details. Each modification has its own cost. | G7: =IFERROR(__xludf.DUMMYFUNCTION("""COMPUTED_VALUE"""),"") | H7: =IFERROR(__xludf.DUMMYFUNCTION("""COMPUTED_VALUE"""),"") | I7: =IFERROR(__xludf.DUMMYFUNCTION("""COMPUTED_VALUE"""),"") | J7: =IFERROR(__xludf.DUMMYFUNCTION("""COMPUTED_VALUE"""),"") | K7: =IFERROR(__xludf.DUMMYFUNCTION("""COMPUTED_VALUE"""),"") | L7: =IFERROR(__xludf.DUMMYFUNCTION("""COMPUTED_VALUE"""),"")
B8: =IFERROR(__xludf.DUMMYFUNCTION("""COMPUTED_VALUE"""),"Aerial Crashdown") -> Aerial Crashdown | D8: =IFERROR(__xludf.DUMMYFUNCTION("""COMPUTED_VALUE"""),"") | E8: =IFERROR(__xludf.DUMMYFUNCTION("""COMPUTED_VALUE"""),"60ft") -> 60ft | F8: =IFERROR(__xludf.DUMMYFUNCTION("""COMPUTED_VALUE"""),"You and your mount crash down on the target. You move towards the target and your mount makes a Heavy attack against it. On damage, the target is knocked prone.") -> You and your mount crash down on the target. You move towards the target and your mount makes a Heavy attack against it. On damage, the target is knocked prone. | G8: =IFERROR(__xludf.DUMMYFUNCTION("""COMPUTED_VALUE"""),"You are mounted on a flying mount and the target is at least 20ft below you.") -> You are mounted on a flying mount and the target is at least 20ft below you. | H8: =IFERROR(__xludf.DUMMYFUNCTION("""COMPUTED_VALUE"""),"2 AP") -> 2 AP | I8: =IFERROR(__xludf.DUMMYFUNCTION("""COMPUTED_VALUE"""),"2 AP") -> 2 AP | J8: =IFERROR(__xludf.DUMMYFUNCTION("""COMPUTED_VALUE"""),"") | K8: =IFERROR(__xludf.DUMMYFUNCTION("""COMPUTED_VALUE"""),"") | L8: =IFERROR(__xludf.DUMMYFUNCTION("""COMPUTED_VALUE"""),"")
B9: =IFERROR(__xludf.DUMMYFUNCTION("""COMPUTED_VALUE"""),"Aerial Loop") -> Aerial Loop | D9: =IFERROR(__xludf.DUMMYFUNCTION("""COMPUTED_VALUE"""),"") | E9: =IFERROR(__xludf.DUMMYFUNCTION("""COMPUTED_VALUE"""),"Self or Mount") -> Self or Mount | F9: =IFERROR(__xludf.DUMMYFUNCTION("""COMPUTED_VALUE"""),"You and your mount take the Dodge action and gain a +5 bonus to evasion against the attack.") -> You and your mount take the Dodge action and gain a +5 bonus to evasion against the attack. | G9: =IFERROR(__xludf.DUMMYFUNCTION("""COMPUTED_VALUE"""),"You are mounted on a flying mount and you or your mount are the target of a ranged attack") -> You are mounted on a flying mount and you or your mount are the target of a ranged attack | H9: =IFERROR(__xludf.DUMMYFUNCTION("""COMPUTED_VALUE"""),"1 MP, 1 RP") -> 1 MP, 1 RP | I9: =IFERROR(__xludf.DUMMYFUNCTION("""COMPUTED_VALUE"""),"") | J9: =IFERROR(__xludf.DUMMYFUNCTION("""COMPUTED_VALUE"""),"1 MP") -> 1 MP | K9: =IFERROR(__xludf.DUMMYFUNCTION("""COMPUTED_VALUE"""),"1 RP") -> 1 RP | L9: =IFERROR(__xludf.DUMMYFUNCTION("""COMPUTED_VALUE"""),"")
B10: =IFERROR(__xludf.DUMMYFUNCTION("""COMPUTED_VALUE"""),"Aerial Mode Switch") -> Aerial Mode Switch | D10: =IFERROR(__xludf.DUMMYFUNCTION("""COMPUTED_VALUE"""),"Quick, Rapid, Aerial Mage") -> Quick, Rapid, Aerial Mage | E10: =IFERROR(__xludf.DUMMYFUNCTION("""COMPUTED_VALUE"""),"Self") -> Self | F10: =IFERROR(__xludf.DUMMYFUNCTION("""COMPUTED_VALUE"""),"You switch between hover and aerial mode. Hover mode allows you to attack with normal attacks with one hand. Your airships movement speed is reduced to 10ft while in hover mode. While in Aerial Mode you cannot use any attacks or actions that are not airsh"&"ip weapons or have the Aerial Mage keyword.") -> You switch between hover and aerial mode. Hover mode allows you to attack with normal attacks with one hand. Your airships movement speed is reduced to 10ft while in hover mode. While in Aerial Mode you cannot use any attacks or actions that are not airship weapons or have the Aerial Mage keyword. | G10: =IFERROR(__xludf.DUMMYFUNCTION("""COMPUTED_VALUE"""),"Riding Aerial Staff.") -> Riding Aerial Staff. | H10: =IFERROR(__xludf.DUMMYFUNCTION("""COMPUTED_VALUE"""),"0 AP") -> 0 AP | I10: =IFERROR(__xludf.DUMMYFUNCTION("""COMPUTED_VALUE"""),"0 AP") -> 0 AP | J10: =IFERROR(__xludf.DUMMYFUNCTION("""COMPUTED_VALUE"""),"") | K10: =IFERROR(__xludf.DUMMYFUNCTION("""COMPUTED_VALUE"""),"") | L10: =IFERROR(__xludf.DUMMYFUNCTION("""COMPUTED_VALUE"""),"")
B11: =IFERROR(__xludf.DUMMYFUNCTION("""COMPUTED_VALUE"""),"Aftershock") -> Aftershock | D11: =IFERROR(__xludf.DUMMYFUNCTION("""COMPUTED_VALUE"""),"Rage, Half Pierce") -> Rage, Half Pierce | E11: =IFERROR(__xludf.DUMMYFUNCTION("""COMPUTED_VALUE"""),"Melee Weapon Range") -> Melee Weapon Range | F11: =IFERROR(__xludf.DUMMYFUNCTION("""COMPUTED_VALUE"""),"You attack with such force that you create aftershocks when you miss your attack, dealing Half Pierce Physical Damage equal to your Power to the target and all enemies within 5ft of it. If the target Dodged the triggering attack, this damage is reduced to"&" half your Power instead. If your attack targets multiple enemies, this only applies if you miss all enemies.") -> You attack with such force that you create aftershocks when you miss your attack, dealing Half Pierce Physical Damage equal to your Power to the target and all enemies within 5ft of it. If the target Dodged the triggering attack, this damage is reduced to half your Power instead. If your attack targets multiple enemies, this only applies if you miss all enemies. | G11: =IFERROR(__xludf.DUMMYFUNCTION("""COMPUTED_VALUE"""),"You missed a Heavy melee attack with a Two-Handed Melee Weapon.") -> You missed a Heavy melee attack with a Two-Handed Melee Weapon. | H11: =IFERROR(__xludf.DUMMYFUNCTION("""COMPUTED_VALUE"""),"1 MP, 0 RP") -> 1 MP, 0 RP | I11: =IFERROR(__xludf.DUMMYFUNCTION("""COMPUTED_VALUE"""),"") | J11: =IFERROR(__xludf.DUMMYFUNCTION("""COMPUTED_VALUE"""),"1 MP") -> 1 MP | K11: =IFERROR(__xludf.DUMMYFUNCTION("""COMPUTED_VALUE"""),"0 RP") -> 0 RP | L11: =IFERROR(__xludf.DUMMYFUNCTION("""COMPUTED_VALUE"""),"")
B12: =IFERROR(__xludf.DUMMYFUNCTION("""COMPUTED_VALUE"""),"Aimed Shot") -> Aimed Shot | D12: =IFERROR(__xludf.DUMMYFUNCTION("""COMPUTED_VALUE"""),"Lock On") -> Lock On | E12: =IFERROR(__xludf.DUMMYFUNCTION("""COMPUTED_VALUE"""),"Ranged Weapon Range") -> Ranged Weapon Range | F12: =IFERROR(__xludf.DUMMYFUNCTION("""COMPUTED_VALUE"""),"You make a Heavy Attack against the target.") -> You make a Heavy Attack against the target. | G12: =IFERROR(__xludf.DUMMYFUNCTION("""COMPUTED_VALUE"""),"") | H12: =IFERROR(__xludf.DUMMYFUNCTION("""COMPUTED_VALUE"""),"2 AP, 2 MP") -> 2 AP, 2 MP | I12: =IFERROR(__xludf.DUMMYFUNCTION("""COMPUTED_VALUE"""),"2 AP") -> 2 AP | J12: =IFERROR(__xludf.DUMMYFUNCTION("""COMPUTED_VALUE"""),"2 MP") -> 2 MP | K12: =IFERROR(__xludf.DUMMYFUNCTION("""COMPUTED_VALUE"""),"") | L12: =IFERROR(__xludf.DUMMYFUNCTION("""COMPUTED_VALUE"""),"")
B13: =IFERROR(__xludf.DUMMYFUNCTION("""COMPUTED_VALUE"""),"Airheart Gravity Turn") -> Airheart Gravity Turn | D13: =IFERROR(__xludf.DUMMYFUNCTION("""COMPUTED_VALUE"""),"Aerial Mage") -> Aerial Mage | E13: =IFERROR(__xludf.DUMMYFUNCTION("""COMPUTED_VALUE"""),"Self") -> Self | F13: =IFERROR(__xludf.DUMMYFUNCTION("""COMPUTED_VALUE"""),"You drop 25 feet altitude in order to immediately change direction. Can be used mid movement, all leftover movement can carry over into the new direction.") -> You drop 25 feet altitude in order to immediately change direction. Can be used mid movement, all leftover movement can carry over into the new direction. | G13: =IFERROR(__xludf.DUMMYFUNCTION("""COMPUTED_VALUE"""),"Must be at least 30ft in the sky and on an aerial staff in Aerial mode") -> Must be at least 30ft in the sky and on an aerial staff in Aerial mode | H13: =IFERROR(__xludf.DUMMYFUNCTION("""COMPUTED_VALUE"""),"1 MP, 0 RP") -> 1 MP, 0 RP | I13: =IFERROR(__xludf.DUMMYFUNCTION("""COMPUTED_VALUE"""),"") | J13: =IFERROR(__xludf.DUMMYFUNCTION("""COMPUTED_VALUE"""),"1 MP") -> 1 MP | K13: =IFERROR(__xludf.DUMMYFUNCTION("""COMPUTED_VALUE"""),"0 RP") -> 0 RP | L13: =IFERROR(__xludf.DUMMYFUNCTION("""COMPUTED_VALUE"""),"")
B14: =IFERROR(__xludf.DUMMYFUNCTION("""COMPUTED_VALUE"""),"Alarm Ward") -> Alarm Ward | D14: =IFERROR(__xludf.DUMMYFUNCTION("""COMPUTED_VALUE"""),"Bounded Field, Spell") -> Bounded Field, Spell | E14: =IFERROR(__xludf.DUMMYFUNCTION("""COMPUTED_VALUE"""),"Touch") -> Touch | F14: =IFERROR(__xludf.DUMMYFUNCTION("""COMPUTED_VALUE"""),"A ward that can be placed on a normal-sized room or can be combined to ward off a house or larger area. Each ward can cover a 40ft radius. For each Alarm Ward placed in the same area as another Alarm Ward, this radius increases by 40ft (For example, 120ft"&" with 3 Alarm Wards). If someone other than you passes through the ward, the ward triggers creating a loud ringing noise that persists until the ward is disabled. Casting this takes 10 minutes of uninterrupted casting. Once triggered, the field remains ac"&"tive for 5 more minutes before vanishing. At the time of casting, you may choose people that can pass through the barrier without triggering it. If not triggered, Alarm Ward lasts until you remove it. For each Alarm Ward you maintain, your maximum mana is"&" reduced by 1. This is considered a tier 1 ward.") -> A ward that can be placed on a normal-sized room or can be combined to ward off a house or larger area. Each ward can cover a 40ft radius. For each Alarm Ward placed in the same area as another Alarm Ward, this radius increases by 40ft (For example, 120ft with 3 Alarm Wards). If someone other than you passes through the ward, the ward triggers creating a loud ringing noise that persists until the ward is disabled. Casting this takes 10 minutes of uninterrupted casting. Once triggered, the field remains active for 5 more minutes before vanishing. At the time of casting, you may choose people that can pass through the barrier without triggering it. If not triggered, Alarm Ward lasts until you remove it. For each Alarm Ward you maintain, your maximum mana is reduced by 1. This is considered a tier 1 ward. | G14: =IFERROR(__xludf.DUMMYFUNCTION("""COMPUTED_VALUE"""),"") | H14: =IFERROR(__xludf.DUMMYFUNCTION("""COMPUTED_VALUE"""),"1 MP") -> 1 MP | I14: =IFERROR(__xludf.DUMMYFUNCTION("""COMPUTED_VALUE"""),"") | J14: =IFERROR(__xludf.DUMMYFUNCTION("""COMPUTED_VALUE"""),"1 MP") -> 1 MP | K14: =IFERROR(__xludf.DUMMYFUNCTION("""COMPUTED_VALUE"""),"") | L14: =IFERROR(__xludf.DUMMYFUNCTION("""COMPUTED_VALUE"""),"")
B15: =IFERROR(__xludf.DUMMYFUNCTION("""COMPUTED_VALUE"""),"Alchemeister Core Crafting") -> Alchemeister Core Crafting | D15: =IFERROR(__xludf.DUMMYFUNCTION("""COMPUTED_VALUE"""),"") | E15: =IFERROR(__xludf.DUMMYFUNCTION("""COMPUTED_VALUE"""),"") | F15: =IFERROR(__xludf.DUMMYFUNCTION("""COMPUTED_VALUE"""),"Masterful Dilution Cost: 40 Crafting Points Description: By diluting the contents to the perfect required amounts, you gain an additional Elixir, Potion, Flask, Potion or Salve upon crafting success. Stacks with Efficient Dilution. Distillation Cost: 40 C"&"rafting Points Description: You extract the highest quality healing materials from herbs, granting Healing +8 to a Potion with a heal or shielding effect. Explosive Lining Cost: 10 Crafting Points Description: You carefully add an alchemical compound to a"&" pressurized Flask. If the Flask has an area of effect, increases the area by another 5ft (example a 10ft radius becomes 15ft radius). Purify Elixir Cost: 40 Crafting Points Description: You reduce the toxicity of an Elixir that has been detoxified while "&"still maintaining its effect, reducing the damage from taking an Elixir by an additional 5.") -> Masterful Dilution Cost: 40 Crafting Points Description: By diluting the contents to the perfect required amounts, you gain an additional Elixir, Potion, Flask, Potion or Salve upon crafting success. Stacks with Efficient Dilution. Distillation Cost: 40 Crafting Points Description: You extract the highest quality healing materials from herbs, granting Healing +8 to a Potion with a heal or shielding effect. Explosive Lining Cost: 10 Crafting Points Description: You carefully add an alchemical compound to a pressurized Flask. If the Flask has an area of effect, increases the area by another 5ft (example a 10ft radius becomes 15ft radius). Purify Elixir Cost: 40 Crafting Points Description: You reduce the toxicity of an Elixir that has been detoxified while still maintaining its effect, reducing the damage from taking an Elixir by an additional 5. | G15: =IFERROR(__xludf.DUMMYFUNCTION("""COMPUTED_VALUE"""),"") | H15: =IFERROR(__xludf.DUMMYFUNCTION("""COMPUTED_VALUE"""),"") | I15: =IFERROR(__xludf.DUMMYFUNCTION("""COMPUTED_VALUE"""),"") | J15: =IFERROR(__xludf.DUMMYFUNCTION("""COMPUTED_VALUE"""),"") | K15: =IFERROR(__xludf.DUMMYFUNCTION("""COMPUTED_VALUE"""),"") | L15: =IFERROR(__xludf.DUMMYFUNCTION("""COMPUTED_VALUE"""),"")
B16: =IFERROR(__xludf.DUMMYFUNCTION("""COMPUTED_VALUE"""),"Alchemical Detonation") -> Alchemical Detonation | D16: =IFERROR(__xludf.DUMMYFUNCTION("""COMPUTED_VALUE"""),"Rapid") -> Rapid | E16: =IFERROR(__xludf.DUMMYFUNCTION("""COMPUTED_VALUE"""),"5ft") -> 5ft | F16: =IFERROR(__xludf.DUMMYFUNCTION("""COMPUTED_VALUE"""),"You touch a wall, door or container in front of you, which shatters from deconstructive force, becoming destroyed. Can destroy up to a 5ftx5ft segment of wall. Only affects objects made out of common building materials (wood, clay, stone, iron etc), how"&"ever it affects all walls made out of player abilities. The GM determines if the object is detonateable. You can then take a movement action to move 5ft into the space where the wall was.") -> You touch a wall, door or container in front of you, which shatters from deconstructive force, becoming destroyed. Can destroy up to a 5ftx5ft segment of wall. Only affects objects made out of common building materials (wood, clay, stone, iron etc), however it affects all walls made out of player abilities. The GM determines if the object is detonateable. You can then take a movement action to move 5ft into the space where the wall was. | G16: =IFERROR(__xludf.DUMMYFUNCTION("""COMPUTED_VALUE"""),"") | H16: =IFERROR(__xludf.DUMMYFUNCTION("""COMPUTED_VALUE"""),"1 AP") -> 1 AP | I16: =IFERROR(__xludf.DUMMYFUNCTION("""COMPUTED_VALUE"""),"1 AP") -> 1 AP | J16: =IFERROR(__xludf.DUMMYFUNCTION("""COMPUTED_VALUE"""),"") | K16: =IFERROR(__xludf.DUMMYFUNCTION("""COMPUTED_VALUE"""),"") | L16: =IFERROR(__xludf.DUMMYFUNCTION("""COMPUTED_VALUE"""),"")
B17: =IFERROR(__xludf.DUMMYFUNCTION("""COMPUTED_VALUE"""),"Alchemist Core Crafting") -> Alchemist Core Crafting | D17: =IFERROR(__xludf.DUMMYFUNCTION("""COMPUTED_VALUE"""),"") | E17: =IFERROR(__xludf.DUMMYFUNCTION("""COMPUTED_VALUE"""),"") | F17: =IFERROR(__xludf.DUMMYFUNCTION("""COMPUTED_VALUE"""),"Efficient Dilution Cost: 10 Crafting Points Description: By diluting the contents to the perfect required amounts, you gain an additional Elixir, Potion, Flask, Poison or Salve upon crafting success. Stone Grinding Cost: 10 Crafting Points Description: Yo"&"u extract the highest quality healing materials from herbs, granting Healing +5 to a Potion with a heal or shielding effect. Pressurization Cost: 10 Crafting Points Description: You pressurize a Flask carefully. If the Flask has an area of effect, increas"&"es the area by 5ft (example a 10ft radius becomes 15ft radius). Volatile Flask Cost: 10 Crafting Points Description: You overload the active ingredients on a Flask, giving it a +5 damage to its damaging effects. Detoxify Elixir Cost: 10 Crafting Points De"&"scription: You reduce the toxicity of an Elixir while still maintaining its effect, reducing the damage from taking an Elixir by 3. Create Oil Coating Cost: Errand Description: You create an Oil Coating from Carpenter materials. See Items: Carpenter Mat"&"erials") -> Efficient Dilution Cost: 10 Crafting Points Description: By diluting the contents to the perfect required amounts, you gain an additional Elixir, Potion, Flask, Poison or Salve upon crafting success. Stone Grinding Cost: 10 Crafting Points Description: You extract the highest quality healing materials from herbs, granting Healing +5 to a Potion with a heal or shielding effect. Pressurization Cost: 10 Crafting Points Description: You pressurize a Flask carefully. If the Flask has an area of effect, increases the area by 5ft (example a 10ft radius becomes 15ft radius). Volatile Flask Cost: 10 Crafting Points Description: You overload the active ingredients on a Flask, giving it a +5 damage to its damaging effects. Detoxify Elixir Cost: 10 Crafting Points Description: You reduce the toxicity of an Elixir while still maintaining its effect, reducing the damage from taking an Elixir by 3. Create Oil Coating Cost: Errand Description: You create an Oil Coating from Carpenter materials. See Items: Carpenter Materials | G17: =IFERROR(__xludf.DUMMYFUNCTION("""COMPUTED_VALUE"""),"") | H17: =IFERROR(__xludf.DUMMYFUNCTION("""COMPUTED_VALUE"""),"") | I17: =IFERROR(__xludf.DUMMYFUNCTION("""COMPUTED_VALUE"""),"") | J17: =IFERROR(__xludf.DUMMYFUNCTION("""COMPUTED_VALUE"""),"") | K17: =IFERROR(__xludf.DUMMYFUNCTION("""COMPUTED_VALUE"""),"") | L17: =IFERROR(__xludf.DUMMYFUNCTION("""COMPUTED_VALUE"""),"")
B18: =IFERROR(__xludf.DUMMYFUNCTION("""COMPUTED_VALUE"""),"Allow me to clean that~") -> Allow me to clean that~ | D18: =IFERROR(__xludf.DUMMYFUNCTION("""COMPUTED_VALUE"""),"Rapid") -> Rapid | E18: =IFERROR(__xludf.DUMMYFUNCTION("""COMPUTED_VALUE"""),"5ft") -> 5ft | F18: =IFERROR(__xludf.DUMMYFUNCTION("""COMPUTED_VALUE"""),"You instantly remove a negative effect from the terrain (such as Oil Slick, Sheet Ice, Web etc). Permanent effects such as fissure or effects with HP like a wall cannot be removed with this. A maximum of 15x15ft can be removed in 1 use and you may move to"&" any spot of the cleaned terrain afterwards. In addition, you may target an ally with this to remove 1 negative physical effect from them instead.") -> You instantly remove a negative effect from the terrain (such as Oil Slick, Sheet Ice, Web etc). Permanent effects such as fissure or effects with HP like a wall cannot be removed with this. A maximum of 15x15ft can be removed in 1 use and you may move to any spot of the cleaned terrain afterwards. In addition, you may target an ally with this to remove 1 negative physical effect from them instead. | G18: =IFERROR(__xludf.DUMMYFUNCTION("""COMPUTED_VALUE"""),"") | H18: =IFERROR(__xludf.DUMMYFUNCTION("""COMPUTED_VALUE"""),"1 AP, 1 MP") -> 1 AP, 1 MP | I18: =IFERROR(__xludf.DUMMYFUNCTION("""COMPUTED_VALUE"""),"1 AP") -> 1 AP | J18: =IFERROR(__xludf.DUMMYFUNCTION("""COMPUTED_VALUE"""),"1 MP") -> 1 MP | K18: =IFERROR(__xludf.DUMMYFUNCTION("""COMPUTED_VALUE"""),"") | L18: =IFERROR(__xludf.DUMMYFUNCTION("""COMPUTED_VALUE"""),"")
B19: =IFERROR(__xludf.DUMMYFUNCTION("""COMPUTED_VALUE"""),"Always Prepared") -> Always Prepared | D19: =IFERROR(__xludf.DUMMYFUNCTION("""COMPUTED_VALUE"""),"Flashback") -> Flashback | E19: =IFERROR(__xludf.DUMMYFUNCTION("""COMPUTED_VALUE"""),"Self") -> Self | F19: =IFERROR(__xludf.DUMMYFUNCTION("""COMPUTED_VALUE"""),"You immediately purchase a single base item with no mods that is worth 1000 clim or less (base cost). You can immediately use the draw/stow action and equip this item into your hand. Can only be used once per arc.") -> You immediately purchase a single base item with no mods that is worth 1000 clim or less (base cost). You can immediately use the draw/stow action and equip this item into your hand. Can only be used once per arc. | G19: =IFERROR(__xludf.DUMMYFUNCTION("""COMPUTED_VALUE"""),"") | H19: =IFERROR(__xludf.DUMMYFUNCTION("""COMPUTED_VALUE"""),"1 MP, 0 RP") -> 1 MP, 0 RP | I19: =IFERROR(__xludf.DUMMYFUNCTION("""COMPUTED_VALUE"""),"") | J19: =IFERROR(__xludf.DUMMYFUNCTION("""COMPUTED_VALUE"""),"1 MP") -> 1 MP | K19: =IFERROR(__xludf.DUMMYFUNCTION("""COMPUTED_VALUE"""),"0 RP") -> 0 RP | L19: =IFERROR(__xludf.DUMMYFUNCTION("""COMPUTED_VALUE"""),"")
B20: =IFERROR(__xludf.DUMMYFUNCTION("""COMPUTED_VALUE"""),"Ambush Trapper") -> Ambush Trapper | D20: =IFERROR(__xludf.DUMMYFUNCTION("""COMPUTED_VALUE"""),"Encounter Start") -> Encounter Start | E20: =IFERROR(__xludf.DUMMYFUNCTION("""COMPUTED_VALUE"""),"Self") -> Self | F20: =IFERROR(__xludf.DUMMYFUNCTION("""COMPUTED_VALUE"""),"You may use Place Trap’s 0 RP effect once this encounter, even if you didn’t spend the time to set it up. The GM may rule that the pitfall and net options are unavailable based on the situation. These activations still cost a Trap when used (but not if yo"&"u don't use them).") -> You may use Place Trap’s 0 RP effect once this encounter, even if you didn’t spend the time to set it up. The GM may rule that the pitfall and net options are unavailable based on the situation. These activations still cost a Trap when used (but not if you don't use them). | G20: =IFERROR(__xludf.DUMMYFUNCTION("""COMPUTED_VALUE"""),"Must be stealthed or have surprised the enemy.") -> Must be stealthed or have surprised the enemy. | H20: =IFERROR(__xludf.DUMMYFUNCTION("""COMPUTED_VALUE"""),"") | I20: =IFERROR(__xludf.DUMMYFUNCTION("""COMPUTED_VALUE"""),"") | J20: =IFERROR(__xludf.DUMMYFUNCTION("""COMPUTED_VALUE"""),"") | K20: =IFERROR(__xludf.DUMMYFUNCTION("""COMPUTED_VALUE"""),"") | L20: =IFERROR(__xludf.DUMMYFUNCTION("""COMPUTED_VALUE"""),"")
B21: =IFERROR(__xludf.DUMMYFUNCTION("""COMPUTED_VALUE"""),"Amoxicillin") -> Amoxicillin | D21: =IFERROR(__xludf.DUMMYFUNCTION("""COMPUTED_VALUE"""),"Concentration, Healing, Spell") -> Concentration, Healing, Spell | E21: =IFERROR(__xludf.DUMMYFUNCTION("""COMPUTED_VALUE"""),"30ft") -> 30ft | F21: =IFERROR(__xludf.DUMMYFUNCTION("""COMPUTED_VALUE"""),"You choose up to 10 willing units in range. After spending 1 minute in concentration, you create a cloud of spores that heals a disease that you can identify.") -> You choose up to 10 willing units in range. After spending 1 minute in concentration, you create a cloud of spores that heals a disease that you can identify. | G21: =IFERROR(__xludf.DUMMYFUNCTION("""COMPUTED_VALUE"""),"You can identify the disease.") -> You can identify the disease. | H21: =IFERROR(__xludf.DUMMYFUNCTION("""COMPUTED_VALUE"""),"") | I21: =IFERROR(__xludf.DUMMYFUNCTION("""COMPUTED_VALUE"""),"") | J21: =IFERROR(__xludf.DUMMYFUNCTION("""COMPUTED_VALUE"""),"") | K21: =IFERROR(__xludf.DUMMYFUNCTION("""COMPUTED_VALUE"""),"") | L21: =IFERROR(__xludf.DUMMYFUNCTION("""COMPUTED_VALUE"""),"")
B22: =IFERROR(__xludf.DUMMYFUNCTION("""COMPUTED_VALUE"""),"Amphibious") -> Amphibious | D22: =IFERROR(__xludf.DUMMYFUNCTION("""COMPUTED_VALUE"""),"") | E22: =IFERROR(__xludf.DUMMYFUNCTION("""COMPUTED_VALUE"""),"") | F22: =IFERROR(__xludf.DUMMYFUNCTION("""COMPUTED_VALUE"""),"You can swim up to your speed and can hold your breath underwater for up to an hour.") -> You can swim up to your speed and can hold your breath underwater for up to an hour. | G22: =IFERROR(__xludf.DUMMYFUNCTION("""COMPUTED_VALUE"""),"") | H22: =IFERROR(__xludf.DUMMYFUNCTION("""COMPUTED_VALUE"""),"") | I22: =IFERROR(__xludf.DUMMYFUNCTION("""COMPUTED_VALUE"""),"") | J22: =IFERROR(__xludf.DUMMYFUNCTION("""COMPUTED_VALUE"""),"") | K22: =IFERROR(__xludf.DUMMYFUNCTION("""COMPUTED_VALUE"""),"") | L22: =IFERROR(__xludf.DUMMYFUNCTION("""COMPUTED_VALUE"""),"")
B23: =IFERROR(__xludf.DUMMYFUNCTION("""COMPUTED_VALUE"""),"Anathema") -> Anathema | D23: =IFERROR(__xludf.DUMMYFUNCTION("""COMPUTED_VALUE"""),"Curse, Spell") -> Curse, Spell | E23: =IFERROR(__xludf.DUMMYFUNCTION("""COMPUTED_VALUE"""),"60ft") -> 60ft | F23: =IFERROR(__xludf.DUMMYFUNCTION("""COMPUTED_VALUE"""),"You choose one target unit and they must save against your Potency or be afflicted by Anathema. Anathema increases the next source of damage that the target receives by your Heavy Attack damage.") -> You choose one target unit and they must save against your Potency or be afflicted by Anathema. Anathema increases the next source of damage that the target receives by your Heavy Attack damage. | G23: =IFERROR(__xludf.DUMMYFUNCTION("""COMPUTED_VALUE"""),"") | H23: =IFERROR(__xludf.DUMMYFUNCTION("""COMPUTED_VALUE"""),"2 AP, 2 MP") -> 2 AP, 2 MP | I23: =IFERROR(__xludf.DUMMYFUNCTION("""COMPUTED_VALUE"""),"2 AP") -> 2 AP | J23: =IFERROR(__xludf.DUMMYFUNCTION("""COMPUTED_VALUE"""),"2 MP") -> 2 MP | K23: =IFERROR(__xludf.DUMMYFUNCTION("""COMPUTED_VALUE"""),"") | L23: =IFERROR(__xludf.DUMMYFUNCTION("""COMPUTED_VALUE"""),"")
B24: =IFERROR(__xludf.DUMMYFUNCTION("""COMPUTED_VALUE"""),"Angel's Embrace") -> Angel's Embrace | D24: =IFERROR(__xludf.DUMMYFUNCTION("""COMPUTED_VALUE"""),"Shield, Spell, Aid") -> Shield, Spell, Aid | E24: =IFERROR(__xludf.DUMMYFUNCTION("""COMPUTED_VALUE"""),"15ft") -> 15ft | F24: =IFERROR(__xludf.DUMMYFUNCTION("""COMPUTED_VALUE"""),"You grant the target ally Angel’s Embrace, which grants a Shield against the triggering attack that blocks damage equal to 5 + (2 x Toughness). This Spell does not provoke attacks of opportunity.") -> You grant the target ally Angel’s Embrace, which grants a Shield against the triggering attack that blocks damage equal to 5 + (2 x Toughness). This Spell does not provoke attacks of opportunity. | G24: =IFERROR(__xludf.DUMMYFUNCTION("""COMPUTED_VALUE"""),"A creature other than you is attacked.") -> A creature other than you is attacked. | H24: =IFERROR(__xludf.DUMMYFUNCTION("""COMPUTED_VALUE"""),"1 RP") -> 1 RP | I24: =IFERROR(__xludf.DUMMYFUNCTION("""COMPUTED_VALUE"""),"") | J24: =IFERROR(__xludf.DUMMYFUNCTION("""COMPUTED_VALUE"""),"") | K24: =IFERROR(__xludf.DUMMYFUNCTION("""COMPUTED_VALUE"""),"1 RP") -> 1 RP | L24: =IFERROR(__xludf.DUMMYFUNCTION("""COMPUTED_VALUE"""),"")
B25: =IFERROR(__xludf.DUMMYFUNCTION("""COMPUTED_VALUE"""),"Antennae") -> Antennae | D25: =IFERROR(__xludf.DUMMYFUNCTION("""COMPUTED_VALUE"""),"") | E25: =IFERROR(__xludf.DUMMYFUNCTION("""COMPUTED_VALUE"""),"") | F25: =IFERROR(__xludf.DUMMYFUNCTION("""COMPUTED_VALUE"""),"You are able to detect creatures by sensing the vibrations in the air. You gain a +10 expertise bonus to Perception (Vibration Sense) which works up to 40ft from you, but only detects creatures.") -> You are able to detect creatures by sensing the vibrations in the air. You gain a +10 expertise bonus to Perception (Vibration Sense) which works up to 40ft from you, but only detects creatures. | G25: =IFERROR(__xludf.DUMMYFUNCTION("""COMPUTED_VALUE"""),"") | H25: =IFERROR(__xludf.DUMMYFUNCTION("""COMPUTED_VALUE"""),"") | I25: =IFERROR(__xludf.DUMMYFUNCTION("""COMPUTED_VALUE"""),"") | J25: =IFERROR(__xludf.DUMMYFUNCTION("""COMPUTED_VALUE"""),"") | K25: =IFERROR(__xludf.DUMMYFUNCTION("""COMPUTED_VALUE"""),"") | L25: =IFERROR(__xludf.DUMMYFUNCTION("""COMPUTED_VALUE"""),"")
B26: =IFERROR(__xludf.DUMMYFUNCTION("""COMPUTED_VALUE"""),"Anti-Magic Shield") -> Anti-Magic Shield | D26: =IFERROR(__xludf.DUMMYFUNCTION("""COMPUTED_VALUE"""),"Aid, Arcane, Shield, Spell") -> Aid, Arcane, Shield, Spell | E26: =IFERROR(__xludf.DUMMYFUNCTION("""COMPUTED_VALUE"""),"60ft") -> 60ft | F26: =IFERROR(__xludf.DUMMYFUNCTION("""COMPUTED_VALUE"""),"You grant the target ally 1 RP that must be spend on a basic Dodge or Block action against the triggering attack as well as Anti-Magic Shield for the triggering attack. Anti-Magic Shield reduces the damage the target ally takes by your Focus.") -> You grant the target ally 1 RP that must be spend on a basic Dodge or Block action against the triggering attack as well as Anti-Magic Shield for the triggering attack. Anti-Magic Shield reduces the damage the target ally takes by your Focus. | G26: =IFERROR(__xludf.DUMMYFUNCTION("""COMPUTED_VALUE"""),"Ally is the target of a damage dealing Spell.") -> Ally is the target of a damage dealing Spell. | H26: =IFERROR(__xludf.DUMMYFUNCTION("""COMPUTED_VALUE"""),"1 RP") -> 1 RP | I26: =IFERROR(__xludf.DUMMYFUNCTION("""COMPUTED_VALUE"""),"") | J26: =IFERROR(__xludf.DUMMYFUNCTION("""COMPUTED_VALUE"""),"") | K26: =IFERROR(__xludf.DUMMYFUNCTION("""COMPUTED_VALUE"""),"1 RP") -> 1 RP | L26: =IFERROR(__xludf.DUMMYFUNCTION("""COMPUTED_VALUE"""),"")
B27: =IFERROR(__xludf.DUMMYFUNCTION("""COMPUTED_VALUE"""),"Anti-Shield") -> Anti-Shield | D27: =IFERROR(__xludf.DUMMYFUNCTION("""COMPUTED_VALUE"""),"Arcane, Spell") -> Arcane, Spell | E27: =IFERROR(__xludf.DUMMYFUNCTION("""COMPUTED_VALUE"""),"60ft") -> 60ft | F27: =IFERROR(__xludf.DUMMYFUNCTION("""COMPUTED_VALUE"""),"You weave a web of magic around the target. The target cannot be the target of any abilities with the Shield keyword until the start of your next turn.") -> You weave a web of magic around the target. The target cannot be the target of any abilities with the Shield keyword until the start of your next turn. | G27: =IFERROR(__xludf.DUMMYFUNCTION("""COMPUTED_VALUE"""),"") | H27: =IFERROR(__xludf.DUMMYFUNCTION("""COMPUTED_VALUE"""),"1 AP") -> 1 AP | I27: =IFERROR(__xludf.DUMMYFUNCTION("""COMPUTED_VALUE"""),"1 AP") -> 1 AP | J27: =IFERROR(__xludf.DUMMYFUNCTION("""COMPUTED_VALUE"""),"") | K27: =IFERROR(__xludf.DUMMYFUNCTION("""COMPUTED_VALUE"""),"") | L27: =IFERROR(__xludf.DUMMYFUNCTION("""COMPUTED_VALUE"""),"")
B28: =IFERROR(__xludf.DUMMYFUNCTION("""COMPUTED_VALUE"""),"Anvil Tactics") -> Anvil Tactics | D28: =IFERROR(__xludf.DUMMYFUNCTION("""COMPUTED_VALUE"""),"") | E28: =IFERROR(__xludf.DUMMYFUNCTION("""COMPUTED_VALUE"""),"80ft") -> 80ft | F28: =IFERROR(__xludf.DUMMYFUNCTION("""COMPUTED_VALUE"""),"A single ally in range may move up to their speed. If they end up in melee range of an enemy and there is an ally on the direct opposite side of that enemy, they may make an Attack of Opportunity. This attack gains Lock On.") -> A single ally in range may move up to their speed. If they end up in melee range of an enemy and there is an ally on the direct opposite side of that enemy, they may make an Attack of Opportunity. This attack gains Lock On. | G28: =IFERROR(__xludf.DUMMYFUNCTION("""COMPUTED_VALUE"""),"") | H28: =IFERROR(__xludf.DUMMYFUNCTION("""COMPUTED_VALUE"""),"1 AP, 1 MP") -> 1 AP, 1 MP | I28: =IFERROR(__xludf.DUMMYFUNCTION("""COMPUTED_VALUE"""),"1 AP") -> 1 AP | J28: =IFERROR(__xludf.DUMMYFUNCTION("""COMPUTED_VALUE"""),"1 MP") -> 1 MP | K28: =IFERROR(__xludf.DUMMYFUNCTION("""COMPUTED_VALUE"""),"") | L28: =IFERROR(__xludf.DUMMYFUNCTION("""COMPUTED_VALUE"""),"")
B29: =IFERROR(__xludf.DUMMYFUNCTION("""COMPUTED_VALUE"""),"Aqua Drill") -> Aqua Drill | D29: =IFERROR(__xludf.DUMMYFUNCTION("""COMPUTED_VALUE"""),"Safe, Water") -> Safe, Water | E29: =IFERROR(__xludf.DUMMYFUNCTION("""COMPUTED_VALUE"""),"60ft") -> 60ft | F29: =IFERROR(__xludf.DUMMYFUNCTION("""COMPUTED_VALUE"""),"You infuse water with your mana firing a spiraling blast of high pressure water, making a heavy attack that deals Water damage against a target within range. You can use either the RP or AP cost for the ability. The water is used as a projectile and spil"&"ls anywhere within 5ft of the target at your choice. If you use an RP for this ability, the mana cost increases by 1.") -> You infuse water with your mana firing a spiraling blast of high pressure water, making a heavy attack that deals Water damage against a target within range. You can use either the RP or AP cost for the ability. The water is used as a projectile and spills anywhere within 5ft of the target at your choice. If you use an RP for this ability, the mana cost increases by 1. | G29: =IFERROR(__xludf.DUMMYFUNCTION("""COMPUTED_VALUE"""),"You are touching an amount of water equal to a normal sized bucket of water.") -> You are touching an amount of water equal to a normal sized bucket of water. | H29: =IFERROR(__xludf.DUMMYFUNCTION("""COMPUTED_VALUE"""),"2 AP, 1 RP") -> 2 AP, 1 RP | I29: =IFERROR(__xludf.DUMMYFUNCTION("""COMPUTED_VALUE"""),"2 AP") -> 2 AP | J29: =IFERROR(__xludf.DUMMYFUNCTION("""COMPUTED_VALUE"""),"") | K29: =IFERROR(__xludf.DUMMYFUNCTION("""COMPUTED_VALUE"""),"1 RP") -> 1 RP | L29: =IFERROR(__xludf.DUMMYFUNCTION("""COMPUTED_VALUE"""),"")
B30: =IFERROR(__xludf.DUMMYFUNCTION("""COMPUTED_VALUE"""),"Aquatic Fae") -> Aquatic Fae | D30: =IFERROR(__xludf.DUMMYFUNCTION("""COMPUTED_VALUE"""),"") | E30: =IFERROR(__xludf.DUMMYFUNCTION("""COMPUTED_VALUE"""),"") | F30: =IFERROR(__xludf.DUMMYFUNCTION("""COMPUTED_VALUE"""),"While swimming, your base movement speed becomes 30, in addition you gain Elemental Mastery: Water. Your Aqua Drill costs 0 mana when used as RP ability while in natural water.") -> While swimming, your base movement speed becomes 30, in addition you gain Elemental Mastery: Water. Your Aqua Drill costs 0 mana when used as RP ability while in natural water. | G30: =IFERROR(__xludf.DUMMYFUNCTION("""COMPUTED_VALUE"""),"") | H30: =IFERROR(__xludf.DUMMYFUNCTION("""COMPUTED_VALUE"""),"") | I30: =IFERROR(__xludf.DUMMYFUNCTION("""COMPUTED_VALUE"""),"") | J30: =IFERROR(__xludf.DUMMYFUNCTION("""COMPUTED_VALUE"""),"") | K30: =IFERROR(__xludf.DUMMYFUNCTION("""COMPUTED_VALUE"""),"") | L30: =IFERROR(__xludf.DUMMYFUNCTION("""COMPUTED_VALUE"""),"")
B31: =IFERROR(__xludf.DUMMYFUNCTION("""COMPUTED_VALUE"""),"Arcane Barrier") -> Arcane Barrier | D31: =IFERROR(__xludf.DUMMYFUNCTION("""COMPUTED_VALUE"""),"Shield, Spell") -> Shield, Spell | E31: =IFERROR(__xludf.DUMMYFUNCTION("""COMPUTED_VALUE"""),"Self") -> Self | F31: =IFERROR(__xludf.DUMMYFUNCTION("""COMPUTED_VALUE"""),"You create a Magical Barrier that absorbs damage until it breaks. The barrier has HP equal to 15 + your Focus. The barrier has a Guard of 0 and any damage it takes is subtracted from the barrier’s HP. When the barrier breaks, any remaining damage is subtr"&"acted from your HP. The barrier otherwise lasts until the start of your next turn or until you take any action other than the Block action. This spell does not provoke attacks of opportunity and does not protect against true damage.") -> You create a Magical Barrier that absorbs damage until it breaks. The barrier has HP equal to 15 + your Focus. The barrier has a Guard of 0 and any damage it takes is subtracted from the barrier’s HP. When the barrier breaks, any remaining damage is subtracted from your HP. The barrier otherwise lasts until the start of your next turn or until you take any action other than the Block action. This spell does not provoke attacks of opportunity and does not protect against true damage. | G31: =IFERROR(__xludf.DUMMYFUNCTION("""COMPUTED_VALUE"""),"You're about to take damage.") -> You're about to take damage. | H31: =IFERROR(__xludf.DUMMYFUNCTION("""COMPUTED_VALUE"""),"1 MP, 1 RP") -> 1 MP, 1 RP | I31: =IFERROR(__xludf.DUMMYFUNCTION("""COMPUTED_VALUE"""),"") | J31: =IFERROR(__xludf.DUMMYFUNCTION("""COMPUTED_VALUE"""),"1 MP") -> 1 MP | K31: =IFERROR(__xludf.DUMMYFUNCTION("""COMPUTED_VALUE"""),"1 RP") -> 1 RP | L31: =IFERROR(__xludf.DUMMYFUNCTION("""COMPUTED_VALUE"""),"")
B32: =IFERROR(__xludf.DUMMYFUNCTION("""COMPUTED_VALUE"""),"Arcane Barrier II") -> Arcane Barrier II | D32: =IFERROR(__xludf.DUMMYFUNCTION("""COMPUTED_VALUE"""),"Shield, Spell") -> Shield, Spell | E32: =IFERROR(__xludf.DUMMYFUNCTION("""COMPUTED_VALUE"""),"Self") -> Self | F32: =IFERROR(__xludf.DUMMYFUNCTION("""COMPUTED_VALUE"""),"You create a Magical Barrier that absorbs damage until it breaks. The barrier has HP equal to 15 + your Focus. The barrier has a Guard of 0 + your guard and any damage it takes is subtracted from the barrier’s HP. When the barrier breaks, any remaining da"&"mage is subtracted from your HP. The barrier otherwise lasts until the start of your next turn or until you take any action other than the Block action. If using the Block action while the barrier is active, the guard of the barrier also increases. This s"&"pell does not provoke attacks of opportunity and does not protect against true damage.") -> You create a Magical Barrier that absorbs damage until it breaks. The barrier has HP equal to 15 + your Focus. The barrier has a Guard of 0 + your guard and any damage it takes is subtracted from the barrier’s HP. When the barrier breaks, any remaining damage is subtracted from your HP. The barrier otherwise lasts until the start of your next turn or until you take any action other than the Block action. If using the Block action while the barrier is active, the guard of the barrier also increases. This spell does not provoke attacks of opportunity and does not protect against true damage. | G32: =IFERROR(__xludf.DUMMYFUNCTION("""COMPUTED_VALUE"""),"You're about to take damage.") -> You're about to take damage. | H32: =IFERROR(__xludf.DUMMYFUNCTION("""COMPUTED_VALUE"""),"1 MP, 1 RP") -> 1 MP, 1 RP | I32: =IFERROR(__xludf.DUMMYFUNCTION("""COMPUTED_VALUE"""),"") | J32: =IFERROR(__xludf.DUMMYFUNCTION("""COMPUTED_VALUE"""),"1 MP") -> 1 MP | K32: =IFERROR(__xludf.DUMMYFUNCTION("""COMPUTED_VALUE"""),"1 RP") -> 1 RP | L32: =IFERROR(__xludf.DUMMYFUNCTION("""COMPUTED_VALUE"""),"")
B33: =IFERROR(__xludf.DUMMYFUNCTION("""COMPUTED_VALUE"""),"Arcane Blast") -> Arcane Blast | D33: =IFERROR(__xludf.DUMMYFUNCTION("""COMPUTED_VALUE"""),"Spell, Circuit") -> Spell, Circuit | E33: =IFERROR(__xludf.DUMMYFUNCTION("""COMPUTED_VALUE"""),"60ft") -> 60ft | F33: =IFERROR(__xludf.DUMMYFUNCTION("""COMPUTED_VALUE"""),"You make a Heavy attack that deals Arcane damage against the target.") -> You make a Heavy attack that deals Arcane damage against the target. | G33: =IFERROR(__xludf.DUMMYFUNCTION("""COMPUTED_VALUE"""),"") | H33: =IFERROR(__xludf.DUMMYFUNCTION("""COMPUTED_VALUE"""),"1 AP, 3 MP") -> 1 AP, 3 MP | I33: =IFERROR(__xludf.DUMMYFUNCTION("""COMPUTED_VALUE"""),"1 AP") -> 1 AP | J33: =IFERROR(__xludf.DUMMYFUNCTION("""COMPUTED_VALUE"""),"3 MP") -> 3 MP | K33: =IFERROR(__xludf.DUMMYFUNCTION("""COMPUTED_VALUE"""),"") | L33: =IFERROR(__xludf.DUMMYFUNCTION("""COMPUTED_VALUE"""),"")
B34: =IFERROR(__xludf.DUMMYFUNCTION("""COMPUTED_VALUE"""),"Arcane Buster") -> Arcane Buster | D34: =IFERROR(__xludf.DUMMYFUNCTION("""COMPUTED_VALUE"""),"Arcane, Spell, Shieldbreaker") -> Arcane, Spell, Shieldbreaker | E34: =IFERROR(__xludf.DUMMYFUNCTION("""COMPUTED_VALUE"""),"60ft") -> 60ft | F34: =IFERROR(__xludf.DUMMYFUNCTION("""COMPUTED_VALUE"""),"You fire a blast of energy, making a Heavy Attack that deals Arcane Damage. This attack has the Shieldbreaker property.") -> You fire a blast of energy, making a Heavy Attack that deals Arcane Damage. This attack has the Shieldbreaker property. | G34: =IFERROR(__xludf.DUMMYFUNCTION("""COMPUTED_VALUE"""),"") | H34: =IFERROR(__xludf.DUMMYFUNCTION("""COMPUTED_VALUE"""),"2 AP") -> 2 AP | I34: =IFERROR(__xludf.DUMMYFUNCTION("""COMPUTED_VALUE"""),"2 AP") -> 2 AP | J34: =IFERROR(__xludf.DUMMYFUNCTION("""COMPUTED_VALUE"""),"") | K34: =IFERROR(__xludf.DUMMYFUNCTION("""COMPUTED_VALUE"""),"") | L34: =IFERROR(__xludf.DUMMYFUNCTION("""COMPUTED_VALUE"""),"")
B35: =IFERROR(__xludf.DUMMYFUNCTION("""COMPUTED_VALUE"""),"Arcane Explosion") -> Arcane Explosion | D35: =IFERROR(__xludf.DUMMYFUNCTION("""COMPUTED_VALUE"""),"Arcane, Rapid, Spell, Blanketing, Safe") -> Arcane, Rapid, Spell, Blanketing, Safe | E35: =IFERROR(__xludf.DUMMYFUNCTION("""COMPUTED_VALUE"""),"Self") -> Self | F35: =IFERROR(__xludf.DUMMYFUNCTION("""COMPUTED_VALUE"""),"You make a Light Attack that deals Arcane damage against all enemies within 10ft of yourself. This Spell does not provoke attacks of opportunity.") -> You make a Light Attack that deals Arcane damage against all enemies within 10ft of yourself. This Spell does not provoke attacks of opportunity. | G35: =IFERROR(__xludf.DUMMYFUNCTION("""COMPUTED_VALUE"""),"") | H35: =IFERROR(__xludf.DUMMYFUNCTION("""COMPUTED_VALUE"""),"2 AP") -> 2 AP | I35: =IFERROR(__xludf.DUMMYFUNCTION("""COMPUTED_VALUE"""),"2 AP") -> 2 AP | J35: =IFERROR(__xludf.DUMMYFUNCTION("""COMPUTED_VALUE"""),"") | K35: =IFERROR(__xludf.DUMMYFUNCTION("""COMPUTED_VALUE"""),"") | L35: =IFERROR(__xludf.DUMMYFUNCTION("""COMPUTED_VALUE"""),"")
B36: =IFERROR(__xludf.DUMMYFUNCTION("""COMPUTED_VALUE"""),"Arcane Power") -> Arcane Power | D36: =IFERROR(__xludf.DUMMYFUNCTION("""COMPUTED_VALUE"""),"Arcane") -> Arcane | E36: =IFERROR(__xludf.DUMMYFUNCTION("""COMPUTED_VALUE"""),"Self") -> Self | F36: =IFERROR(__xludf.DUMMYFUNCTION("""COMPUTED_VALUE"""),"You gain Arcane Power, which adds 3 damage to the damage of all your Arcane Damage rolls until the start of your next turn.") -> You gain Arcane Power, which adds 3 damage to the damage of all your Arcane Damage rolls until the start of your next turn. | G36: =IFERROR(__xludf.DUMMYFUNCTION("""COMPUTED_VALUE"""),"") | H36: =IFERROR(__xludf.DUMMYFUNCTION("""COMPUTED_VALUE"""),"0 AP, 3 MP") -> 0 AP, 3 MP | I36: =IFERROR(__xludf.DUMMYFUNCTION("""COMPUTED_VALUE"""),"0 AP") -> 0 AP | J36: =IFERROR(__xludf.DUMMYFUNCTION("""COMPUTED_VALUE"""),"3 MP") -> 3 MP | K36: =IFERROR(__xludf.DUMMYFUNCTION("""COMPUTED_VALUE"""),"") | L36: =IFERROR(__xludf.DUMMYFUNCTION("""COMPUTED_VALUE"""),"")
B37: =IFERROR(__xludf.DUMMYFUNCTION("""COMPUTED_VALUE"""),"Arcane Pull") -> Arcane Pull | D37: =IFERROR(__xludf.DUMMYFUNCTION("""COMPUTED_VALUE"""),"Spell") -> Spell | E37: =IFERROR(__xludf.DUMMYFUNCTION("""COMPUTED_VALUE"""),"40ft") -> 40ft | F37: =IFERROR(__xludf.DUMMYFUNCTION("""COMPUTED_VALUE"""),"You pull the target to an empty square next to you. This movement does not provoke attacks of opportunity. Your next Block or Dodge action against the target before the start of your next turn costs 0 RP. This Spell does not provoke attacks of opportunity"&".") -> You pull the target to an empty square next to you. This movement does not provoke attacks of opportunity. Your next Block or Dodge action against the target before the start of your next turn costs 0 RP. This Spell does not provoke attacks of opportunity. | G37: =IFERROR(__xludf.DUMMYFUNCTION("""COMPUTED_VALUE"""),"Target is challenged by you and attacking someone that isn't you.") -> Target is challenged by you and attacking someone that isn't you. | H37: =IFERROR(__xludf.DUMMYFUNCTION("""COMPUTED_VALUE"""),"1 RP") -> 1 RP | I37: =IFERROR(__xludf.DUMMYFUNCTION("""COMPUTED_VALUE"""),"") | J37: =IFERROR(__xludf.DUMMYFUNCTION("""COMPUTED_VALUE"""),"") | K37: =IFERROR(__xludf.DUMMYFUNCTION("""COMPUTED_VALUE"""),"1 RP") -> 1 RP | L37: =IFERROR(__xludf.DUMMYFUNCTION("""COMPUTED_VALUE"""),"")
B38: =IFERROR(__xludf.DUMMYFUNCTION("""COMPUTED_VALUE"""),"Arcane Rapidfire") -> Arcane Rapidfire | D38: =IFERROR(__xludf.DUMMYFUNCTION("""COMPUTED_VALUE"""),"Spell, Arcane, Circuit") -> Spell, Arcane, Circuit | E38: =IFERROR(__xludf.DUMMYFUNCTION("""COMPUTED_VALUE"""),"60ft") -> 60ft | F38: =IFERROR(__xludf.DUMMYFUNCTION("""COMPUTED_VALUE"""),"You make 4 light attacks that deal Arcane damage against the target.") -> You make 4 light attacks that deal Arcane damage against the target. | G38: =IFERROR(__xludf.DUMMYFUNCTION("""COMPUTED_VALUE"""),"") | H38: =IFERROR(__xludf.DUMMYFUNCTION("""COMPUTED_VALUE"""),"2 AP, 3 MP") -> 2 AP, 3 MP | I38: =IFERROR(__xludf.DUMMYFUNCTION("""COMPUTED_VALUE"""),"2 AP") -> 2 AP | J38: =IFERROR(__xludf.DUMMYFUNCTION("""COMPUTED_VALUE"""),"3 MP") -> 3 MP | K38: =IFERROR(__xludf.DUMMYFUNCTION("""COMPUTED_VALUE"""),"") | L38: =IFERROR(__xludf.DUMMYFUNCTION("""COMPUTED_VALUE"""),"")
B39: =IFERROR(__xludf.DUMMYFUNCTION("""COMPUTED_VALUE"""),"Armor Crushing Shell") -> Armor Crushing Shell | D39: =IFERROR(__xludf.DUMMYFUNCTION("""COMPUTED_VALUE"""),"Artillery, Sunder, Cannon") -> Artillery, Sunder, Cannon | E39: =IFERROR(__xludf.DUMMYFUNCTION("""COMPUTED_VALUE"""),"Ranged Weapon Range") -> Ranged Weapon Range | F39: =IFERROR(__xludf.DUMMYFUNCTION("""COMPUTED_VALUE"""),"You make a Light attack against the target. On damage, you apply Sunder 2 until the start of your next turn.") -> You make a Light attack against the target. On damage, you apply Sunder 2 until the start of your next turn. | G39: =IFERROR(__xludf.DUMMYFUNCTION("""COMPUTED_VALUE"""),"Cannon only.") -> Cannon only. | H39: =IFERROR(__xludf.DUMMYFUNCTION("""COMPUTED_VALUE"""),"1 AP, 1 MP") -> 1 AP, 1 MP | I39: =IFERROR(__xludf.DUMMYFUNCTION("""COMPUTED_VALUE"""),"1 AP") -> 1 AP | J39: =IFERROR(__xludf.DUMMYFUNCTION("""COMPUTED_VALUE"""),"1 MP") -> 1 MP | K39: =IFERROR(__xludf.DUMMYFUNCTION("""COMPUTED_VALUE"""),"") | L39: =IFERROR(__xludf.DUMMYFUNCTION("""COMPUTED_VALUE"""),"")
B40: =IFERROR(__xludf.DUMMYFUNCTION("""COMPUTED_VALUE"""),"Armor Up") -> Armor Up | D40: =IFERROR(__xludf.DUMMYFUNCTION("""COMPUTED_VALUE"""),"Shield") -> Shield | E40: =IFERROR(__xludf.DUMMYFUNCTION("""COMPUTED_VALUE"""),"Self") -> Self | F40: =IFERROR(__xludf.DUMMYFUNCTION("""COMPUTED_VALUE"""),"You gain temporary HP equal to the Block value of your armor and shield, up to a maximum of 40 temporary HP.") -> You gain temporary HP equal to the Block value of your armor and shield, up to a maximum of 40 temporary HP. | G40: =IFERROR(__xludf.DUMMYFUNCTION("""COMPUTED_VALUE"""),"Must be wearing armor and/or a shield.") -> Must be wearing armor and/or a shield. | H40: =IFERROR(__xludf.DUMMYFUNCTION("""COMPUTED_VALUE"""),"1 AP, 3 MP") -> 1 AP, 3 MP | I40: =IFERROR(__xludf.DUMMYFUNCTION("""COMPUTED_VALUE"""),"1 AP") -> 1 AP | J40: =IFERROR(__xludf.DUMMYFUNCTION("""COMPUTED_VALUE"""),"3 MP") -> 3 MP | K40: =IFERROR(__xludf.DUMMYFUNCTION("""COMPUTED_VALUE"""),"") | L40: =IFERROR(__xludf.DUMMYFUNCTION("""COMPUTED_VALUE"""),"")
B41: =IFERROR(__xludf.DUMMYFUNCTION("""COMPUTED_VALUE"""),"Armored Blow") -> Armored Blow | D41: =IFERROR(__xludf.DUMMYFUNCTION("""COMPUTED_VALUE"""),"") | E41: =IFERROR(__xludf.DUMMYFUNCTION("""COMPUTED_VALUE"""),"Melee Weapon Range") -> Melee Weapon Range | F41: =IFERROR(__xludf.DUMMYFUNCTION("""COMPUTED_VALUE"""),"You make a Heavy attack against the target. Your next Block against that target costs 0 RP and gains a +10 bonus.") -> You make a Heavy attack against the target. Your next Block against that target costs 0 RP and gains a +10 bonus. | G41: =IFERROR(__xludf.DUMMYFUNCTION("""COMPUTED_VALUE"""),"May only be used after moving at least 20ft in the previous action. Must be mounted.") -> May only be used after moving at least 20ft in the previous action. Must be mounted. | H41: =IFERROR(__xludf.DUMMYFUNCTION("""COMPUTED_VALUE"""),"2 AP, 1 MP") -> 2 AP, 1 MP | I41: =IFERROR(__xludf.DUMMYFUNCTION("""COMPUTED_VALUE"""),"2 AP") -> 2 AP | J41: =IFERROR(__xludf.DUMMYFUNCTION("""COMPUTED_VALUE"""),"1 MP") -> 1 MP | K41: =IFERROR(__xludf.DUMMYFUNCTION("""COMPUTED_VALUE"""),"") | L41: =IFERROR(__xludf.DUMMYFUNCTION("""COMPUTED_VALUE"""),"")
B42: =IFERROR(__xludf.DUMMYFUNCTION("""COMPUTED_VALUE"""),"Armorsmith Basics") -> Armorsmith Basics | D42: =IFERROR(__xludf.DUMMYFUNCTION("""COMPUTED_VALUE"""),"") | E42: =IFERROR(__xludf.DUMMYFUNCTION("""COMPUTED_VALUE"""),"") | F42: =IFERROR(__xludf.DUMMYFUNCTION("""COMPUTED_VALUE"""),"Armorsmith's Modification A Cost: X Crafting Points Description: You add an A-Type modification to the armor. See the Universal Armor page as well as the individual armor pages for details. Each modification has its own cost. Armorsmith's Modification Fra"&"me Cost: X Crafting Points Description: You add an Frame-Type modification to the armor. See the Universal Armor page as well as the individual armor pages for details. Each modification has its own cost. Adaptive Layering Cost: X crafting points Descript"&"ion: You mix a special material into the armor or shield. Each material has its own crafting point cost. Cloak Layering Cost: X crafting points Description: You use a special material for the creation of the cloak. Each material has its own crafting point"&" cost. Only cloak special materials can be used and mixing in a special material increases the burden cost of the cloak by 1. Create Ingot Cost: Errand Description: You create an ingot from armorsmithing base materials or from armorsmithing special materi"&"als. See Item: Armorsmithing Materials. Tan Leather Cost: Errand Description: You create a tanned hide from armorsmithing base leather materials. See item: Armorsmithing materials.") -> Armorsmith's Modification A Cost: X Crafting Points Description: You add an A-Type modification to the armor. See the Universal Armor page as well as the individual armor pages for details. Each modification has its own cost. Armorsmith's Modification Frame Cost: X Crafting Points Description: You add an Frame-Type modification to the armor. See the Universal Armor page as well as the individual armor pages for details. Each modification has its own cost. Adaptive Layering Cost: X crafting points Description: You mix a special material into the armor or shield. Each material has its own crafting point cost. Cloak Layering Cost: X crafting points Description: You use a special material for the creation of the cloak. Each material has its own crafting point cost. Only cloak special materials can be used and mixing in a special material increases the burden cost of the cloak by 1. Create Ingot Cost: Errand Description: You create an ingot from armorsmithing base materials or from armorsmithing special materials. See Item: Armorsmithing Materials. Tan Leather Cost: Errand Description: You create a tanned hide from armorsmithing base leather materials. See item: Armorsmithing materials. | G42: =IFERROR(__xludf.DUMMYFUNCTION("""COMPUTED_VALUE"""),"") | H42: =IFERROR(__xludf.DUMMYFUNCTION("""COMPUTED_VALUE"""),"") | I42: =IFERROR(__xludf.DUMMYFUNCTION("""COMPUTED_VALUE"""),"") | J42: =IFERROR(__xludf.DUMMYFUNCTION("""COMPUTED_VALUE"""),"") | K42: =IFERROR(__xludf.DUMMYFUNCTION("""COMPUTED_VALUE"""),"") | L42: =IFERROR(__xludf.DUMMYFUNCTION("""COMPUTED_VALUE"""),"")
B43: =IFERROR(__xludf.DUMMYFUNCTION("""COMPUTED_VALUE"""),"Armorsmithing Expert") -> Armorsmithing Expert | D43: =IFERROR(__xludf.DUMMYFUNCTION("""COMPUTED_VALUE"""),"") | E43: =IFERROR(__xludf.DUMMYFUNCTION("""COMPUTED_VALUE"""),"") | F43: =IFERROR(__xludf.DUMMYFUNCTION("""COMPUTED_VALUE"""),"Armorsmith's Modification B Cost: X Crafting Points Description: You add an B-Type modification to the weapon or tool. See the Universal Armor page as well as the individual armor pages for details. Each modification has its own cost.") -> Armorsmith's Modification B Cost: X Crafting Points Description: You add an B-Type modification to the weapon or tool. See the Universal Armor page as well as the individual armor pages for details. Each modification has its own cost. | G43: =IFERROR(__xludf.DUMMYFUNCTION("""COMPUTED_VALUE"""),"") | H43: =IFERROR(__xludf.DUMMYFUNCTION("""COMPUTED_VALUE"""),"") | I43: =IFERROR(__xludf.DUMMYFUNCTION("""COMPUTED_VALUE"""),"") | J43: =IFERROR(__xludf.DUMMYFUNCTION("""COMPUTED_VALUE"""),"") | K43: =IFERROR(__xludf.DUMMYFUNCTION("""COMPUTED_VALUE"""),"") | L43: =IFERROR(__xludf.DUMMYFUNCTION("""COMPUTED_VALUE"""),"")
B44: =IFERROR(__xludf.DUMMYFUNCTION("""COMPUTED_VALUE"""),"Artery Cut") -> Artery Cut | D44: =IFERROR(__xludf.DUMMYFUNCTION("""COMPUTED_VALUE"""),"") | E44: =IFERROR(__xludf.DUMMYFUNCTION("""COMPUTED_VALUE"""),"Melee Weapon Range") -> Melee Weapon Range | F44: =IFERROR(__xludf.DUMMYFUNCTION("""COMPUTED_VALUE"""),"You change the arc of your weapon and go for a vital spot, turning the hit into a critical hit.") -> You change the arc of your weapon and go for a vital spot, turning the hit into a critical hit. | G44: =IFERROR(__xludf.DUMMYFUNCTION("""COMPUTED_VALUE"""),"One-Handed weapon only, can be used after a light attack hits and is not reacted against.") -> One-Handed weapon only, can be used after a light attack hits and is not reacted against. | H44: =IFERROR(__xludf.DUMMYFUNCTION("""COMPUTED_VALUE"""),"1 RP") -> 1 RP | I44: =IFERROR(__xludf.DUMMYFUNCTION("""COMPUTED_VALUE"""),"") | J44: =IFERROR(__xludf.DUMMYFUNCTION("""COMPUTED_VALUE"""),"") | K44: =IFERROR(__xludf.DUMMYFUNCTION("""COMPUTED_VALUE"""),"1 RP") -> 1 RP | L44: =IFERROR(__xludf.DUMMYFUNCTION("""COMPUTED_VALUE"""),"")
B45: =IFERROR(__xludf.DUMMYFUNCTION("""COMPUTED_VALUE"""),"Artificer Basics") -> Artificer Basics | D45: =IFERROR(__xludf.DUMMYFUNCTION("""COMPUTED_VALUE"""),"") | E45: =IFERROR(__xludf.DUMMYFUNCTION("""COMPUTED_VALUE"""),"") | F45: =IFERROR(__xludf.DUMMYFUNCTION("""COMPUTED_VALUE"""),"Artifice Modification A Cost: X Crafting Points Description: You add an A-Type modification to an artifice. See the Universal Artifice mods page as well as the individual artifice page for details. Each modification has its own cost. Weapon Modification A"&" Cost: X Crafting Points Description: You add an A-Type modification to the weapon. See the Universal Weapon mods page as well as the individual weapon page for details. Each modification has its own cost. Artifice Modification C Cost: X Crafting Points D"&"escription: You add an C-Type modification to the weapon. See the Universal Artifice mods page as well as the individual artifice page for details. Each modification has its own cost. Craft Fuel Shells Cost: Errand Description: You craft up to 5 small she"&"lls. You can instead craft a medium shell instead of 2 small shells. Small shells require 50 magical fuel, medium shells require 200 magical fuel. Craft Artifice Parts Cost: Errand Description: You create up to 3000u of artifice parts of the same type o"&"f blacksmithing material used to make them at a 1:1 rate. (3000u of Iron Creates 3000u of Iron Artifice Parts.) See Items: Blacksmithing Materials, Artificer Materials. When converting items of a higher tier, you can convert up to 6000 of tamahagane, 90"&"00 of mithril, 12000 of Orihalcum or 15000 of escudo. Firearm Alloy Cost: X Crafting Points Description: You mix a special material into the firearm or artifice weapon. Each material has its own crafting point cost. Create Ingot Cost: Errand Description: "&"You create an ingot from blacksmithing base materials or from blacksmithing special materials. See Item: Blacksmithing Materials.") -> Artifice Modification A Cost: X Crafting Points Description: You add an A-Type modification to an artifice. See the Universal Artifice mods page as well as the individual artifice page for details. Each modification has its own cost. Weapon Modification A Cost: X Crafting Points Description: You add an A-Type modification to the weapon. See the Universal Weapon mods page as well as the individual weapon page for details. Each modification has its own cost. Artifice Modification C Cost: X Crafting Points Description: You add an C-Type modification to the weapon. See the Universal Artifice mods page as well as the individual artifice page for details. Each modification has its own cost. Craft Fuel Shells Cost: Errand Description: You craft up to 5 small shells. You can instead craft a medium shell instead of 2 small shells. Small shells require 50 magical fuel, medium shells require 200 magical fuel. Craft Artifice Parts Cost: Errand Description: You create up to 3000u of artifice parts of the same type of blacksmithing material used to make them at a 1:1 rate. (3000u of Iron Creates 3000u of Iron Artifice Parts.) See Items: Blacksmithing Materials, Artificer Materials. When converting items of a higher tier, you can convert up to 6000 of tamahagane, 9000 of mithril, 12000 of Orihalcum or 15000 of escudo. Firearm Alloy Cost: X Crafting Points Description: You mix a special material into the firearm or artifice weapon. Each material has its own crafting point cost. Create Ingot Cost: Errand Description: You create an ingot from blacksmithing base materials or from blacksmithing special materials. See Item: Blacksmithing Materials. | G45: =IFERROR(__xludf.DUMMYFUNCTION("""COMPUTED_VALUE"""),"") | H45: =IFERROR(__xludf.DUMMYFUNCTION("""COMPUTED_VALUE"""),"") | I45: =IFERROR(__xludf.DUMMYFUNCTION("""COMPUTED_VALUE"""),"") | J45: =IFERROR(__xludf.DUMMYFUNCTION("""COMPUTED_VALUE"""),"") | K45: =IFERROR(__xludf.DUMMYFUNCTION("""COMPUTED_VALUE"""),"") | L45: =IFERROR(__xludf.DUMMYFUNCTION("""COMPUTED_VALUE"""),"")
B46: =IFERROR(__xludf.DUMMYFUNCTION("""COMPUTED_VALUE"""),"Assign Decoy") -> Assign Decoy | D46: =IFERROR(__xludf.DUMMYFUNCTION("""COMPUTED_VALUE"""),"Challenge, Quick") -> Challenge, Quick | E46: =IFERROR(__xludf.DUMMYFUNCTION("""COMPUTED_VALUE"""),"60ft") -> 60ft | F46: =IFERROR(__xludf.DUMMYFUNCTION("""COMPUTED_VALUE"""),"Choose one willing ally other than yourself within range and one enemy within range. The enemy is Challenged by the chosen ally until the start of your next turn.") -> Choose one willing ally other than yourself within range and one enemy within range. The enemy is Challenged by the chosen ally until the start of your next turn. | G46: =IFERROR(__xludf.DUMMYFUNCTION("""COMPUTED_VALUE"""),"") | H46: =IFERROR(__xludf.DUMMYFUNCTION("""COMPUTED_VALUE"""),"0 AP") -> 0 AP | I46: =IFERROR(__xludf.DUMMYFUNCTION("""COMPUTED_VALUE"""),"0 AP") -> 0 AP | J46: =IFERROR(__xludf.DUMMYFUNCTION("""COMPUTED_VALUE"""),"") | K46: =IFERROR(__xludf.DUMMYFUNCTION("""COMPUTED_VALUE"""),"") | L46: =IFERROR(__xludf.DUMMYFUNCTION("""COMPUTED_VALUE"""),"")
B47: =IFERROR(__xludf.DUMMYFUNCTION("""COMPUTED_VALUE"""),"Astral Projection") -> Astral Projection | D47: =IFERROR(__xludf.DUMMYFUNCTION("""COMPUTED_VALUE"""),"") | E47: =IFERROR(__xludf.DUMMYFUNCTION("""COMPUTED_VALUE"""),"Self") -> Self | F47: =IFERROR(__xludf.DUMMYFUNCTION("""COMPUTED_VALUE"""),"After a 10 minute channel you arrive at the space between worlds, allowing you to interact with Eidolons that wish to meet with you.") -> After a 10 minute channel you arrive at the space between worlds, allowing you to interact with Eidolons that wish to meet with you. | G47: =IFERROR(__xludf.DUMMYFUNCTION("""COMPUTED_VALUE"""),"") | H47: =IFERROR(__xludf.DUMMYFUNCTION("""COMPUTED_VALUE"""),"") | I47: =IFERROR(__xludf.DUMMYFUNCTION("""COMPUTED_VALUE"""),"") | J47: =IFERROR(__xludf.DUMMYFUNCTION("""COMPUTED_VALUE"""),"") | K47: =IFERROR(__xludf.DUMMYFUNCTION("""COMPUTED_VALUE"""),"") | L47: =IFERROR(__xludf.DUMMYFUNCTION("""COMPUTED_VALUE"""),"")
B48: =IFERROR(__xludf.DUMMYFUNCTION("""COMPUTED_VALUE"""),"At your side") -> At your side | D48: =IFERROR(__xludf.DUMMYFUNCTION("""COMPUTED_VALUE"""),"Teleport") -> Teleport | E48: =IFERROR(__xludf.DUMMYFUNCTION("""COMPUTED_VALUE"""),"Self") -> Self | F48: =IFERROR(__xludf.DUMMYFUNCTION("""COMPUTED_VALUE"""),"You teleport up to 40ft. This must place you next to your VIP.") -> You teleport up to 40ft. This must place you next to your VIP. | G48: =IFERROR(__xludf.DUMMYFUNCTION("""COMPUTED_VALUE"""),"") | H48: =IFERROR(__xludf.DUMMYFUNCTION("""COMPUTED_VALUE"""),"2 MP, 0 RP") -> 2 MP, 0 RP | I48: =IFERROR(__xludf.DUMMYFUNCTION("""COMPUTED_VALUE"""),"") | J48: =IFERROR(__xludf.DUMMYFUNCTION("""COMPUTED_VALUE"""),"2 MP") -> 2 MP | K48: =IFERROR(__xludf.DUMMYFUNCTION("""COMPUTED_VALUE"""),"0 RP") -> 0 RP | L48: =IFERROR(__xludf.DUMMYFUNCTION("""COMPUTED_VALUE"""),"")
B49: =IFERROR(__xludf.DUMMYFUNCTION("""COMPUTED_VALUE"""),"Attack in Detail") -> Attack in Detail | D49: =IFERROR(__xludf.DUMMYFUNCTION("""COMPUTED_VALUE"""),"") | E49: =IFERROR(__xludf.DUMMYFUNCTION("""COMPUTED_VALUE"""),"120ft") -> 120ft | F49: =IFERROR(__xludf.DUMMYFUNCTION("""COMPUTED_VALUE"""),"You target one enemy unit. All allied units (including yourself) gain a +1 Damage Bonus when that enemy unit is the target of an attack until the start of your next turn. In addition, all allied units gain +5 Movement Speed when moving towards that enemy "&"unit.") -> You target one enemy unit. All allied units (including yourself) gain a +1 Damage Bonus when that enemy unit is the target of an attack until the start of your next turn. In addition, all allied units gain +5 Movement Speed when moving towards that enemy unit. | G49: =IFERROR(__xludf.DUMMYFUNCTION("""COMPUTED_VALUE"""),"") | H49: =IFERROR(__xludf.DUMMYFUNCTION("""COMPUTED_VALUE"""),"2 AP") -> 2 AP | I49: =IFERROR(__xludf.DUMMYFUNCTION("""COMPUTED_VALUE"""),"2 AP") -> 2 AP | J49: =IFERROR(__xludf.DUMMYFUNCTION("""COMPUTED_VALUE"""),"") | K49: =IFERROR(__xludf.DUMMYFUNCTION("""COMPUTED_VALUE"""),"") | L49: =IFERROR(__xludf.DUMMYFUNCTION("""COMPUTED_VALUE"""),"")
B50: =IFERROR(__xludf.DUMMYFUNCTION("""COMPUTED_VALUE"""),"Attacks from the Past") -> Attacks from the Past | D50: =IFERROR(__xludf.DUMMYFUNCTION("""COMPUTED_VALUE"""),"Rage") -> Rage | E50: =IFERROR(__xludf.DUMMYFUNCTION("""COMPUTED_VALUE"""),"Self") -> Self | F50: =IFERROR(__xludf.DUMMYFUNCTION("""COMPUTED_VALUE"""),"After making a melee weapon attack, you may repeat the attack from one of your past self tokens. You may target the same enemy as your original attack. Cannot repeat Secret Arts or other attacks with a once per combat/arc etc type limitation. Can only rep"&"eat attacks with a base cost of 2 AP or lower and any mana cost must be paid as normal.") -> After making a melee weapon attack, you may repeat the attack from one of your past self tokens. You may target the same enemy as your original attack. Cannot repeat Secret Arts or other attacks with a once per combat/arc etc type limitation. Can only repeat attacks with a base cost of 2 AP or lower and any mana cost must be paid as normal. | G50: =IFERROR(__xludf.DUMMYFUNCTION("""COMPUTED_VALUE"""),"") | H50: =IFERROR(__xludf.DUMMYFUNCTION("""COMPUTED_VALUE"""),"1 RP") -> 1 RP | I50: =IFERROR(__xludf.DUMMYFUNCTION("""COMPUTED_VALUE"""),"") | J50: =IFERROR(__xludf.DUMMYFUNCTION("""COMPUTED_VALUE"""),"") | K50: =IFERROR(__xludf.DUMMYFUNCTION("""COMPUTED_VALUE"""),"1 RP") -> 1 RP | L50: =IFERROR(__xludf.DUMMYFUNCTION("""COMPUTED_VALUE"""),"")
B51: =IFERROR(__xludf.DUMMYFUNCTION("""COMPUTED_VALUE"""),"Attune Eidolon") -> Attune Eidolon | D51: =IFERROR(__xludf.DUMMYFUNCTION("""COMPUTED_VALUE"""),"Encounter Start") -> Encounter Start | E51: =IFERROR(__xludf.DUMMYFUNCTION("""COMPUTED_VALUE"""),"Self") -> Self | F51: =IFERROR(__xludf.DUMMYFUNCTION("""COMPUTED_VALUE"""),"You attune to a specific Eidolon, paying the attunement cost (if applicable) and then activating its Passive (if applicable). You gain its Channel Eidolon, Summon Lesser Eidolon and Secret Art: Summon Eidolon abilities provided that you have advanced eno"&"ugh in this class to get them. You may use this as an Encounter Start ability without paying an AP cost.") -> You attune to a specific Eidolon, paying the attunement cost (if applicable) and then activating its Passive (if applicable). You gain its Channel Eidolon, Summon Lesser Eidolon and Secret Art: Summon Eidolon abilities provided that you have advanced enough in this class to get them. You may use this as an Encounter Start ability without paying an AP cost. | G51: =IFERROR(__xludf.DUMMYFUNCTION("""COMPUTED_VALUE"""),"You have an Eidolon you are contracted to.") -> You have an Eidolon you are contracted to. | H51: =IFERROR(__xludf.DUMMYFUNCTION("""COMPUTED_VALUE"""),"2 AP") -> 2 AP | I51: =IFERROR(__xludf.DUMMYFUNCTION("""COMPUTED_VALUE"""),"2 AP") -> 2 AP | J51: =IFERROR(__xludf.DUMMYFUNCTION("""COMPUTED_VALUE"""),"") | K51: =IFERROR(__xludf.DUMMYFUNCTION("""COMPUTED_VALUE"""),"") | L51: =IFERROR(__xludf.DUMMYFUNCTION("""COMPUTED_VALUE"""),"")
B52: =IFERROR(__xludf.DUMMYFUNCTION("""COMPUTED_VALUE"""),"Aura of Protection") -> Aura of Protection | D52: =IFERROR(__xludf.DUMMYFUNCTION("""COMPUTED_VALUE"""),"Aura") -> Aura | E52: =IFERROR(__xludf.DUMMYFUNCTION("""COMPUTED_VALUE"""),"Self") -> Self | F52: =IFERROR(__xludf.DUMMYFUNCTION("""COMPUTED_VALUE"""),"You create a 30ft radius Aura of Protection around yourself. While this aura is active, when an ally within 30ft of you takes the Block action you may spend 1 Mana to replace their Block Value with your own. In addition, any abilities with the Aid keyword"&" have their range increased by 20ft while inside the Aura.") -> You create a 30ft radius Aura of Protection around yourself. While this aura is active, when an ally within 30ft of you takes the Block action you may spend 1 Mana to replace their Block Value with your own. In addition, any abilities with the Aid keyword have their range increased by 20ft while inside the Aura. | G52: =IFERROR(__xludf.DUMMYFUNCTION("""COMPUTED_VALUE"""),"") | H52: =IFERROR(__xludf.DUMMYFUNCTION("""COMPUTED_VALUE"""),"1 AP") -> 1 AP | I52: =IFERROR(__xludf.DUMMYFUNCTION("""COMPUTED_VALUE"""),"1 AP") -> 1 AP | J52: =IFERROR(__xludf.DUMMYFUNCTION("""COMPUTED_VALUE"""),"") | K52: =IFERROR(__xludf.DUMMYFUNCTION("""COMPUTED_VALUE"""),"") | L52: =IFERROR(__xludf.DUMMYFUNCTION("""COMPUTED_VALUE"""),"")
B53: =IFERROR(__xludf.DUMMYFUNCTION("""COMPUTED_VALUE"""),"Aura of Resistance") -> Aura of Resistance | D53: =IFERROR(__xludf.DUMMYFUNCTION("""COMPUTED_VALUE"""),"Aura") -> Aura | E53: =IFERROR(__xludf.DUMMYFUNCTION("""COMPUTED_VALUE"""),"Self") -> Self | F53: =IFERROR(__xludf.DUMMYFUNCTION("""COMPUTED_VALUE"""),"You create a 30ft radius Aura of Resistance around yourself until the end of the encounter. While this aura is active, when an ally other than yourself fails a save you may spend 1 Mana to make them treat their save as if they were using your Toughness va"&"lue instead of their own.") -> You create a 30ft radius Aura of Resistance around yourself until the end of the encounter. While this aura is active, when an ally other than yourself fails a save you may spend 1 Mana to make them treat their save as if they were using your Toughness value instead of their own. | G53: =IFERROR(__xludf.DUMMYFUNCTION("""COMPUTED_VALUE"""),"") | H53: =IFERROR(__xludf.DUMMYFUNCTION("""COMPUTED_VALUE"""),"1 AP") -> 1 AP | I53: =IFERROR(__xludf.DUMMYFUNCTION("""COMPUTED_VALUE"""),"1 AP") -> 1 AP | J53: =IFERROR(__xludf.DUMMYFUNCTION("""COMPUTED_VALUE"""),"") | K53: =IFERROR(__xludf.DUMMYFUNCTION("""COMPUTED_VALUE"""),"") | L53: =IFERROR(__xludf.DUMMYFUNCTION("""COMPUTED_VALUE"""),"")
B54: =IFERROR(__xludf.DUMMYFUNCTION("""COMPUTED_VALUE"""),"Aurora Blade Style Secret Art: Permafrost Guilotine") -> Aurora Blade Style Secret Art: Permafrost Guilotine | D54: =IFERROR(__xludf.DUMMYFUNCTION("""COMPUTED_VALUE"""),"Secret Art, Stance, Frost") -> Secret Art, Stance, Frost | E54: =IFERROR(__xludf.DUMMYFUNCTION("""COMPUTED_VALUE"""),"Melee Weapon Range") -> Melee Weapon Range | F54: =IFERROR(__xludf.DUMMYFUNCTION("""COMPUTED_VALUE"""),"You make a light attack against the target or spend 1 extra AP to make a heavy or precise attack that deals Frost damage. On damage, the target is rooted until the end of your next turn. Then, enter Permafrost Guillotine stance. While in this stance you c"&"an use Aurora Blade Style Secret Art: Permafrost Guillotine again. The stance lasts until the end of combat or until you enter different stance.") -> You make a light attack against the target or spend 1 extra AP to make a heavy or precise attack that deals Frost damage. On damage, the target is rooted until the end of your next turn. Then, enter Permafrost Guillotine stance. While in this stance you can use Aurora Blade Style Secret Art: Permafrost Guillotine again. The stance lasts until the end of combat or until you enter different stance. | G54: =IFERROR(__xludf.DUMMYFUNCTION("""COMPUTED_VALUE"""),"Can only be used after you move to a target using Rimestep. Light swords, longsword, katana or dueling weapon only.") -> Can only be used after you move to a target using Rimestep. Light swords, longsword, katana or dueling weapon only. | H54: =IFERROR(__xludf.DUMMYFUNCTION("""COMPUTED_VALUE"""),"0 AP") -> 0 AP | I54: =IFERROR(__xludf.DUMMYFUNCTION("""COMPUTED_VALUE"""),"0 AP") -> 0 AP | J54: =IFERROR(__xludf.DUMMYFUNCTION("""COMPUTED_VALUE"""),"") | K54: =IFERROR(__xludf.DUMMYFUNCTION("""COMPUTED_VALUE"""),"") | L54: =IFERROR(__xludf.DUMMYFUNCTION("""COMPUTED_VALUE"""),"")
B55: =IFERROR(__xludf.DUMMYFUNCTION("""COMPUTED_VALUE"""),"Aurora Blade Style: Aurora Slash") -> Aurora Blade Style: Aurora Slash | D55: =IFERROR(__xludf.DUMMYFUNCTION("""COMPUTED_VALUE"""),"Slow, Frost") -> Slow, Frost | E55: =IFERROR(__xludf.DUMMYFUNCTION("""COMPUTED_VALUE"""),"80ft") -> 80ft | F55: =IFERROR(__xludf.DUMMYFUNCTION("""COMPUTED_VALUE"""),"You fire slashes in a straight line creating a curtain of light which strikes the first target hit with a light attack that deals frost damage. On hit the target is slowed until the end of your next turn. The light from the slash continues for the full ra"&"nge, creating a 300ft high wall that blocks vision on both sides. This wall of multicolored light last until the start of your next turn.") -> You fire slashes in a straight line creating a curtain of light which strikes the first target hit with a light attack that deals frost damage. On hit the target is slowed until the end of your next turn. The light from the slash continues for the full range, creating a 300ft high wall that blocks vision on both sides. This wall of multicolored light last until the start of your next turn. | G55: =IFERROR(__xludf.DUMMYFUNCTION("""COMPUTED_VALUE"""),"Light swords, longsword, katana or dueling weapon only.") -> Light swords, longsword, katana or dueling weapon only. | H55: =IFERROR(__xludf.DUMMYFUNCTION("""COMPUTED_VALUE"""),"2 AP, 1 MP") -> 2 AP, 1 MP | I55: =IFERROR(__xludf.DUMMYFUNCTION("""COMPUTED_VALUE"""),"2 AP") -> 2 AP | J55: =IFERROR(__xludf.DUMMYFUNCTION("""COMPUTED_VALUE"""),"1 MP") -> 1 MP | K55: =IFERROR(__xludf.DUMMYFUNCTION("""COMPUTED_VALUE"""),"") | L55: =IFERROR(__xludf.DUMMYFUNCTION("""COMPUTED_VALUE"""),"")
B56: =IFERROR(__xludf.DUMMYFUNCTION("""COMPUTED_VALUE"""),"Aurora Blade Style: Rimestep") -> Aurora Blade Style: Rimestep | D56: =IFERROR(__xludf.DUMMYFUNCTION("""COMPUTED_VALUE"""),"Sidestep") -> Sidestep | E56: =IFERROR(__xludf.DUMMYFUNCTION("""COMPUTED_VALUE"""),"Self") -> Self | F56: =IFERROR(__xludf.DUMMYFUNCTION("""COMPUTED_VALUE"""),"When a target is slowed by an attack with the frost keyword, you may sidestep up to your speed towards the target. If you have enough movement you can end your movement anywhere next to the target. Overcharge: You may spend 1 Mana to instead make it three"&" times your speed.") -> When a target is slowed by an attack with the frost keyword, you may sidestep up to your speed towards the target. If you have enough movement you can end your movement anywhere next to the target. Overcharge: You may spend 1 Mana to instead make it three times your speed. | G56: =IFERROR(__xludf.DUMMYFUNCTION("""COMPUTED_VALUE"""),"") | H56: =IFERROR(__xludf.DUMMYFUNCTION("""COMPUTED_VALUE"""),"0 RP") -> 0 RP | I56: =IFERROR(__xludf.DUMMYFUNCTION("""COMPUTED_VALUE"""),"") | J56: =IFERROR(__xludf.DUMMYFUNCTION("""COMPUTED_VALUE"""),"") | K56: =IFERROR(__xludf.DUMMYFUNCTION("""COMPUTED_VALUE"""),"0 RP") -> 0 RP | L56: =IFERROR(__xludf.DUMMYFUNCTION("""COMPUTED_VALUE"""),"")
B57: =IFERROR(__xludf.DUMMYFUNCTION("""COMPUTED_VALUE"""),"Aurora Blade Style: Winter's Edge") -> Aurora Blade Style: Winter's Edge | D57: =IFERROR(__xludf.DUMMYFUNCTION("""COMPUTED_VALUE"""),"Slow, Frost") -> Slow, Frost | E57: =IFERROR(__xludf.DUMMYFUNCTION("""COMPUTED_VALUE"""),"Melee Weapon Range") -> Melee Weapon Range | F57: =IFERROR(__xludf.DUMMYFUNCTION("""COMPUTED_VALUE"""),"You imbue your blade with frost energy and make a precise attack that deals Frost damage. On hit, the target is slowed until the end of your next turn.") -> You imbue your blade with frost energy and make a precise attack that deals Frost damage. On hit, the target is slowed until the end of your next turn. | G57: =IFERROR(__xludf.DUMMYFUNCTION("""COMPUTED_VALUE"""),"Light swords, longsword, katana or dueling weapon only.") -> Light swords, longsword, katana or dueling weapon only. | H57: =IFERROR(__xludf.DUMMYFUNCTION("""COMPUTED_VALUE"""),"2 AP, 1 MP") -> 2 AP, 1 MP | I57: =IFERROR(__xludf.DUMMYFUNCTION("""COMPUTED_VALUE"""),"2 AP") -> 2 AP | J57: =IFERROR(__xludf.DUMMYFUNCTION("""COMPUTED_VALUE"""),"1 MP") -> 1 MP | K57: =IFERROR(__xludf.DUMMYFUNCTION("""COMPUTED_VALUE"""),"") | L57: =IFERROR(__xludf.DUMMYFUNCTION("""COMPUTED_VALUE"""),"")
B58: =IFERROR(__xludf.DUMMYFUNCTION("""COMPUTED_VALUE"""),"Ave María") -> Ave María | D58: =IFERROR(__xludf.DUMMYFUNCTION("""COMPUTED_VALUE"""),"") | E58: =IFERROR(__xludf.DUMMYFUNCTION("""COMPUTED_VALUE"""),"Melee Weapon Range") -> Melee Weapon Range | F58: =IFERROR(__xludf.DUMMYFUNCTION("""COMPUTED_VALUE"""),"You attack with a swift double slash in the blink of an eye, making a Heavy Attack that deals Light damage + Heavy Holy damage.") -> You attack with a swift double slash in the blink of an eye, making a Heavy Attack that deals Light damage + Heavy Holy damage. | G58: =IFERROR(__xludf.DUMMYFUNCTION("""COMPUTED_VALUE"""),"") | H58: =IFERROR(__xludf.DUMMYFUNCTION("""COMPUTED_VALUE"""),"3 AP") -> 3 AP | I58: =IFERROR(__xludf.DUMMYFUNCTION("""COMPUTED_VALUE"""),"3 AP") -> 3 AP | J58: =IFERROR(__xludf.DUMMYFUNCTION("""COMPUTED_VALUE"""),"") | K58: =IFERROR(__xludf.DUMMYFUNCTION("""COMPUTED_VALUE"""),"") | L58: =IFERROR(__xludf.DUMMYFUNCTION("""COMPUTED_VALUE"""),"")
B59: =IFERROR(__xludf.DUMMYFUNCTION("""COMPUTED_VALUE"""),"Backlash") -> Backlash | D59: =IFERROR(__xludf.DUMMYFUNCTION("""COMPUTED_VALUE"""),"Full Pierce, Lockstep") -> Full Pierce, Lockstep | E59: =IFERROR(__xludf.DUMMYFUNCTION("""COMPUTED_VALUE"""),"Melee Weapon Range") -> Melee Weapon Range | F59: =IFERROR(__xludf.DUMMYFUNCTION("""COMPUTED_VALUE"""),"You make a Light attack against the target. You take true damage equal to half the damage dealt.") -> You make a Light attack against the target. You take true damage equal to half the damage dealt. | G59: =IFERROR(__xludf.DUMMYFUNCTION("""COMPUTED_VALUE"""),"") | H59: =IFERROR(__xludf.DUMMYFUNCTION("""COMPUTED_VALUE"""),"1 AP") -> 1 AP | I59: =IFERROR(__xludf.DUMMYFUNCTION("""COMPUTED_VALUE"""),"1 AP") -> 1 AP | J59: =IFERROR(__xludf.DUMMYFUNCTION("""COMPUTED_VALUE"""),"") | K59: =IFERROR(__xludf.DUMMYFUNCTION("""COMPUTED_VALUE"""),"") | L59: =IFERROR(__xludf.DUMMYFUNCTION("""COMPUTED_VALUE"""),"")
B60: =IFERROR(__xludf.DUMMYFUNCTION("""COMPUTED_VALUE"""),"Banana Peel") -> Banana Peel | D60: =IFERROR(__xludf.DUMMYFUNCTION("""COMPUTED_VALUE"""),"") | E60: =IFERROR(__xludf.DUMMYFUNCTION("""COMPUTED_VALUE"""),"20ft") -> 20ft | F60: =IFERROR(__xludf.DUMMYFUNCTION("""COMPUTED_VALUE"""),"You toss a banana peel in front of the target and they must make a Save or fall prone. If they fall prone, you may immediately use Pie Toss against them for 0 RP.") -> You toss a banana peel in front of the target and they must make a Save or fall prone. If they fall prone, you may immediately use Pie Toss against them for 0 RP. | G60: =IFERROR(__xludf.DUMMYFUNCTION("""COMPUTED_VALUE"""),"An enemy is moving within range.") -> An enemy is moving within range. | H60: =IFERROR(__xludf.DUMMYFUNCTION("""COMPUTED_VALUE"""),"1 RP") -> 1 RP | I60: =IFERROR(__xludf.DUMMYFUNCTION("""COMPUTED_VALUE"""),"") | J60: =IFERROR(__xludf.DUMMYFUNCTION("""COMPUTED_VALUE"""),"") | K60: =IFERROR(__xludf.DUMMYFUNCTION("""COMPUTED_VALUE"""),"1 RP") -> 1 RP | L60: =IFERROR(__xludf.DUMMYFUNCTION("""COMPUTED_VALUE"""),"")
B61: =IFERROR(__xludf.DUMMYFUNCTION("""COMPUTED_VALUE"""),"Barrel Roll") -> Barrel Roll | D61: =IFERROR(__xludf.DUMMYFUNCTION("""COMPUTED_VALUE"""),"Aerial Mage") -> Aerial Mage | E61: =IFERROR(__xludf.DUMMYFUNCTION("""COMPUTED_VALUE"""),"Self") -> Self | F61: =IFERROR(__xludf.DUMMYFUNCTION("""COMPUTED_VALUE"""),"You take the Dodge action and remove Lock On from the attack. You may spend an additional RP to automatically make the attack miss you, even if the attack has Sure Hit.") -> You take the Dodge action and remove Lock On from the attack. You may spend an additional RP to automatically make the attack miss you, even if the attack has Sure Hit. | G61: =IFERROR(__xludf.DUMMYFUNCTION("""COMPUTED_VALUE"""),"You are on an aerial staff and in Aerial mode.") -> You are on an aerial staff and in Aerial mode. | H61: =IFERROR(__xludf.DUMMYFUNCTION("""COMPUTED_VALUE"""),"1 MP, 1 RP") -> 1 MP, 1 RP | I61: =IFERROR(__xludf.DUMMYFUNCTION("""COMPUTED_VALUE"""),"") | J61: =IFERROR(__xludf.DUMMYFUNCTION("""COMPUTED_VALUE"""),"1 MP") -> 1 MP | K61: =IFERROR(__xludf.DUMMYFUNCTION("""COMPUTED_VALUE"""),"1 RP") -> 1 RP | L61: =IFERROR(__xludf.DUMMYFUNCTION("""COMPUTED_VALUE"""),"")
B62: =IFERROR(__xludf.DUMMYFUNCTION("""COMPUTED_VALUE"""),"Battle Cast") -> Battle Cast | D62: =IFERROR(__xludf.DUMMYFUNCTION("""COMPUTED_VALUE"""),"Circuit") -> Circuit | E62: =IFERROR(__xludf.DUMMYFUNCTION("""COMPUTED_VALUE"""),"Self") -> Self | F62: =IFERROR(__xludf.DUMMYFUNCTION("""COMPUTED_VALUE"""),"The next Spell you cast before the end of your turn does not provoke an attack of opportunity from being casted in Melee Range of an opponent.") -> The next Spell you cast before the end of your turn does not provoke an attack of opportunity from being casted in Melee Range of an opponent. | G62: =IFERROR(__xludf.DUMMYFUNCTION("""COMPUTED_VALUE"""),"") | H62: =IFERROR(__xludf.DUMMYFUNCTION("""COMPUTED_VALUE"""),"0 AP, 1 MP") -> 0 AP, 1 MP | I62: =IFERROR(__xludf.DUMMYFUNCTION("""COMPUTED_VALUE"""),"0 AP") -> 0 AP | J62: =IFERROR(__xludf.DUMMYFUNCTION("""COMPUTED_VALUE"""),"1 MP") -> 1 MP | K62: =IFERROR(__xludf.DUMMYFUNCTION("""COMPUTED_VALUE"""),"") | L62: =IFERROR(__xludf.DUMMYFUNCTION("""COMPUTED_VALUE"""),"")
B63: =IFERROR(__xludf.DUMMYFUNCTION("""COMPUTED_VALUE"""),"Bear Maul") -> Bear Maul | D63: =IFERROR(__xludf.DUMMYFUNCTION("""COMPUTED_VALUE"""),"Unarmed Strike") -> Unarmed Strike | E63: =IFERROR(__xludf.DUMMYFUNCTION("""COMPUTED_VALUE"""),"5ft") -> 5ft | F63: =IFERROR(__xludf.DUMMYFUNCTION("""COMPUTED_VALUE"""),"You swing your paw at the target and make a Heavy attack against it that deals maximum damage. If the target dodges, this attack automatically misses. You are considered proficient in unarmed attacks for this attack, even if you normally wouldn’t be.") -> You swing your paw at the target and make a Heavy attack against it that deals maximum damage. If the target dodges, this attack automatically misses. You are considered proficient in unarmed attacks for this attack, even if you normally wouldn’t be. | G63: =IFERROR(__xludf.DUMMYFUNCTION("""COMPUTED_VALUE"""),"") | H63: =IFERROR(__xludf.DUMMYFUNCTION("""COMPUTED_VALUE"""),"2 AP, 1 MP") -> 2 AP, 1 MP | I63: =IFERROR(__xludf.DUMMYFUNCTION("""COMPUTED_VALUE"""),"2 AP") -> 2 AP | J63: =IFERROR(__xludf.DUMMYFUNCTION("""COMPUTED_VALUE"""),"1 MP") -> 1 MP | K63: =IFERROR(__xludf.DUMMYFUNCTION("""COMPUTED_VALUE"""),"") | L63: =IFERROR(__xludf.DUMMYFUNCTION("""COMPUTED_VALUE"""),"")
B64: =IFERROR(__xludf.DUMMYFUNCTION("""COMPUTED_VALUE"""),"Bear Shock") -> Bear Shock | D64: =IFERROR(__xludf.DUMMYFUNCTION("""COMPUTED_VALUE"""),"") | E64: =IFERROR(__xludf.DUMMYFUNCTION("""COMPUTED_VALUE"""),"") | F64: =IFERROR(__xludf.DUMMYFUNCTION("""COMPUTED_VALUE"""),"You gain a +20 bonus to Deception checks when disguising yourself as something other than a bearfolk.") -> You gain a +20 bonus to Deception checks when disguising yourself as something other than a bearfolk. | G64: =IFERROR(__xludf.DUMMYFUNCTION("""COMPUTED_VALUE"""),"") | H64: =IFERROR(__xludf.DUMMYFUNCTION("""COMPUTED_VALUE"""),"") | I64: =IFERROR(__xludf.DUMMYFUNCTION("""COMPUTED_VALUE"""),"") | J64: =IFERROR(__xludf.DUMMYFUNCTION("""COMPUTED_VALUE"""),"") | K64: =IFERROR(__xludf.DUMMYFUNCTION("""COMPUTED_VALUE"""),"") | L64: =IFERROR(__xludf.DUMMYFUNCTION("""COMPUTED_VALUE"""),"")
B65: =IFERROR(__xludf.DUMMYFUNCTION("""COMPUTED_VALUE"""),"Bear Trap") -> Bear Trap | D65: =IFERROR(__xludf.DUMMYFUNCTION("""COMPUTED_VALUE"""),"Root, Full Pierce, Stealth") -> Root, Full Pierce, Stealth | E65: =IFERROR(__xludf.DUMMYFUNCTION("""COMPUTED_VALUE"""),"5ft") -> 5ft | F65: =IFERROR(__xludf.DUMMYFUNCTION("""COMPUTED_VALUE"""),"You place down a bear trap in an empty square within range. If an enemy enters that square, they trigger the trap taking Light full pierce damage and becoming rooted until they spend 2 AP to remove the effect. Against beasts, this does Heavy damage instea"&"d of Light damage. This ability consumes a Trap.") -> You place down a bear trap in an empty square within range. If an enemy enters that square, they trigger the trap taking Light full pierce damage and becoming rooted until they spend 2 AP to remove the effect. Against beasts, this does Heavy damage instead of Light damage. This ability consumes a Trap. | G65: =IFERROR(__xludf.DUMMYFUNCTION("""COMPUTED_VALUE"""),"") | H65: =IFERROR(__xludf.DUMMYFUNCTION("""COMPUTED_VALUE"""),"1 AP") -> 1 AP | I65: =IFERROR(__xludf.DUMMYFUNCTION("""COMPUTED_VALUE"""),"1 AP") -> 1 AP | J65: =IFERROR(__xludf.DUMMYFUNCTION("""COMPUTED_VALUE"""),"") | K65: =IFERROR(__xludf.DUMMYFUNCTION("""COMPUTED_VALUE"""),"") | L65: =IFERROR(__xludf.DUMMYFUNCTION("""COMPUTED_VALUE"""),"")
B66: =IFERROR(__xludf.DUMMYFUNCTION("""COMPUTED_VALUE"""),"Benediction") -> Benediction | D66: =IFERROR(__xludf.DUMMYFUNCTION("""COMPUTED_VALUE"""),"Spell, Sanctify") -> Spell, Sanctify | E66: =IFERROR(__xludf.DUMMYFUNCTION("""COMPUTED_VALUE"""),"60ft") -> 60ft | F66: =IFERROR(__xludf.DUMMYFUNCTION("""COMPUTED_VALUE"""),"You make a precise attack against the target that deals Holy damage. On damage, inflict Sanctify 3. This attack does not benefit from Pinpoint.") -> You make a precise attack against the target that deals Holy damage. On damage, inflict Sanctify 3. This attack does not benefit from Pinpoint. | G66: =IFERROR(__xludf.DUMMYFUNCTION("""COMPUTED_VALUE"""),"") | H66: =IFERROR(__xludf.DUMMYFUNCTION("""COMPUTED_VALUE"""),"1 AP, 3 MP") -> 1 AP, 3 MP | I66: =IFERROR(__xludf.DUMMYFUNCTION("""COMPUTED_VALUE"""),"1 AP") -> 1 AP | J66: =IFERROR(__xludf.DUMMYFUNCTION("""COMPUTED_VALUE"""),"3 MP") -> 3 MP | K66: =IFERROR(__xludf.DUMMYFUNCTION("""COMPUTED_VALUE"""),"") | L66: =IFERROR(__xludf.DUMMYFUNCTION("""COMPUTED_VALUE"""),"")
B67: =IFERROR(__xludf.DUMMYFUNCTION("""COMPUTED_VALUE"""),"Bestial Command") -> Bestial Command | D67: =IFERROR(__xludf.DUMMYFUNCTION("""COMPUTED_VALUE"""),"") | E67: =IFERROR(__xludf.DUMMYFUNCTION("""COMPUTED_VALUE"""),"Sight") -> Sight | F67: =IFERROR(__xludf.DUMMYFUNCTION("""COMPUTED_VALUE"""),"The summon may take basic actions as if it had 2 AP to spend. In addition, if your summon is under the effects of Independent Action, it gains Bestial Command until the end of the encounter, it dies or you cancel it for 0 AP. While Bestial Command lasts, "&"its maximum AP and AP recovery are increased by 2 while your AP recovery is lowered by 2.") -> The summon may take basic actions as if it had 2 AP to spend. In addition, if your summon is under the effects of Independent Action, it gains Bestial Command until the end of the encounter, it dies or you cancel it for 0 AP. While Bestial Command lasts, its maximum AP and AP recovery are increased by 2 while your AP recovery is lowered by 2. | G67: =IFERROR(__xludf.DUMMYFUNCTION("""COMPUTED_VALUE"""),"Can only target your summoned animal.") -> Can only target your summoned animal. | H67: =IFERROR(__xludf.DUMMYFUNCTION("""COMPUTED_VALUE"""),"0 AP, 2 MP") -> 0 AP, 2 MP | I67: =IFERROR(__xludf.DUMMYFUNCTION("""COMPUTED_VALUE"""),"0 AP") -> 0 AP | J67: =IFERROR(__xludf.DUMMYFUNCTION("""COMPUTED_VALUE"""),"2 MP") -> 2 MP | K67: =IFERROR(__xludf.DUMMYFUNCTION("""COMPUTED_VALUE"""),"") | L67: =IFERROR(__xludf.DUMMYFUNCTION("""COMPUTED_VALUE"""),"")
B68: =IFERROR(__xludf.DUMMYFUNCTION("""COMPUTED_VALUE"""),"Biohacking") -> Biohacking | D68: =IFERROR(__xludf.DUMMYFUNCTION("""COMPUTED_VALUE"""),"") | E68: =IFERROR(__xludf.DUMMYFUNCTION("""COMPUTED_VALUE"""),"Self") -> Self | F68: =IFERROR(__xludf.DUMMYFUNCTION("""COMPUTED_VALUE"""),"At the start of an arc, you can transmute a gene from a Chimera Subrace into your DNA as long as you have a sample (a vial of blood). Transmuting the gene does not consume the item. Add a single Chimera gene to your gene inventory. You can perform this ac"&"tion again for an IP or EP. Biohacking can store genes equal to your gene limit.") -> At the start of an arc, you can transmute a gene from a Chimera Subrace into your DNA as long as you have a sample (a vial of blood). Transmuting the gene does not consume the item. Add a single Chimera gene to your gene inventory. You can perform this action again for an IP or EP. Biohacking can store genes equal to your gene limit. | G68: =IFERROR(__xludf.DUMMYFUNCTION("""COMPUTED_VALUE"""),"") | H68: =IFERROR(__xludf.DUMMYFUNCTION("""COMPUTED_VALUE"""),"") | I68: =IFERROR(__xludf.DUMMYFUNCTION("""COMPUTED_VALUE"""),"") | J68: =IFERROR(__xludf.DUMMYFUNCTION("""COMPUTED_VALUE"""),"") | K68: =IFERROR(__xludf.DUMMYFUNCTION("""COMPUTED_VALUE"""),"") | L68: =IFERROR(__xludf.DUMMYFUNCTION("""COMPUTED_VALUE"""),"")
B69: =IFERROR(__xludf.DUMMYFUNCTION("""COMPUTED_VALUE"""),"Blackbird") -> Blackbird | D69: =IFERROR(__xludf.DUMMYFUNCTION("""COMPUTED_VALUE"""),"") | E69: =IFERROR(__xludf.DUMMYFUNCTION("""COMPUTED_VALUE"""),"5ft") -> 5ft | F69: =IFERROR(__xludf.DUMMYFUNCTION("""COMPUTED_VALUE"""),"You deploy a Blackbird, a small artifice drone that outputs a grainy image to a device on your wrist. The blackbird has a maximum range of 3000ft and can observe major movements and structures such as doors and enemies. The drone cannot display fine mov"&"ements or detail such as words in a book without being up close, but can see large signs. The blackbird is the size of a walnut and is relatively quiet, and can only be heard by those with normal human hearing within 10 ft. The fuel shell lasts for one f"&"light, up to 15 minutes. If your Blackbird is lost or damaged, you must create a new one as an errand action before you can use this again.") -> You deploy a Blackbird, a small artifice drone that outputs a grainy image to a device on your wrist. The blackbird has a maximum range of 3000ft and can observe major movements and structures such as doors and enemies. The drone cannot display fine movements or detail such as words in a book without being up close, but can see large signs. The blackbird is the size of a walnut and is relatively quiet, and can only be heard by those with normal human hearing within 10 ft. The fuel shell lasts for one flight, up to 15 minutes. If your Blackbird is lost or damaged, you must create a new one as an errand action before you can use this again. | G69: =IFERROR(__xludf.DUMMYFUNCTION("""COMPUTED_VALUE"""),"") | H69: =IFERROR(__xludf.DUMMYFUNCTION("""COMPUTED_VALUE"""),"1 AP, 1 Small Shell") -> 1 AP, 1 Small Shell | I69: =IFERROR(__xludf.DUMMYFUNCTION("""COMPUTED_VALUE"""),"1 AP") -> 1 AP | J69: =IFERROR(__xludf.DUMMYFUNCTION("""COMPUTED_VALUE"""),"") | K69: =IFERROR(__xludf.DUMMYFUNCTION("""COMPUTED_VALUE"""),"") | L69: =IFERROR(__xludf.DUMMYFUNCTION("""COMPUTED_VALUE"""),"")
B70: =IFERROR(__xludf.DUMMYFUNCTION("""COMPUTED_VALUE"""),"Blacksmith Core Crafting") -> Blacksmith Core Crafting | D70: =IFERROR(__xludf.DUMMYFUNCTION("""COMPUTED_VALUE"""),"") | E70: =IFERROR(__xludf.DUMMYFUNCTION("""COMPUTED_VALUE"""),"") | F70: =IFERROR(__xludf.DUMMYFUNCTION("""COMPUTED_VALUE"""),"Blacksmith’s Modification A Cost: X Crafting Points Description: You add an A-Type modification to the weapon or tool. See the Universal Weapon or Crafting mods page as well as the individual weapon page for details. Each modification has its own cost. We"&"apon Alloy Cost: X Crafting Points Description: You mix a special material into the smithing weapon. Each material has its own crafting point cost. Create Ingot Cost: Errand Description: You create an ingot from blacksmithing base materials or from blacks"&"mithing special materials. See Item: Blacksmithing Materials.") -> Blacksmith’s Modification A Cost: X Crafting Points Description: You add an A-Type modification to the weapon or tool. See the Universal Weapon or Crafting mods page as well as the individual weapon page for details. Each modification has its own cost. Weapon Alloy Cost: X Crafting Points Description: You mix a special material into the smithing weapon. Each material has its own crafting point cost. Create Ingot Cost: Errand Description: You create an ingot from blacksmithing base materials or from blacksmithing special materials. See Item: Blacksmithing Materials. | G70: =IFERROR(__xludf.DUMMYFUNCTION("""COMPUTED_VALUE"""),"") | H70: =IFERROR(__xludf.DUMMYFUNCTION("""COMPUTED_VALUE"""),"") | I70: =IFERROR(__xludf.DUMMYFUNCTION("""COMPUTED_VALUE"""),"") | J70: =IFERROR(__xludf.DUMMYFUNCTION("""COMPUTED_VALUE"""),"") | K70: =IFERROR(__xludf.DUMMYFUNCTION("""COMPUTED_VALUE"""),"") | L70: =IFERROR(__xludf.DUMMYFUNCTION("""COMPUTED_VALUE"""),"")
B71: =IFERROR(__xludf.DUMMYFUNCTION("""COMPUTED_VALUE"""),"Blast Away") -> Blast Away | D71: =IFERROR(__xludf.DUMMYFUNCTION("""COMPUTED_VALUE"""),"") | E71: =IFERROR(__xludf.DUMMYFUNCTION("""COMPUTED_VALUE"""),"5ft") -> 5ft | F71: =IFERROR(__xludf.DUMMYFUNCTION("""COMPUTED_VALUE"""),"You fire a point blank shot at an enemy unit. The enemy must save against your Potency or be knocked back 5ft and take Light Damage. This ability does not provoke attacks of opportunity.") -> You fire a point blank shot at an enemy unit. The enemy must save against your Potency or be knocked back 5ft and take Light Damage. This ability does not provoke attacks of opportunity. | G71: =IFERROR(__xludf.DUMMYFUNCTION("""COMPUTED_VALUE"""),"") | H71: =IFERROR(__xludf.DUMMYFUNCTION("""COMPUTED_VALUE"""),"1 AP") -> 1 AP | I71: =IFERROR(__xludf.DUMMYFUNCTION("""COMPUTED_VALUE"""),"1 AP") -> 1 AP | J71: =IFERROR(__xludf.DUMMYFUNCTION("""COMPUTED_VALUE"""),"") | K71: =IFERROR(__xludf.DUMMYFUNCTION("""COMPUTED_VALUE"""),"") | L71: =IFERROR(__xludf.DUMMYFUNCTION("""COMPUTED_VALUE"""),"")
B72: =IFERROR(__xludf.DUMMYFUNCTION("""COMPUTED_VALUE"""),"Blast Wave") -> Blast Wave | D72: =IFERROR(__xludf.DUMMYFUNCTION("""COMPUTED_VALUE"""),"Fire, Spell, Blanketing") -> Fire, Spell, Blanketing | E72: =IFERROR(__xludf.DUMMYFUNCTION("""COMPUTED_VALUE"""),"Self") -> Self | F72: =IFERROR(__xludf.DUMMYFUNCTION("""COMPUTED_VALUE"""),"You may make a Light attack that deals Fire damage against every character within 10ft of you. On damage, they are pushed back 10ft. This spell does not provoke attacks of opportunity.") -> You may make a Light attack that deals Fire damage against every character within 10ft of you. On damage, they are pushed back 10ft. This spell does not provoke attacks of opportunity. | G72: =IFERROR(__xludf.DUMMYFUNCTION("""COMPUTED_VALUE"""),"") | H72: =IFERROR(__xludf.DUMMYFUNCTION("""COMPUTED_VALUE"""),"2 AP") -> 2 AP | I72: =IFERROR(__xludf.DUMMYFUNCTION("""COMPUTED_VALUE"""),"2 AP") -> 2 AP | J72: =IFERROR(__xludf.DUMMYFUNCTION("""COMPUTED_VALUE"""),"") | K72: =IFERROR(__xludf.DUMMYFUNCTION("""COMPUTED_VALUE"""),"") | L72: =IFERROR(__xludf.DUMMYFUNCTION("""COMPUTED_VALUE"""),"")
B73: =IFERROR(__xludf.DUMMYFUNCTION("""COMPUTED_VALUE"""),"Blinding Dust") -> Blinding Dust | D73: =IFERROR(__xludf.DUMMYFUNCTION("""COMPUTED_VALUE"""),"Sidestep, Blinded, Circuit") -> Sidestep, Blinded, Circuit | E73: =IFERROR(__xludf.DUMMYFUNCTION("""COMPUTED_VALUE"""),"5ft") -> 5ft | F73: =IFERROR(__xludf.DUMMYFUNCTION("""COMPUTED_VALUE"""),"You flap your wings and blow dust in the eyes of the attacker, making them Blinded 6 until the end of their attack. If their attack against you misses, you may Sidestep 5ft.") -> You flap your wings and blow dust in the eyes of the attacker, making them Blinded 6 until the end of their attack. If their attack against you misses, you may Sidestep 5ft. | G73: =IFERROR(__xludf.DUMMYFUNCTION("""COMPUTED_VALUE"""),"You are the target of an attack.") -> You are the target of an attack. | H73: =IFERROR(__xludf.DUMMYFUNCTION("""COMPUTED_VALUE"""),"2 MP, 1 RP") -> 2 MP, 1 RP | I73: =IFERROR(__xludf.DUMMYFUNCTION("""COMPUTED_VALUE"""),"") | J73: =IFERROR(__xludf.DUMMYFUNCTION("""COMPUTED_VALUE"""),"2 MP") -> 2 MP | K73: =IFERROR(__xludf.DUMMYFUNCTION("""COMPUTED_VALUE"""),"1 RP") -> 1 RP | L73: =IFERROR(__xludf.DUMMYFUNCTION("""COMPUTED_VALUE"""),"")
B74: =IFERROR(__xludf.DUMMYFUNCTION("""COMPUTED_VALUE"""),"Blocking Move") -> Blocking Move | D74: =IFERROR(__xludf.DUMMYFUNCTION("""COMPUTED_VALUE"""),"") | E74: =IFERROR(__xludf.DUMMYFUNCTION("""COMPUTED_VALUE"""),"Self") -> Self | F74: =IFERROR(__xludf.DUMMYFUNCTION("""COMPUTED_VALUE"""),"You move in front of the target and their movement action immediately ends. Until the end of their turn, they are Challenged by you and your next Block action against them costs 0 RP. If they willingly move from you through any method (including teleports"&") you may make a Heavy attack against them with Sure Hit. Your movement may ignore Line Movement restrictions for this ability.") -> You move in front of the target and their movement action immediately ends. Until the end of their turn, they are Challenged by you and your next Block action against them costs 0 RP. If they willingly move from you through any method (including teleports) you may make a Heavy attack against them with Sure Hit. Your movement may ignore Line Movement restrictions for this ability. | G74: =IFERROR(__xludf.DUMMYFUNCTION("""COMPUTED_VALUE"""),"You made an opportunity attack against a target moving away from you. Must be mounted.") -> You made an opportunity attack against a target moving away from you. Must be mounted. | H74: =IFERROR(__xludf.DUMMYFUNCTION("""COMPUTED_VALUE"""),"1 RP") -> 1 RP | I74: =IFERROR(__xludf.DUMMYFUNCTION("""COMPUTED_VALUE"""),"") | J74: =IFERROR(__xludf.DUMMYFUNCTION("""COMPUTED_VALUE"""),"") | K74: =IFERROR(__xludf.DUMMYFUNCTION("""COMPUTED_VALUE"""),"1 RP") -> 1 RP | L74: =IFERROR(__xludf.DUMMYFUNCTION("""COMPUTED_VALUE"""),"")
B75: =IFERROR(__xludf.DUMMYFUNCTION("""COMPUTED_VALUE"""),"Blood Drain") -> Blood Drain | D75: =IFERROR(__xludf.DUMMYFUNCTION("""COMPUTED_VALUE"""),"Healing, Safe") -> Healing, Safe | E75: =IFERROR(__xludf.DUMMYFUNCTION("""COMPUTED_VALUE"""),"40ft") -> 40ft | F75: =IFERROR(__xludf.DUMMYFUNCTION("""COMPUTED_VALUE"""),"You make a Light Attack that deals Dark damage against the target. On damage, you recover HP equal to your Toughness + 3.") -> You make a Light Attack that deals Dark damage against the target. On damage, you recover HP equal to your Toughness + 3. | G75: =IFERROR(__xludf.DUMMYFUNCTION("""COMPUTED_VALUE"""),"Target must be a living creature. Target cannot be an ally.") -> Target must be a living creature. Target cannot be an ally. | H75: =IFERROR(__xludf.DUMMYFUNCTION("""COMPUTED_VALUE"""),"1 AP, 1 MP") -> 1 AP, 1 MP | I75: =IFERROR(__xludf.DUMMYFUNCTION("""COMPUTED_VALUE"""),"1 AP") -> 1 AP | J75: =IFERROR(__xludf.DUMMYFUNCTION("""COMPUTED_VALUE"""),"1 MP") -> 1 MP | K75: =IFERROR(__xludf.DUMMYFUNCTION("""COMPUTED_VALUE"""),"") | L75: =IFERROR(__xludf.DUMMYFUNCTION("""COMPUTED_VALUE"""),"")
B76: =IFERROR(__xludf.DUMMYFUNCTION("""COMPUTED_VALUE"""),"Blood Frenzy") -> Blood Frenzy | D76: =IFERROR(__xludf.DUMMYFUNCTION("""COMPUTED_VALUE"""),"") | E76: =IFERROR(__xludf.DUMMYFUNCTION("""COMPUTED_VALUE"""),"Self") -> Self | F76: =IFERROR(__xludf.DUMMYFUNCTION("""COMPUTED_VALUE"""),"You go into a blood frenzy, mindlessly attacking enemies near you. While the blood frenzy lasts, you must attack the nearest enemy target with a basic unarmed attack. If two targets are equally close, you may choose which one you attack. If no enemies are"&" within range, you must use your movement to move closer to the closest visible enemy until you can attack them. While under the effect of blood frenzy, you heal for half the damage you deal with your unarmed attacks. You cannot use Vampire Bite while und"&"er the effect of Blood Frenzy. This effect lasts until all visible enemies are dead or until your mana runs out. At the start of your turn, you lose 2 mana.") -> You go into a blood frenzy, mindlessly attacking enemies near you. While the blood frenzy lasts, you must attack the nearest enemy target with a basic unarmed attack. If two targets are equally close, you may choose which one you attack. If no enemies are within range, you must use your movement to move closer to the closest visible enemy until you can attack them. While under the effect of blood frenzy, you heal for half the damage you deal with your unarmed attacks. You cannot use Vampire Bite while under the effect of Blood Frenzy. This effect lasts until all visible enemies are dead or until your mana runs out. At the start of your turn, you lose 2 mana. | G76: =IFERROR(__xludf.DUMMYFUNCTION("""COMPUTED_VALUE"""),"") | H76: =IFERROR(__xludf.DUMMYFUNCTION("""COMPUTED_VALUE"""),"0 AP, 2 MP") -> 0 AP, 2 MP | I76: =IFERROR(__xludf.DUMMYFUNCTION("""COMPUTED_VALUE"""),"0 AP") -> 0 AP | J76: =IFERROR(__xludf.DUMMYFUNCTION("""COMPUTED_VALUE"""),"2 MP") -> 2 MP | K76: =IFERROR(__xludf.DUMMYFUNCTION("""COMPUTED_VALUE"""),"") | L76: =IFERROR(__xludf.DUMMYFUNCTION("""COMPUTED_VALUE"""),"")
B77: =IFERROR(__xludf.DUMMYFUNCTION("""COMPUTED_VALUE"""),"Blood Shield") -> Blood Shield | D77: =IFERROR(__xludf.DUMMYFUNCTION("""COMPUTED_VALUE"""),"Aid, Healing, Shield") -> Aid, Healing, Shield | E77: =IFERROR(__xludf.DUMMYFUNCTION("""COMPUTED_VALUE"""),"40ft") -> 40ft | F77: =IFERROR(__xludf.DUMMYFUNCTION("""COMPUTED_VALUE"""),"You grant the target 1 RP that must be spent on the Block action against the triggering attack. They gain a +5 bonus to their Guard for this Block action. After the attack, the target regains HP equal to half the damage blocked (Blocked meaning the damage"&" reduced through block, not necessarily your total block value).") -> You grant the target 1 RP that must be spent on the Block action against the triggering attack. They gain a +5 bonus to their Guard for this Block action. After the attack, the target regains HP equal to half the damage blocked (Blocked meaning the damage reduced through block, not necessarily your total block value). | G77: =IFERROR(__xludf.DUMMYFUNCTION("""COMPUTED_VALUE"""),"Target is the target of an attack.") -> Target is the target of an attack. | H77: =IFERROR(__xludf.DUMMYFUNCTION("""COMPUTED_VALUE"""),"2 MP, 1 RP") -> 2 MP, 1 RP | I77: =IFERROR(__xludf.DUMMYFUNCTION("""COMPUTED_VALUE"""),"") | J77: =IFERROR(__xludf.DUMMYFUNCTION("""COMPUTED_VALUE"""),"2 MP") -> 2 MP | K77: =IFERROR(__xludf.DUMMYFUNCTION("""COMPUTED_VALUE"""),"1 RP") -> 1 RP | L77: =IFERROR(__xludf.DUMMYFUNCTION("""COMPUTED_VALUE"""),"")
B78: =IFERROR(__xludf.DUMMYFUNCTION("""COMPUTED_VALUE"""),"Bloodbolt") -> Bloodbolt | D78: =IFERROR(__xludf.DUMMYFUNCTION("""COMPUTED_VALUE"""),"Overcharge") -> Overcharge | E78: =IFERROR(__xludf.DUMMYFUNCTION("""COMPUTED_VALUE"""),"60ft") -> 60ft | F78: =IFERROR(__xludf.DUMMYFUNCTION("""COMPUTED_VALUE"""),"You make a Light attack against the target. Overcharge: You may spend X HP to increase the damage the attack deals by X. X may not exceed your Toughness.") -> You make a Light attack against the target. Overcharge: You may spend X HP to increase the damage the attack deals by X. X may not exceed your Toughness. | G78: =IFERROR(__xludf.DUMMYFUNCTION("""COMPUTED_VALUE"""),"") | H78: =IFERROR(__xludf.DUMMYFUNCTION("""COMPUTED_VALUE"""),"1 AP") -> 1 AP | I78: =IFERROR(__xludf.DUMMYFUNCTION("""COMPUTED_VALUE"""),"1 AP") -> 1 AP | J78: =IFERROR(__xludf.DUMMYFUNCTION("""COMPUTED_VALUE"""),"") | K78: =IFERROR(__xludf.DUMMYFUNCTION("""COMPUTED_VALUE"""),"") | L78: =IFERROR(__xludf.DUMMYFUNCTION("""COMPUTED_VALUE"""),"")
B79: =IFERROR(__xludf.DUMMYFUNCTION("""COMPUTED_VALUE"""),"Blue Tide") -> Blue Tide | D79: =IFERROR(__xludf.DUMMYFUNCTION("""COMPUTED_VALUE"""),"Domain, Spell") -> Domain, Spell | E79: =IFERROR(__xludf.DUMMYFUNCTION("""COMPUTED_VALUE"""),"Self") -> Self | F79: =IFERROR(__xludf.DUMMYFUNCTION("""COMPUTED_VALUE"""),"You create a 15ft radius zone of 1ft of water in a circle around yourself. This zone of water remains stationary at its original position, even after you move. This zone lasts until the end of the encounter and automatically replenishes itself when Aqua D"&"rill is used inside of it. You may have multiple of these zones active at once.") -> You create a 15ft radius zone of 1ft of water in a circle around yourself. This zone of water remains stationary at its original position, even after you move. This zone lasts until the end of the encounter and automatically replenishes itself when Aqua Drill is used inside of it. You may have multiple of these zones active at once. | G79: =IFERROR(__xludf.DUMMYFUNCTION("""COMPUTED_VALUE"""),"") | H79: =IFERROR(__xludf.DUMMYFUNCTION("""COMPUTED_VALUE"""),"1 AP") -> 1 AP | I79: =IFERROR(__xludf.DUMMYFUNCTION("""COMPUTED_VALUE"""),"1 AP") -> 1 AP | J79: =IFERROR(__xludf.DUMMYFUNCTION("""COMPUTED_VALUE"""),"") | K79: =IFERROR(__xludf.DUMMYFUNCTION("""COMPUTED_VALUE"""),"") | L79: =IFERROR(__xludf.DUMMYFUNCTION("""COMPUTED_VALUE"""),"")
B80: =IFERROR(__xludf.DUMMYFUNCTION("""COMPUTED_VALUE"""),"Bolting") -> Bolting | D80: =IFERROR(__xludf.DUMMYFUNCTION("""COMPUTED_VALUE"""),"Lightning, Rapid, Spell") -> Lightning, Rapid, Spell | E80: =IFERROR(__xludf.DUMMYFUNCTION("""COMPUTED_VALUE"""),"360ft") -> 360ft | F80: =IFERROR(__xludf.DUMMYFUNCTION("""COMPUTED_VALUE"""),"You may make a Heavy Attack that deals Lightning Damage with a bolt from the sky. On damage, inflict Static X where X equals your Focus x 3. As the attack from the sky, any cover is calculated from above the target rather than from your path to the target"&".") -> You may make a Heavy Attack that deals Lightning Damage with a bolt from the sky. On damage, inflict Static X where X equals your Focus x 3. As the attack from the sky, any cover is calculated from above the target rather than from your path to the target. | G80: =IFERROR(__xludf.DUMMYFUNCTION("""COMPUTED_VALUE"""),"") | H80: =IFERROR(__xludf.DUMMYFUNCTION("""COMPUTED_VALUE"""),"2 AP, 1 MP") -> 2 AP, 1 MP | I80: =IFERROR(__xludf.DUMMYFUNCTION("""COMPUTED_VALUE"""),"2 AP") -> 2 AP | J80: =IFERROR(__xludf.DUMMYFUNCTION("""COMPUTED_VALUE"""),"1 MP") -> 1 MP | K80: =IFERROR(__xludf.DUMMYFUNCTION("""COMPUTED_VALUE"""),"") | L80: =IFERROR(__xludf.DUMMYFUNCTION("""COMPUTED_VALUE"""),"")
B81: =IFERROR(__xludf.DUMMYFUNCTION("""COMPUTED_VALUE"""),"Bone Armor") -> Bone Armor | D81: =IFERROR(__xludf.DUMMYFUNCTION("""COMPUTED_VALUE"""),"") | E81: =IFERROR(__xludf.DUMMYFUNCTION("""COMPUTED_VALUE"""),"30ft") -> 30ft | F81: =IFERROR(__xludf.DUMMYFUNCTION("""COMPUTED_VALUE"""),"You target and destroy a corpse within range to give yourself Bone Armor, which gives you a +2 bonus to your guard. Bone Armor lasts until the end of the encounter or until you take 2 or more damage from an attack.") -> You target and destroy a corpse within range to give yourself Bone Armor, which gives you a +2 bonus to your guard. Bone Armor lasts until the end of the encounter or until you take 2 or more damage from an attack. | G81: =IFERROR(__xludf.DUMMYFUNCTION("""COMPUTED_VALUE"""),"Corpse within range.") -> Corpse within range. | H81: =IFERROR(__xludf.DUMMYFUNCTION("""COMPUTED_VALUE"""),"1 AP") -> 1 AP | I81: =IFERROR(__xludf.DUMMYFUNCTION("""COMPUTED_VALUE"""),"1 AP") -> 1 AP | J81: =IFERROR(__xludf.DUMMYFUNCTION("""COMPUTED_VALUE"""),"") | K81: =IFERROR(__xludf.DUMMYFUNCTION("""COMPUTED_VALUE"""),"") | L81: =IFERROR(__xludf.DUMMYFUNCTION("""COMPUTED_VALUE"""),"")
B82: =IFERROR(__xludf.DUMMYFUNCTION("""COMPUTED_VALUE"""),"Bottle Smash") -> Bottle Smash | D82: =IFERROR(__xludf.DUMMYFUNCTION("""COMPUTED_VALUE"""),"Daze, Prone") -> Daze, Prone | E82: =IFERROR(__xludf.DUMMYFUNCTION("""COMPUTED_VALUE"""),"5ft") -> 5ft | F82: =IFERROR(__xludf.DUMMYFUNCTION("""COMPUTED_VALUE"""),"You may make a Light Attack against the target. On damage, the target becomes Dazed. After this attack, your improvised weapon breaks.") -> You may make a Light Attack against the target. On damage, the target becomes Dazed. After this attack, your improvised weapon breaks. | G82: =IFERROR(__xludf.DUMMYFUNCTION("""COMPUTED_VALUE"""),"Improvised weapon only.") -> Improvised weapon only. | H82: =IFERROR(__xludf.DUMMYFUNCTION("""COMPUTED_VALUE"""),"1 AP") -> 1 AP | I82: =IFERROR(__xludf.DUMMYFUNCTION("""COMPUTED_VALUE"""),"1 AP") -> 1 AP | J82: =IFERROR(__xludf.DUMMYFUNCTION("""COMPUTED_VALUE"""),"") | K82: =IFERROR(__xludf.DUMMYFUNCTION("""COMPUTED_VALUE"""),"") | L82: =IFERROR(__xludf.DUMMYFUNCTION("""COMPUTED_VALUE"""),"")
B83: =IFERROR(__xludf.DUMMYFUNCTION("""COMPUTED_VALUE"""),"Bottle Toss") -> Bottle Toss | D83: =IFERROR(__xludf.DUMMYFUNCTION("""COMPUTED_VALUE"""),"Daze") -> Daze | E83: =IFERROR(__xludf.DUMMYFUNCTION("""COMPUTED_VALUE"""),"20ft") -> 20ft | F83: =IFERROR(__xludf.DUMMYFUNCTION("""COMPUTED_VALUE"""),"You may make a Light Attack against the target. On damage, the target becomes Dazed. After this attack, your improvised weapon breaks.") -> You may make a Light Attack against the target. On damage, the target becomes Dazed. After this attack, your improvised weapon breaks. | G83: =IFERROR(__xludf.DUMMYFUNCTION("""COMPUTED_VALUE"""),"Improvised weapon only.") -> Improvised weapon only. | H83: =IFERROR(__xludf.DUMMYFUNCTION("""COMPUTED_VALUE"""),"1 AP, 1 MP") -> 1 AP, 1 MP | I83: =IFERROR(__xludf.DUMMYFUNCTION("""COMPUTED_VALUE"""),"1 AP") -> 1 AP | J83: =IFERROR(__xludf.DUMMYFUNCTION("""COMPUTED_VALUE"""),"1 MP") -> 1 MP | K83: =IFERROR(__xludf.DUMMYFUNCTION("""COMPUTED_VALUE"""),"") | L83: =IFERROR(__xludf.DUMMYFUNCTION("""COMPUTED_VALUE"""),"")
B84: =IFERROR(__xludf.DUMMYFUNCTION("""COMPUTED_VALUE"""),"Boundless Wind Stance") -> Boundless Wind Stance | D84: =IFERROR(__xludf.DUMMYFUNCTION("""COMPUTED_VALUE"""),"Stance") -> Stance | E84: =IFERROR(__xludf.DUMMYFUNCTION("""COMPUTED_VALUE"""),"Self") -> Self | F84: =IFERROR(__xludf.DUMMYFUNCTION("""COMPUTED_VALUE"""),"You enter the Wind Stance, an unarmed style focusing around aerial combat. While in this stance, you may Hover and Fly up to your speed. If you already have a natural Flying speed or the Flight racial ability, your flying speed is increased by 10ft. This"&" stance lasts until you enter a different stance or make an attack with anything other than a melee attack or an ability with the Unarmed Strike keyword.") -> You enter the Wind Stance, an unarmed style focusing around aerial combat. While in this stance, you may Hover and Fly up to your speed. If you already have a natural Flying speed or the Flight racial ability, your flying speed is increased by 10ft. This stance lasts until you enter a different stance or make an attack with anything other than a melee attack or an ability with the Unarmed Strike keyword. | G84: =IFERROR(__xludf.DUMMYFUNCTION("""COMPUTED_VALUE"""),"") | H84: =IFERROR(__xludf.DUMMYFUNCTION("""COMPUTED_VALUE"""),"0 AP, 1 MP") -> 0 AP, 1 MP | I84: =IFERROR(__xludf.DUMMYFUNCTION("""COMPUTED_VALUE"""),"0 AP") -> 0 AP | J84: =IFERROR(__xludf.DUMMYFUNCTION("""COMPUTED_VALUE"""),"1 MP") -> 1 MP | K84: =IFERROR(__xludf.DUMMYFUNCTION("""COMPUTED_VALUE"""),"") | L84: =IFERROR(__xludf.DUMMYFUNCTION("""COMPUTED_VALUE"""),"")
B85: =IFERROR(__xludf.DUMMYFUNCTION("""COMPUTED_VALUE"""),"Break Away") -> Break Away | D85: =IFERROR(__xludf.DUMMYFUNCTION("""COMPUTED_VALUE"""),"") | E85: =IFERROR(__xludf.DUMMYFUNCTION("""COMPUTED_VALUE"""),"Self") -> Self | F85: =IFERROR(__xludf.DUMMYFUNCTION("""COMPUTED_VALUE"""),"You disengage and may move up to half your speed away from the nearest enemy.") -> You disengage and may move up to half your speed away from the nearest enemy. | G85: =IFERROR(__xludf.DUMMYFUNCTION("""COMPUTED_VALUE"""),"Must be mounted.") -> Must be mounted. | H85: =IFERROR(__xludf.DUMMYFUNCTION("""COMPUTED_VALUE"""),"1 AP, 2 MP") -> 1 AP, 2 MP | I85: =IFERROR(__xludf.DUMMYFUNCTION("""COMPUTED_VALUE"""),"1 AP") -> 1 AP | J85: =IFERROR(__xludf.DUMMYFUNCTION("""COMPUTED_VALUE"""),"2 MP") -> 2 MP | K85: =IFERROR(__xludf.DUMMYFUNCTION("""COMPUTED_VALUE"""),"") | L85: =IFERROR(__xludf.DUMMYFUNCTION("""COMPUTED_VALUE"""),"")
B86: =IFERROR(__xludf.DUMMYFUNCTION("""COMPUTED_VALUE"""),"Break Free") -> Break Free | D86: =IFERROR(__xludf.DUMMYFUNCTION("""COMPUTED_VALUE"""),"Rage") -> Rage | E86: =IFERROR(__xludf.DUMMYFUNCTION("""COMPUTED_VALUE"""),"Self") -> Self | F86: =IFERROR(__xludf.DUMMYFUNCTION("""COMPUTED_VALUE"""),"You may use this ability when you would be affected by a Stun, Root, Fear or a similar effect that would prevent you from acting that's inflicted by an enemy. You may immediately enter Rage Stance without spending any AP or RP. You gain immunity to this e"&"ffect for the duration of the Rage.") -> You may use this ability when you would be affected by a Stun, Root, Fear or a similar effect that would prevent you from acting that's inflicted by an enemy. You may immediately enter Rage Stance without spending any AP or RP. You gain immunity to this effect for the duration of the Rage. | G86: =IFERROR(__xludf.DUMMYFUNCTION("""COMPUTED_VALUE"""),"Not in Rage Stance.") -> Not in Rage Stance. | H86: =IFERROR(__xludf.DUMMYFUNCTION("""COMPUTED_VALUE"""),"0 RP") -> 0 RP | I86: =IFERROR(__xludf.DUMMYFUNCTION("""COMPUTED_VALUE"""),"") | J86: =IFERROR(__xludf.DUMMYFUNCTION("""COMPUTED_VALUE"""),"") | K86: =IFERROR(__xludf.DUMMYFUNCTION("""COMPUTED_VALUE"""),"0 RP") -> 0 RP | L86: =IFERROR(__xludf.DUMMYFUNCTION("""COMPUTED_VALUE"""),"")
B87: =IFERROR(__xludf.DUMMYFUNCTION("""COMPUTED_VALUE"""),"Brilliance") -> Brilliance | D87: =IFERROR(__xludf.DUMMYFUNCTION("""COMPUTED_VALUE"""),"Spell, Illumination, Light") -> Spell, Illumination, Light | E87: =IFERROR(__xludf.DUMMYFUNCTION("""COMPUTED_VALUE"""),"80ft") -> 80ft | F87: =IFERROR(__xludf.DUMMYFUNCTION("""COMPUTED_VALUE"""),"You make a Light attack against the target dealing Holy(Light) damage. On damage, inflict Illumination X, where X equals your Focus / 2 (rounded down) until the end of your next turn.") -> You make a Light attack against the target dealing Holy(Light) damage. On damage, inflict Illumination X, where X equals your Focus / 2 (rounded down) until the end of your next turn. | G87: =IFERROR(__xludf.DUMMYFUNCTION("""COMPUTED_VALUE"""),"") | H87: =IFERROR(__xludf.DUMMYFUNCTION("""COMPUTED_VALUE"""),"1 AP, 1 MP") -> 1 AP, 1 MP | I87: =IFERROR(__xludf.DUMMYFUNCTION("""COMPUTED_VALUE"""),"1 AP") -> 1 AP | J87: =IFERROR(__xludf.DUMMYFUNCTION("""COMPUTED_VALUE"""),"1 MP") -> 1 MP | K87: =IFERROR(__xludf.DUMMYFUNCTION("""COMPUTED_VALUE"""),"") | L87: =IFERROR(__xludf.DUMMYFUNCTION("""COMPUTED_VALUE"""),"")
B88: =IFERROR(__xludf.DUMMYFUNCTION("""COMPUTED_VALUE"""),"Bring out your dead") -> Bring out your dead | D88: =IFERROR(__xludf.DUMMYFUNCTION("""COMPUTED_VALUE"""),"Encounter Start") -> Encounter Start | E88: =IFERROR(__xludf.DUMMYFUNCTION("""COMPUTED_VALUE"""),"10ft") -> 10ft | F88: =IFERROR(__xludf.DUMMYFUNCTION("""COMPUTED_VALUE"""),"You summon 3 zombies, as if you used Raise Undead 3 times. Restrictions on max zombie limit still apply. Does not require corpses.") -> You summon 3 zombies, as if you used Raise Undead 3 times. Restrictions on max zombie limit still apply. Does not require corpses. | G88: =IFERROR(__xludf.DUMMYFUNCTION("""COMPUTED_VALUE"""),"") | H88: =IFERROR(__xludf.DUMMYFUNCTION("""COMPUTED_VALUE"""),"") | I88: =IFERROR(__xludf.DUMMYFUNCTION("""COMPUTED_VALUE"""),"") | J88: =IFERROR(__xludf.DUMMYFUNCTION("""COMPUTED_VALUE"""),"") | K88: =IFERROR(__xludf.DUMMYFUNCTION("""COMPUTED_VALUE"""),"") | L88: =IFERROR(__xludf.DUMMYFUNCTION("""COMPUTED_VALUE"""),"")
B89: =IFERROR(__xludf.DUMMYFUNCTION("""COMPUTED_VALUE"""),"Bulk Orders") -> Bulk Orders | D89: =IFERROR(__xludf.DUMMYFUNCTION("""COMPUTED_VALUE"""),"") | E89: =IFERROR(__xludf.DUMMYFUNCTION("""COMPUTED_VALUE"""),"") | F89: =IFERROR(__xludf.DUMMYFUNCTION("""COMPUTED_VALUE"""),"When purchasing five or more of the same item from an NPC or Procurement, reduce the total price by 10%. For commodities, you must purchase at least 4000 units.") -> When purchasing five or more of the same item from an NPC or Procurement, reduce the total price by 10%. For commodities, you must purchase at least 4000 units. | G89: =IFERROR(__xludf.DUMMYFUNCTION("""COMPUTED_VALUE"""),"") | H89: =IFERROR(__xludf.DUMMYFUNCTION("""COMPUTED_VALUE"""),"") | I89: =IFERROR(__xludf.DUMMYFUNCTION("""COMPUTED_VALUE"""),"") | J89: =IFERROR(__xludf.DUMMYFUNCTION("""COMPUTED_VALUE"""),"") | K89: =IFERROR(__xludf.DUMMYFUNCTION("""COMPUTED_VALUE"""),"") | L89: =IFERROR(__xludf.DUMMYFUNCTION("""COMPUTED_VALUE"""),"")
B90: =IFERROR(__xludf.DUMMYFUNCTION("""COMPUTED_VALUE"""),"Bullet Magnet") -> Bullet Magnet | D90: =IFERROR(__xludf.DUMMYFUNCTION("""COMPUTED_VALUE"""),"") | E90: =IFERROR(__xludf.DUMMYFUNCTION("""COMPUTED_VALUE"""),"20ft") -> 20ft | F90: =IFERROR(__xludf.DUMMYFUNCTION("""COMPUTED_VALUE"""),"Until the start of your next turn, any single target Ranged Weapon Attack made against an ally in range is made against you instead.") -> Until the start of your next turn, any single target Ranged Weapon Attack made against an ally in range is made against you instead. | G90: =IFERROR(__xludf.DUMMYFUNCTION("""COMPUTED_VALUE"""),"Must be using a greatshield.") -> Must be using a greatshield. | H90: =IFERROR(__xludf.DUMMYFUNCTION("""COMPUTED_VALUE"""),"1 AP") -> 1 AP | I90: =IFERROR(__xludf.DUMMYFUNCTION("""COMPUTED_VALUE"""),"1 AP") -> 1 AP | J90: =IFERROR(__xludf.DUMMYFUNCTION("""COMPUTED_VALUE"""),"") | K90: =IFERROR(__xludf.DUMMYFUNCTION("""COMPUTED_VALUE"""),"") | L90: =IFERROR(__xludf.DUMMYFUNCTION("""COMPUTED_VALUE"""),"")
B91: =IFERROR(__xludf.DUMMYFUNCTION("""COMPUTED_VALUE"""),"Bunshin Tai no Jutsu") -> Bunshin Tai no Jutsu | D91: =IFERROR(__xludf.DUMMYFUNCTION("""COMPUTED_VALUE"""),"Ninjutsu, Stealth") -> Ninjutsu, Stealth | E91: =IFERROR(__xludf.DUMMYFUNCTION("""COMPUTED_VALUE"""),"5ft") -> 5ft | F91: =IFERROR(__xludf.DUMMYFUNCTION("""COMPUTED_VALUE"""),"You create a body double of yourself that has the same stats you do at the time of creation. You and the body double share the same HP, Mana, AP and RP etc and unless stated otherwise your clones are considered you. All effects on you are mirrored on your"&" clone and vice versa, however a clone cannot benefit from Presence Concealment. When taking an action, you may choose to let the user be yourself or the body double. However, the body double may only use basic abilities and abilities with the Ninjutsu ke"&"yword and cannot create more body doubles of itself. When you take the movement action or use a non-teleport movement ability, your clone may move for the same amount of distance as you moved. You may spend 0 AP or 1 RP to dismiss the body double. A clone"&" can never travel more than 300ft from your actual body, but while it lasts you may spend 2 AP to swap locations with it. A clone lasts until you rest.") -> You create a body double of yourself that has the same stats you do at the time of creation. You and the body double share the same HP, Mana, AP and RP etc and unless stated otherwise your clones are considered you. All effects on you are mirrored on your clone and vice versa, however a clone cannot benefit from Presence Concealment. When taking an action, you may choose to let the user be yourself or the body double. However, the body double may only use basic abilities and abilities with the Ninjutsu keyword and cannot create more body doubles of itself. When you take the movement action or use a non-teleport movement ability, your clone may move for the same amount of distance as you moved. You may spend 0 AP or 1 RP to dismiss the body double. A clone can never travel more than 300ft from your actual body, but while it lasts you may spend 2 AP to swap locations with it. A clone lasts until you rest. | G91: =IFERROR(__xludf.DUMMYFUNCTION("""COMPUTED_VALUE"""),"") | H91: =IFERROR(__xludf.DUMMYFUNCTION("""COMPUTED_VALUE"""),"1 AP, 2 MP") -> 1 AP, 2 MP | I91: =IFERROR(__xludf.DUMMYFUNCTION("""COMPUTED_VALUE"""),"1 AP") -> 1 AP | J91: =IFERROR(__xludf.DUMMYFUNCTION("""COMPUTED_VALUE"""),"2 MP") -> 2 MP | K91: =IFERROR(__xludf.DUMMYFUNCTION("""COMPUTED_VALUE"""),"") | L91: =IFERROR(__xludf.DUMMYFUNCTION("""COMPUTED_VALUE"""),"")
B92: =IFERROR(__xludf.DUMMYFUNCTION("""COMPUTED_VALUE"""),"Call of the Grave") -> Call of the Grave | D92: =IFERROR(__xludf.DUMMYFUNCTION("""COMPUTED_VALUE"""),"Challenge") -> Challenge | E92: =IFERROR(__xludf.DUMMYFUNCTION("""COMPUTED_VALUE"""),"60ft") -> 60ft | F92: =IFERROR(__xludf.DUMMYFUNCTION("""COMPUTED_VALUE"""),"You make a Heavy Attack against the target that deals Dark damage. On hit, if the target is large or smaller, you pull them to you. They are Challenged until the start of your next turn. This ability does not provoke an attack of opportunity.") -> You make a Heavy Attack against the target that deals Dark damage. On hit, if the target is large or smaller, you pull them to you. They are Challenged until the start of your next turn. This ability does not provoke an attack of opportunity. | G92: =IFERROR(__xludf.DUMMYFUNCTION("""COMPUTED_VALUE"""),"") | H92: =IFERROR(__xludf.DUMMYFUNCTION("""COMPUTED_VALUE"""),"2 AP, 2 MP") -> 2 AP, 2 MP | I92: =IFERROR(__xludf.DUMMYFUNCTION("""COMPUTED_VALUE"""),"2 AP") -> 2 AP | J92: =IFERROR(__xludf.DUMMYFUNCTION("""COMPUTED_VALUE"""),"2 MP") -> 2 MP | K92: =IFERROR(__xludf.DUMMYFUNCTION("""COMPUTED_VALUE"""),"") | L92: =IFERROR(__xludf.DUMMYFUNCTION("""COMPUTED_VALUE"""),"")
B93: =IFERROR(__xludf.DUMMYFUNCTION("""COMPUTED_VALUE"""),"Call to Grace") -> Call to Grace | D93: =IFERROR(__xludf.DUMMYFUNCTION("""COMPUTED_VALUE"""),"Sanctify") -> Sanctify | E93: =IFERROR(__xludf.DUMMYFUNCTION("""COMPUTED_VALUE"""),"60ft") -> 60ft | F93: =IFERROR(__xludf.DUMMYFUNCTION("""COMPUTED_VALUE"""),"You trigger the effect of Sanctify, healing the target of the attack by your sanctify amount (and reducing the sanctify stacks). If the attack targets multiple creatures, you only heal one.") -> You trigger the effect of Sanctify, healing the target of the attack by your sanctify amount (and reducing the sanctify stacks). If the attack targets multiple creatures, you only heal one. | G93: =IFERROR(__xludf.DUMMYFUNCTION("""COMPUTED_VALUE"""),"An enemy within range that inflicted with Sanctify is attacking an ally.") -> An enemy within range that inflicted with Sanctify is attacking an ally. | H93: =IFERROR(__xludf.DUMMYFUNCTION("""COMPUTED_VALUE"""),"0 RP") -> 0 RP | I93: =IFERROR(__xludf.DUMMYFUNCTION("""COMPUTED_VALUE"""),"") | J93: =IFERROR(__xludf.DUMMYFUNCTION("""COMPUTED_VALUE"""),"") | K93: =IFERROR(__xludf.DUMMYFUNCTION("""COMPUTED_VALUE"""),"0 RP") -> 0 RP | L93: =IFERROR(__xludf.DUMMYFUNCTION("""COMPUTED_VALUE"""),"")
B94: =IFERROR(__xludf.DUMMYFUNCTION("""COMPUTED_VALUE"""),"Can't Escape Death") -> Can't Escape Death | D94: =IFERROR(__xludf.DUMMYFUNCTION("""COMPUTED_VALUE"""),"Sidestep") -> Sidestep | E94: =IFERROR(__xludf.DUMMYFUNCTION("""COMPUTED_VALUE"""),"Melee Weapon Range") -> Melee Weapon Range | F94: =IFERROR(__xludf.DUMMYFUNCTION("""COMPUTED_VALUE"""),"You may use this after an enemy leaves your melee range. After the target finishes moving, you may sidestep up to your speed towards them. For 1 RP, you may move double your speed instead.") -> You may use this after an enemy leaves your melee range. After the target finishes moving, you may sidestep up to your speed towards them. For 1 RP, you may move double your speed instead. | G94: =IFERROR(__xludf.DUMMYFUNCTION("""COMPUTED_VALUE"""),"A target Challenged by you leaves your melee range.") -> A target Challenged by you leaves your melee range. | H94: =IFERROR(__xludf.DUMMYFUNCTION("""COMPUTED_VALUE"""),"0 RP") -> 0 RP | I94: =IFERROR(__xludf.DUMMYFUNCTION("""COMPUTED_VALUE"""),"") | J94: =IFERROR(__xludf.DUMMYFUNCTION("""COMPUTED_VALUE"""),"") | K94: =IFERROR(__xludf.DUMMYFUNCTION("""COMPUTED_VALUE"""),"0 RP") -> 0 RP | L94: =IFERROR(__xludf.DUMMYFUNCTION("""COMPUTED_VALUE"""),"")
B95: =IFERROR(__xludf.DUMMYFUNCTION("""COMPUTED_VALUE"""),"Cannonball") -> Cannonball | D95: =IFERROR(__xludf.DUMMYFUNCTION("""COMPUTED_VALUE"""),"Cannon, Artillery") -> Cannon, Artillery | E95: =IFERROR(__xludf.DUMMYFUNCTION("""COMPUTED_VALUE"""),"Ranged Weapon Range") -> Ranged Weapon Range | F95: =IFERROR(__xludf.DUMMYFUNCTION("""COMPUTED_VALUE"""),"You make 2 heavy attacks against the target and a light attack against all other enemies within 5ft of the target.") -> You make 2 heavy attacks against the target and a light attack against all other enemies within 5ft of the target. | G95: =IFERROR(__xludf.DUMMYFUNCTION("""COMPUTED_VALUE"""),"Cannon only.") -> Cannon only. | H95: =IFERROR(__xludf.DUMMYFUNCTION("""COMPUTED_VALUE"""),"4 AP") -> 4 AP | I95: =IFERROR(__xludf.DUMMYFUNCTION("""COMPUTED_VALUE"""),"4 AP") -> 4 AP | J95: =IFERROR(__xludf.DUMMYFUNCTION("""COMPUTED_VALUE"""),"") | K95: =IFERROR(__xludf.DUMMYFUNCTION("""COMPUTED_VALUE"""),"") | L95: =IFERROR(__xludf.DUMMYFUNCTION("""COMPUTED_VALUE"""),"")
B96: =IFERROR(__xludf.DUMMYFUNCTION("""COMPUTED_VALUE"""),"Canter") -> Canter | D96: =IFERROR(__xludf.DUMMYFUNCTION("""COMPUTED_VALUE"""),"Sidestep") -> Sidestep | E96: =IFERROR(__xludf.DUMMYFUNCTION("""COMPUTED_VALUE"""),"Self") -> Self | F96: =IFERROR(__xludf.DUMMYFUNCTION("""COMPUTED_VALUE"""),"You may Sidestep 10ft.") -> You may Sidestep 10ft. | G96: =IFERROR(__xludf.DUMMYFUNCTION("""COMPUTED_VALUE"""),"Must be mounted and can be used immediately after making a weapon attack.") -> Must be mounted and can be used immediately after making a weapon attack. | H96: =IFERROR(__xludf.DUMMYFUNCTION("""COMPUTED_VALUE"""),"0 AP, 1 MP") -> 0 AP, 1 MP | I96: =IFERROR(__xludf.DUMMYFUNCTION("""COMPUTED_VALUE"""),"0 AP") -> 0 AP | J96: =IFERROR(__xludf.DUMMYFUNCTION("""COMPUTED_VALUE"""),"1 MP") -> 1 MP | K96: =IFERROR(__xludf.DUMMYFUNCTION("""COMPUTED_VALUE"""),"") | L96: =IFERROR(__xludf.DUMMYFUNCTION("""COMPUTED_VALUE"""),"")
B97: =IFERROR(__xludf.DUMMYFUNCTION("""COMPUTED_VALUE"""),"Carpenter Basics") -> Carpenter Basics | D97: =IFERROR(__xludf.DUMMYFUNCTION("""COMPUTED_VALUE"""),"") | E97: =IFERROR(__xludf.DUMMYFUNCTION("""COMPUTED_VALUE"""),"") | F97: =IFERROR(__xludf.DUMMYFUNCTION("""COMPUTED_VALUE"""),"Carpenter's Modification A Cost: X Crafting Points Description: You add an A-Type modification to the weapon or tool. See the Universal Weapon page as well as the individual weapon page for details. Each modification has its own cost. Joining and Assembli"&"ng Cost: X Crafting Points Description: You mix a special material into the carpentry project. Each material has its own crafting point cost. Create Oil Coating Cost: Errand Description: You create an Oil Coating from Carpenter materials. See Items: Carp"&"enter Materials. Create Wood Block Cost: Errand Description: You create a Wood Block from Carpenter materials. See Items: Carpenter Materials. Infuse Wand Cost: 5 Crafting Points Description: You add a drop of Oil Coating into a wand, changing the built "&"in damage type to the element of the oil. Only works with oils that change the damage type. Does not consume the oil.") -> Carpenter's Modification A Cost: X Crafting Points Description: You add an A-Type modification to the weapon or tool. See the Universal Weapon page as well as the individual weapon page for details. Each modification has its own cost. Joining and Assembling Cost: X Crafting Points Description: You mix a special material into the carpentry project. Each material has its own crafting point cost. Create Oil Coating Cost: Errand Description: You create an Oil Coating from Carpenter materials. See Items: Carpenter Materials. Create Wood Block Cost: Errand Description: You create a Wood Block from Carpenter materials. See Items: Carpenter Materials. Infuse Wand Cost: 5 Crafting Points Description: You add a drop of Oil Coating into a wand, changing the built in damage type to the element of the oil. Only works with oils that change the damage type. Does not consume the oil. | G97: =IFERROR(__xludf.DUMMYFUNCTION("""COMPUTED_VALUE"""),"") | H97: =IFERROR(__xludf.DUMMYFUNCTION("""COMPUTED_VALUE"""),"") | I97: =IFERROR(__xludf.DUMMYFUNCTION("""COMPUTED_VALUE"""),"") | J97: =IFERROR(__xludf.DUMMYFUNCTION("""COMPUTED_VALUE"""),"") | K97: =IFERROR(__xludf.DUMMYFUNCTION("""COMPUTED_VALUE"""),"") | L97: =IFERROR(__xludf.DUMMYFUNCTION("""COMPUTED_VALUE"""),"")
B98: =IFERROR(__xludf.DUMMYFUNCTION("""COMPUTED_VALUE"""),"Castling") -> Castling | D98: =IFERROR(__xludf.DUMMYFUNCTION("""COMPUTED_VALUE"""),"Teleport") -> Teleport | E98: =IFERROR(__xludf.DUMMYFUNCTION("""COMPUTED_VALUE"""),"40ft") -> 40ft | F98: =IFERROR(__xludf.DUMMYFUNCTION("""COMPUTED_VALUE"""),"You swap positions with a Rook puppet piece you control.") -> You swap positions with a Rook puppet piece you control. | G98: =IFERROR(__xludf.DUMMYFUNCTION("""COMPUTED_VALUE"""),"") | H98: =IFERROR(__xludf.DUMMYFUNCTION("""COMPUTED_VALUE"""),"1 MP, 0 RP") -> 1 MP, 0 RP | I98: =IFERROR(__xludf.DUMMYFUNCTION("""COMPUTED_VALUE"""),"") | J98: =IFERROR(__xludf.DUMMYFUNCTION("""COMPUTED_VALUE"""),"1 MP") -> 1 MP | K98: =IFERROR(__xludf.DUMMYFUNCTION("""COMPUTED_VALUE"""),"0 RP") -> 0 RP | L98: =IFERROR(__xludf.DUMMYFUNCTION("""COMPUTED_VALUE"""),"")
B99: =IFERROR(__xludf.DUMMYFUNCTION("""COMPUTED_VALUE"""),"Cat Form") -> Cat Form | D99: =IFERROR(__xludf.DUMMYFUNCTION("""COMPUTED_VALUE"""),"Transformation") -> Transformation | E99: =IFERROR(__xludf.DUMMYFUNCTION("""COMPUTED_VALUE"""),"") | F99: =IFERROR(__xludf.DUMMYFUNCTION("""COMPUTED_VALUE"""),"You transform into cat form, reducing your Guard to 0 but increasing your Evasion by +3 and Dodge by +6. Your size is tiny and you are able to occupy the same square as an ally. While in Cat form the only attack you can make is Light Melee Attack. If y"&"ou take damage in Cat Form, you immediately return to your normal form. You can dispel this form for 0 AP or 1 RP.") -> You transform into cat form, reducing your Guard to 0 but increasing your Evasion by +3 and Dodge by +6. Your size is tiny and you are able to occupy the same square as an ally. While in Cat form the only attack you can make is Light Melee Attack. If you take damage in Cat Form, you immediately return to your normal form. You can dispel this form for 0 AP or 1 RP. | G99: =IFERROR(__xludf.DUMMYFUNCTION("""COMPUTED_VALUE"""),"") | H99: =IFERROR(__xludf.DUMMYFUNCTION("""COMPUTED_VALUE"""),"1 RP") -> 1 RP | I99: =IFERROR(__xludf.DUMMYFUNCTION("""COMPUTED_VALUE"""),"") | J99: =IFERROR(__xludf.DUMMYFUNCTION("""COMPUTED_VALUE"""),"") | K99: =IFERROR(__xludf.DUMMYFUNCTION("""COMPUTED_VALUE"""),"1 RP") -> 1 RP | L99: =IFERROR(__xludf.DUMMYFUNCTION("""COMPUTED_VALUE"""),"")
B100: =IFERROR(__xludf.DUMMYFUNCTION("""COMPUTED_VALUE"""),"Catalyze") -> Catalyze | D100: =IFERROR(__xludf.DUMMYFUNCTION("""COMPUTED_VALUE"""),"Poison, Circuit, Stagger, Sunder") -> Poison, Circuit, Stagger, Sunder | E100: =IFERROR(__xludf.DUMMYFUNCTION("""COMPUTED_VALUE"""),"40ft") -> 40ft | F100: =IFERROR(__xludf.DUMMYFUNCTION("""COMPUTED_VALUE"""),"The target must succeed at a Save. On failure, you inflict Stagger II or Sunder II until the end of your next turn.") -> The target must succeed at a Save. On failure, you inflict Stagger II or Sunder II until the end of your next turn. | G100: =IFERROR(__xludf.DUMMYFUNCTION("""COMPUTED_VALUE"""),"Target is afflicted with your Toxic.") -> Target is afflicted with your Toxic. | H100: =IFERROR(__xludf.DUMMYFUNCTION("""COMPUTED_VALUE"""),"1 AP, 1 MP") -> 1 AP, 1 MP | I100: =IFERROR(__xludf.DUMMYFUNCTION("""COMPUTED_VALUE"""),"1 AP") -> 1 AP | J100: =IFERROR(__xludf.DUMMYFUNCTION("""COMPUTED_VALUE"""),"1 MP") -> 1 MP | K100: =IFERROR(__xludf.DUMMYFUNCTION("""COMPUTED_VALUE"""),"") | L100: =IFERROR(__xludf.DUMMYFUNCTION("""COMPUTED_VALUE"""),"")
...

Sheet Breakthroughs
A1: =IFERROR(__xludf.DUMMYFUNCTION("IMPORTRANGE(""https://docs.google.com/spreadsheets/d/1xgDM68xiM34Lb7pPa9X0VaOqdhswjHKkl6KIk-vu_2Q/edit?gid=1937057292#gid=1937057292"", ""Breakthroughs!B1:B"")"),"Name") -> Name | B1: =IFERROR(__xludf.DUMMYFUNCTION("IMPORTRANGE(""https://docs.google.com/spreadsheets/d/1xgDM68xiM34Lb7pPa9X0VaOqdhswjHKkl6KIk-vu_2Q/edit?gid=1937057292#gid=1937057292"", ""Breakthroughs!C1:C"")"),"Cost") -> Cost | C1: =IFERROR(__xludf.DUMMYFUNCTION("IMPORTRANGE(""https://docs.google.com/spreadsheets/d/1xgDM68xiM34Lb7pPa9X0VaOqdhswjHKkl6KIk-vu_2Q/edit?gid=1937057292#gid=1937057292"", ""Breakthroughs!D1:D"")"),"Requirement") -> Requirement | D1: =IFERROR(__xludf.DUMMYFUNCTION("IMPORTRANGE(""https://docs.google.com/spreadsheets/d/1xgDM68xiM34Lb7pPa9X0VaOqdhswjHKkl6KIk-vu_2Q/edit?gid=1937057292#gid=1937057292"", ""Breakthroughs!E1:E"")"),"Description") -> Description
A2: =IFERROR(__xludf.DUMMYFUNCTION("""COMPUTED_VALUE"""),"8 Eyes (Spiderfolk)") -> 8 Eyes (Spiderfolk) | B2: =IFERROR(__xludf.DUMMYFUNCTION("""COMPUTED_VALUE"""),"100") -> 100 | C2: =IFERROR(__xludf.DUMMYFUNCTION("""COMPUTED_VALUE"""),"Must be a spiderfolk.") -> Must be a spiderfolk. | D2: =IFERROR(__xludf.DUMMYFUNCTION("""COMPUTED_VALUE"""),"You may have up to 8 Mystic Eyes instead of the regular 2.") -> You may have up to 8 Mystic Eyes instead of the regular 2.
A3: =IFERROR(__xludf.DUMMYFUNCTION("""COMPUTED_VALUE"""),"Angelblooded (Human) (Restricted)") -> Angelblooded (Human) (Restricted) | B3: =IFERROR(__xludf.DUMMYFUNCTION("""COMPUTED_VALUE"""),"0") -> 0 | C3: =IFERROR(__xludf.DUMMYFUNCTION("""COMPUTED_VALUE"""),"Must be a human and only a human. Requires GM Approval") -> Must be a human and only a human. Requires GM Approval | D3: =IFERROR(__xludf.DUMMYFUNCTION("""COMPUTED_VALUE"""),"You have the blood of angels in you. You may purchase the Angelblooded class.") -> You have the blood of angels in you. You may purchase the Angelblooded class.
A4: =IFERROR(__xludf.DUMMYFUNCTION("""COMPUTED_VALUE"""),"Arachne (Spiderfolk)") -> Arachne (Spiderfolk) | B4: =IFERROR(__xludf.DUMMYFUNCTION("""COMPUTED_VALUE"""),"0") -> 0 | C4: =IFERROR(__xludf.DUMMYFUNCTION("""COMPUTED_VALUE"""),"Must be a spiderfolk. Can only be taken at character creation.") -> Must be a spiderfolk. Can only be taken at character creation. | D4: =IFERROR(__xludf.DUMMYFUNCTION("""COMPUTED_VALUE"""),"You lose your extra arms racial ability. In exchange, you become Large size and your max burden is increased by 2. When attempting to move through 5ft wide spaces, it is considered difficult terrain for you and many humanoid buildings will struggle to acc"&"ommodate you. You also suffer a -10 penalty to swimming checks, but you may climb through your spider climb ability at your normal speed instead of half speed. In addition, you count as mounted for the purposes of abilities that require you to be mounted."&" This does not let you be a mount to other creatures.") -> You lose your extra arms racial ability. In exchange, you become Large size and your max burden is increased by 2. When attempting to move through 5ft wide spaces, it is considered difficult terrain for you and many humanoid buildings will struggle to accommodate you. You also suffer a -10 penalty to swimming checks, but you may climb through your spider climb ability at your normal speed instead of half speed. In addition, you count as mounted for the purposes of abilities that require you to be mounted. This does not let you be a mount to other creatures.
A5: =IFERROR(__xludf.DUMMYFUNCTION("""COMPUTED_VALUE"""),"Become Fire (Salamander)") -> Become Fire (Salamander) | B5: =IFERROR(__xludf.DUMMYFUNCTION("""COMPUTED_VALUE"""),"200") -> 200 | C5: =IFERROR(__xludf.DUMMYFUNCTION("""COMPUTED_VALUE"""),"Must be a Salamander.") -> Must be a Salamander. | D5: =IFERROR(__xludf.DUMMYFUNCTION("""COMPUTED_VALUE"""),"The RP cost of Consume Fire is reduced to 0.") -> The RP cost of Consume Fire is reduced to 0.
A6: =IFERROR(__xludf.DUMMYFUNCTION("""COMPUTED_VALUE"""),"Become Ice (Yuki-Onna)") -> Become Ice (Yuki-Onna) | B6: =IFERROR(__xludf.DUMMYFUNCTION("""COMPUTED_VALUE"""),"200") -> 200 | C6: =IFERROR(__xludf.DUMMYFUNCTION("""COMPUTED_VALUE"""),"Must be a Yuki-Onna.") -> Must be a Yuki-Onna. | D6: =IFERROR(__xludf.DUMMYFUNCTION("""COMPUTED_VALUE"""),"The RP cost of Absorb Ice is reduced to 0 the first time you use it per round. Cost is reset back to 0 when it becomes your turn") -> The RP cost of Absorb Ice is reduced to 0 the first time you use it per round. Cost is reset back to 0 when it becomes your turn
A7: =IFERROR(__xludf.DUMMYFUNCTION("""COMPUTED_VALUE"""),"Become Lightning (Raijin)") -> Become Lightning (Raijin) | B7: =IFERROR(__xludf.DUMMYFUNCTION("""COMPUTED_VALUE"""),"200") -> 200 | C7: =IFERROR(__xludf.DUMMYFUNCTION("""COMPUTED_VALUE"""),"Must be a Raijin Youkai.") -> Must be a Raijin Youkai. | D7: =IFERROR(__xludf.DUMMYFUNCTION("""COMPUTED_VALUE"""),"The RP cost of Consume Lightning is reduced to 0 the first time you use it per round. Cost is reset back to 0 when it becomes your turn. Any Power bonus you gain from using Consume Lightning does not stack.") -> The RP cost of Consume Lightning is reduced to 0 the first time you use it per round. Cost is reset back to 0 when it becomes your turn. Any Power bonus you gain from using Consume Lightning does not stack.
A8: =IFERROR(__xludf.DUMMYFUNCTION("""COMPUTED_VALUE"""),"Become Wind (Sylph)") -> Become Wind (Sylph) | B8: =IFERROR(__xludf.DUMMYFUNCTION("""COMPUTED_VALUE"""),"200") -> 200 | C8: =IFERROR(__xludf.DUMMYFUNCTION("""COMPUTED_VALUE"""),"Must be a Sylph Fae") -> Must be a Sylph Fae | D8: =IFERROR(__xludf.DUMMYFUNCTION("""COMPUTED_VALUE"""),"The RP cost of Consume Wind is reduced to 0 the first time you use it per round. Cost is reset back to 0 when it becomes your turn") -> The RP cost of Consume Wind is reduced to 0 the first time you use it per round. Cost is reset back to 0 when it becomes your turn
A9: =IFERROR(__xludf.DUMMYFUNCTION("""COMPUTED_VALUE"""),"Blend In (Slimefolk)") -> Blend In (Slimefolk) | B9: =IFERROR(__xludf.DUMMYFUNCTION("""COMPUTED_VALUE"""),"200") -> 200 | C9: =IFERROR(__xludf.DUMMYFUNCTION("""COMPUTED_VALUE"""),"Must be a Slimefolk.") -> Must be a Slimefolk. | D9: =IFERROR(__xludf.DUMMYFUNCTION("""COMPUTED_VALUE"""),"You disguise your appearance using magic to be that of another race (and gain a +30 bonus to hide this magical effect from things such as sense magic). This skill does not allow you to change your appearance at will, but instead lets you appear as you wou"&"ld as a different race. You choose this race when this breakthrough is picked up and cannot change it. In addition, the first time you use Slime Body while disguised in this way, it costs 0 RP instead of 1 RP but reveals your actual race. This effect do"&"es not work if the attacker knows that you are a Slimefolk.") -> You disguise your appearance using magic to be that of another race (and gain a +30 bonus to hide this magical effect from things such as sense magic). This skill does not allow you to change your appearance at will, but instead lets you appear as you would as a different race. You choose this race when this breakthrough is picked up and cannot change it. In addition, the first time you use Slime Body while disguised in this way, it costs 0 RP instead of 1 RP but reveals your actual race. This effect does not work if the attacker knows that you are a Slimefolk.
A10: =IFERROR(__xludf.DUMMYFUNCTION("""COMPUTED_VALUE"""),"Blend In II (Slimefolk)") -> Blend In II (Slimefolk) | B10: =IFERROR(__xludf.DUMMYFUNCTION("""COMPUTED_VALUE"""),"25") -> 25 | C10: =IFERROR(__xludf.DUMMYFUNCTION("""COMPUTED_VALUE"""),"Must have Blend In.") -> Must have Blend In. | D10: =IFERROR(__xludf.DUMMYFUNCTION("""COMPUTED_VALUE"""),"You may disguise as a different race in addition to your chosen race during Blend In. You may take this breakthrough multiple times, selecting a new race to disguise as each time.") -> You may disguise as a different race in addition to your chosen race during Blend In. You may take this breakthrough multiple times, selecting a new race to disguise as each time.
A11: =IFERROR(__xludf.DUMMYFUNCTION("""COMPUTED_VALUE"""),"Blessed by Kari (Human)") -> Blessed by Kari (Human) | B11: =IFERROR(__xludf.DUMMYFUNCTION("""COMPUTED_VALUE"""),"100") -> 100 | C11: =IFERROR(__xludf.DUMMYFUNCTION("""COMPUTED_VALUE"""),"Must be a Human.") -> Must be a Human. | D11: =IFERROR(__xludf.DUMMYFUNCTION("""COMPUTED_VALUE"""),"After using Divine Providence you may use it a second time before resting, but the cost increases to 1 RP. This second use must pick a different option then your first one.") -> After using Divine Providence you may use it a second time before resting, but the cost increases to 1 RP. This second use must pick a different option then your first one.
A12: =IFERROR(__xludf.DUMMYFUNCTION("""COMPUTED_VALUE"""),"Bully") -> Bully | B12: =IFERROR(__xludf.DUMMYFUNCTION("""COMPUTED_VALUE"""),"50") -> 50 | C12: =IFERROR(__xludf.DUMMYFUNCTION("""COMPUTED_VALUE"""),"") | D12: =IFERROR(__xludf.DUMMYFUNCTION("""COMPUTED_VALUE"""),"You gain a +5 bonus to intimidation skill checks against targets with less Fitness than you.") -> You gain a +5 bonus to intimidation skill checks against targets with less Fitness than you.
A13: =IFERROR(__xludf.DUMMYFUNCTION("""COMPUTED_VALUE"""),"Celestial Dragon (Ryujin)") -> Celestial Dragon (Ryujin) | B13: =IFERROR(__xludf.DUMMYFUNCTION("""COMPUTED_VALUE"""),"300") -> 300 | C13: =IFERROR(__xludf.DUMMYFUNCTION("""COMPUTED_VALUE"""),"Must be a Ryujin. Can only be taken at character creation.") -> Must be a Ryujin. Can only be taken at character creation. | D13: =IFERROR(__xludf.DUMMYFUNCTION("""COMPUTED_VALUE"""),"You gain controlled Flight up to your speed. If you take damage while flying higher than 5ft above the ground, your altitude drops by 20ft. If this would reduce your altitude to the point where you touch the ground, you become rooted and cannot fly again "&"until the end of your next turn. If the attack that reduced your HP came from a flying creature other than yourself, you do not lose altitude. When you end your turn within 5ft of the ground, Flight ends.") -> You gain controlled Flight up to your speed. If you take damage while flying higher than 5ft above the ground, your altitude drops by 20ft. If this would reduce your altitude to the point where you touch the ground, you become rooted and cannot fly again until the end of your next turn. If the attack that reduced your HP came from a flying creature other than yourself, you do not lose altitude. When you end your turn within 5ft of the ground, Flight ends.
A14: =IFERROR(__xludf.DUMMYFUNCTION("""COMPUTED_VALUE"""),"Combat Doggy (Cu Sith)") -> Combat Doggy (Cu Sith) | B14: =IFERROR(__xludf.DUMMYFUNCTION("""COMPUTED_VALUE"""),"100") -> 100 | C14: =IFERROR(__xludf.DUMMYFUNCTION("""COMPUTED_VALUE"""),"Must be a Cu Sith.") -> Must be a Cu Sith. | D14: =IFERROR(__xludf.DUMMYFUNCTION("""COMPUTED_VALUE"""),"You may use abilities like normal while in Dog Form and may use One-Handed weapon. Any abilities that require a specific armor or other specific physical requirements still cannot be used. Your Dog Form no longer breaks upon taking damage.") -> You may use abilities like normal while in Dog Form and may use One-Handed weapon. Any abilities that require a specific armor or other specific physical requirements still cannot be used. Your Dog Form no longer breaks upon taking damage.
A15: =IFERROR(__xludf.DUMMYFUNCTION("""COMPUTED_VALUE"""),"Combat Kitty (Cait Sith)") -> Combat Kitty (Cait Sith) | B15: =IFERROR(__xludf.DUMMYFUNCTION("""COMPUTED_VALUE"""),"100") -> 100 | C15: =IFERROR(__xludf.DUMMYFUNCTION("""COMPUTED_VALUE"""),"Must be a Cait Sith.") -> Must be a Cait Sith. | D15: =IFERROR(__xludf.DUMMYFUNCTION("""COMPUTED_VALUE"""),"You may use abilities like normal while in cat form and may use One-Handed weapon. Any abilities that require a specific armor or other specific physical requirements still cannot be used. Your cat form no longer breaks on damage.") -> You may use abilities like normal while in cat form and may use One-Handed weapon. Any abilities that require a specific armor or other specific physical requirements still cannot be used. Your cat form no longer breaks on damage.
A16: =IFERROR(__xludf.DUMMYFUNCTION("""COMPUTED_VALUE"""),"Curse of Vampirism") -> Curse of Vampirism | B16: =IFERROR(__xludf.DUMMYFUNCTION("""COMPUTED_VALUE"""),"300") -> 300 | C16: =IFERROR(__xludf.DUMMYFUNCTION("""COMPUTED_VALUE"""),"Must be taken at character creation or after being killed by a vampire's bite.") -> Must be taken at character creation or after being killed by a vampire's bite. | D16: =IFERROR(__xludf.DUMMYFUNCTION("""COMPUTED_VALUE"""),"You rise as a vampire, an immortal creature that feeds on the blood of living creatures and immediately gain the Vampire racial style class and its key ability. Your race changes to ‘Vampire’, but you keep the benefits of your previous race. As a vampire,"&" you no longer age and your physical appearance changes slightly. Your skin becomes more pale and you grow a pair of fangs. You still need to eat, drink and breathe as normal. A vampire’s spirit core is cracked, making it difficult for it to regenerate ma"&"na naturally and requiring it to obtain it from other creatures. You no longer regenerate mana from eating (including potions), resting and can no longer use the Draw Mana encounter conclusion action. You still recover full mana at the start of a new arc."&" You are weak to sunlight. Every round you spend in sunlight without proper protection you take 10 true damage and your maximum HP is lowered by 10. Your maximum HP remains lowered until you finish a rest. You may carry a parasol or similar object in one "&"hand to protect yourself from the sun and can do so even in combat. In addition to these drawbacks, you no longer receive Wounds unless the damage that reduced your HP to 0 was fire, holy or true damage. You also gain 60ft Darkvision. Darkvision lets you "&"see in total darkness, even if there's no source of light.") -> You rise as a vampire, an immortal creature that feeds on the blood of living creatures and immediately gain the Vampire racial style class and its key ability. Your race changes to ‘Vampire’, but you keep the benefits of your previous race. As a vampire, you no longer age and your physical appearance changes slightly. Your skin becomes more pale and you grow a pair of fangs. You still need to eat, drink and breathe as normal. A vampire’s spirit core is cracked, making it difficult for it to regenerate mana naturally and requiring it to obtain it from other creatures. You no longer regenerate mana from eating (including potions), resting and can no longer use the Draw Mana encounter conclusion action. You still recover full mana at the start of a new arc. You are weak to sunlight. Every round you spend in sunlight without proper protection you take 10 true damage and your maximum HP is lowered by 10. Your maximum HP remains lowered until you finish a rest. You may carry a parasol or similar object in one hand to protect yourself from the sun and can do so even in combat. In addition to these drawbacks, you no longer receive Wounds unless the damage that reduced your HP to 0 was fire, holy or true damage. You also gain 60ft Darkvision. Darkvision lets you see in total darkness, even if there's no source of light.
A17: =IFERROR(__xludf.DUMMYFUNCTION("""COMPUTED_VALUE"""),"Deep Connection") -> Deep Connection | B17: =IFERROR(__xludf.DUMMYFUNCTION("""COMPUTED_VALUE"""),"50") -> 50 | C17: =IFERROR(__xludf.DUMMYFUNCTION("""COMPUTED_VALUE"""),"Cavalier mastered.") -> Cavalier mastered. | D17: =IFERROR(__xludf.DUMMYFUNCTION("""COMPUTED_VALUE"""),"You may command your mount to move and attack even if you're not mounted on it. This still using AP, Mana etc like normal as if you were mounted.") -> You may command your mount to move and attack even if you're not mounted on it. This still using AP, Mana etc like normal as if you were mounted.
A18: =IFERROR(__xludf.DUMMYFUNCTION("""COMPUTED_VALUE"""),"Deus Ex Machina") -> Deus Ex Machina | B18: =IFERROR(__xludf.DUMMYFUNCTION("""COMPUTED_VALUE"""),"600") -> 600 | C18: =IFERROR(__xludf.DUMMYFUNCTION("""COMPUTED_VALUE"""),"") | D18: =IFERROR(__xludf.DUMMYFUNCTION("""COMPUTED_VALUE"""),"The first time you would die from a mortal wound at Encounter Conclusion, the mortal wound is removed and you instead receive a normal injury. The benefit of this breakthrough is then lost and you may not choose this breakthrough again after.") -> The first time you would die from a mortal wound at Encounter Conclusion, the mortal wound is removed and you instead receive a normal injury. The benefit of this breakthrough is then lost and you may not choose this breakthrough again after.
A19: =IFERROR(__xludf.DUMMYFUNCTION("""COMPUTED_VALUE"""),"Divine Luck I") -> Divine Luck I | B19: =IFERROR(__xludf.DUMMYFUNCTION("""COMPUTED_VALUE"""),"300") -> 300 | C19: =IFERROR(__xludf.DUMMYFUNCTION("""COMPUTED_VALUE"""),"") | D19: =IFERROR(__xludf.DUMMYFUNCTION("""COMPUTED_VALUE"""),"Once per rest, you may roll an additional dice when making a check and take the higher result.") -> Once per rest, you may roll an additional dice when making a check and take the higher result.
A20: =IFERROR(__xludf.DUMMYFUNCTION("""COMPUTED_VALUE"""),"Divine Luck II") -> Divine Luck II | B20: =IFERROR(__xludf.DUMMYFUNCTION("""COMPUTED_VALUE"""),"600") -> 600 | C20: =IFERROR(__xludf.DUMMYFUNCTION("""COMPUTED_VALUE"""),"Must have purchased Divine Luck I.") -> Must have purchased Divine Luck I. | D20: =IFERROR(__xludf.DUMMYFUNCTION("""COMPUTED_VALUE"""),"Once per arc, you may choose to automatically succeed on a check (if success is possible).") -> Once per arc, you may choose to automatically succeed on a check (if success is possible).
